Workbook

Sheet Read Me
B2: Bond Portfolio Model
B3: version 2.2
B5: Objective
C6: This model is built for Goldman Sachs, with the objective to look across various fixed income asset classes (munis, corporates, treasuries, etc.) and come up with an optimized, laddered portfolio based on client’s federal and state tax rates.
C7: And then optimize over time based on changes in the market, clients cost basis, short term versus long term tax implications.
B9: Investor Input
C10: The Investor Input tab is where the client or the investor specifies some of the basic details like their state of residence, tax bracket, amount to invest, and investment horizon
B12: Bond Portfolio Scenarios - High Yield Scenario, Secure Bonds Scenario, and Stable Income Scenario
C13: Each scenario tab is built to present a list of bonds curated and personalized based on client's inputs on the Investor Input tab.
C14: The client can go into each tab and go down the list to pick the number of bonds to purchase for each CUSIP. The cells meant to be updated are shaded yellow (column M).
C15: Note that the purchase quantity entered in column M cannot be less than the minimum quantity specified within parantheses in column L. The field should be left blank to exclude the bond from purchase.
C16: Also note that the total price at the bottom of the list cannot exceed the amount entered in the Investor Input tab. If this happens the cell will turn red to indicate the error.
B18: YTM Analysis
C19: The YTM Analysis tab presents a comprehensive Pre-Tax /After-Tax Yield to Maturity comparison for each scenario. Toggle between Pre-/After-Tax options from the dropdown to compare the YTM changes for each portfolio.
C20: The table at the bottom of the tab lists the Y/Y yields while the average yield and average credit rating of each portfolio is listed on the bottom right.
B22: Cash Flow Analysis
C23: The Cash Flow Analysis is meant to present a comparison of coupon payments by month for each scenario. This provides the client with an option to take a laddered approach when picking the bonds for their portfolio.
C24: The client can adjust their portfolio on the scenario tabs and then go to the Cash Flow Analysis tab to compare the month over month income in any given year.
C25: Similar to the YTM Analysis tab, client can toggle between Pre-/After-Tax options from the dropdown to compare the YTM changes for each portfolio.
B27: Master Bond List (hidden)
C28: This is the master list of all the relevant bonds.
B30: Misc Lists (hidden)
C31: List of user input validation

Sheet Investor Input
B2: Investor Input
B3: State of Residence: | C3: New Jersey | D3: =VLOOKUP('Investor Input'!C3,'Misc Lists'!A2:B51,2,TRUE) -> NJ
B4: Federal Tax Bracket: | C4: 0.37
B5: State Tax Bracket: | C5: 0.09
B6: Amount to Invest ($) | C6: 1000000
B7: Investment Horizon (Years): | C7: 5

Sheet High Yield Scenario
A1: {=MID(CELL("filename",A1),FIND("]",CELL("filename",A1))+1,255)} -> High Yield Scenario
B2: General Bond Information | M2: Purchase Information | V2: Valuation on Maturity | Y2: Yearly Cash Flow Information | AC2: Rating Info
B3: CUSIP | C3: State | D3: Description | E3: Type | F3: Cpn | G3: Maturity Date | H3: Mdy | I3: S&P | J3: Price | K3: YTM | L3: Qty (Min) | M3: Purchase Qty | N3: Total Price | O3: Portfolio Pct | P3: Annual Coupon | Q3: Purchase Date | R3: Yrs to Maturity | S3: Duration Yrs | T3: YTM At Buy | U3: After-Tax YTM | V3: Price | W3: Interest Earned | X3: Total Return | Y3: 1st Coupon Mth | Z3: 2nd Coupon Month | AA3: Coupon Amt | AB3: After-Tax Coupon Amt | AC3: Mdy Rating | AD3: Mdy Score | AE3: S&P Rating | AF3: S&P Score
B4: {=_xlfn.TAKE(_xlfn._xlws.SORT(_xlfn._xlws.FILTER(_xlfn._xlws.FILTER(Master_Bond_List[], ('Investor Input'!C6 >= IFERROR(VALUE(MID(Master_Bond_List[Quantity Ask(min)], FIND("(", Master_Bond_List[Quantity Ask(min)]) + 1, LEN(Master_Bond_List[Quantity Ask(min)]) - FIND("(", Master_Bond_List[Quantity Ask(min)])-1)), 1)*1000)*((Master_Bond_List[Maturity Date]-TODAY()) < 'Investor Input'!C7*365)*(Master_Bond_List[Type] = "Muni")*(Master_Bond_List[State]='Investor Input'!D3) + ('Investor Input'!C6 >= IFERROR(VALUE(MID(Master_Bond_List[Quantity Ask(min)], FIND("(", Master_Bond_List[Quantity Ask(min)]) + 1, LEN(Master_Bond_List[Quantity Ask(min)]) - FIND("(", Master_Bond_List[Quantity Ask(min)])-1)), 1)*1000)*((Master_Bond_List[Maturity Date]-TODAY()) < 'Investor Input'!C7*365)*(Master_Bond_List[Type] = "Corp")), {1,1,1,1,1,1,0,1,1,0,1,0,0,1,0,0,1,0}), {4,10}, {1,-1}),500)} -> 06745NUM6 | C4: N/A | D4: BARCLAYS BANK PLC SER A MTN 6.25000% 11/03/2028 | E4: Corp | F4: 6.25 | G4: 47060 | H4: A1 | I4: A+ | J4: 100.888 | K4: 5.972 | L4: 1(1) | N4: =IF(AND(M4<>"", M4<>0), IF(L4 <> "N/A", IF(M4>=VALUE(LEFT(L4, FIND("(", L4)-1)), J4*10*M4, 1000*M4), 1000*M4), "") | O4: =IF(AND(M4<>"",M4<>0),N4/$N$505, "") | P4: =IF(AND(M4<>"", M4<>0), F4*1000/100, "") | Q4: =IF(AND(M4<>"", M4<>0), NOW(), "") | R4: =IF(AND(M4<>"", M4<>0), ROUND((G4 - Q4)/365, 0), "") | S4: =IF(AND(M4<>"",M4<>0),MDURATION(Q4,G4,F4/100,K4/100,2), "") | T4: =IF(AND(M4<>"",M4<>0),YIELD(Q4,G4,F4/100,N4/(M4*10),100,2),"") | U4: =IF(AND(M4<>"",M4<>0), IF(E4 = "Muni", T4, IF(E4="Corp", T4*(1 -'Investor Input'!$C$4-'Investor Input'!$C$5), T4*(1 -'Investor Input'!$C$4))), T4) | V4: =IF(AND(M4<>"",M4<>0),(FV(K4/(2*100),(G4-Q4)*2/365, F4*1000/(2*100), -N4/M4))*M4, "") | W4: =IF(AND(M4<>"",M4<>0),V4-N4,"") | X4: =IF(AND(M4<>"",M4<>0),W4/N4,"") | Y4: =IF(AND(M4<>"", M4<>0), MONTH(G4), "") | Z4: =IF(AND(M4<>"", M4<>0), MONTH(EDATE(G4, 6)), "") | AA4: =IF(AND(M4<>"", M4<>0), F4*1000*M4/(100*2), "") | AB4: =IF(AND(AA4<>"",AA4<>0), IF(E4="Muni", AA4, IF(E4 = "Corp", (1-'Investor Input'!$C$4-'Investor Input'!$C$5)*AA4, (1-'Investor Input'!$C$4)*AA4)), AA4) | AC4: =IF(AND(M4<>"", M4<>0), H4, "") | AD4: =IF(AND(M4<>"", M4<>0), N4/$N$505*MATCH(AC4,'Misc Lists'!$K$2:$K$25,0), "") | AE4: =IF(AND(M4<>"", M4<>0), I4, "") | AF4: =IF(AND(M4<>"", M4<>0), N4/$N$505*MATCH(AE4,'Misc Lists'!$L$2:$L$25,0), "")
B5: 06055JFF1 | C5: N/A | D5: BANK AMERICA CORP SER P MTN 5.50000% 07/23/2029 | E5: Corp | F5: 5.5 | G5: 47322 | H5: A1 | I5: A- | J5: 100.407 | K5: 5.392 | L5: 3(3) | N5: =IF(AND(M5<>"", M5<>0), IF(L5 <> "N/A", IF(M5>=VALUE(LEFT(L5, FIND("(", L5)-1)), J5*10*M5, 1000*M5), 1000*M5), "") | O5: =IF(AND(M5<>"",M5<>0),N5/$N$505, "") | P5: =IF(AND(M5<>"", M5<>0), F5*1000/100, "") | Q5: =IF(AND(M5<>"", M5<>0), NOW(), "") | R5: =IF(AND(M5<>"", M5<>0), ROUND((G5 - Q5)/365, 0), "") | S5: =IF(AND(M5<>"",M5<>0),MDURATION(Q5,G5,F5/100,K5/100,2), "") | T5: =IF(AND(M5<>"",M5<>0),YIELD(Q5,G5,F5/100,N5/(M5*10),100,2),"") | U5: =IF(AND(M5<>"",M5<>0), IF(E5 = "Muni", T5, IF(E5="Corp", T5*(1 -'Investor Input'!$C$4-'Investor Input'!$C$5), T5*(1 -'Investor Input'!$C$4))), T5) | V5: =IF(AND(M5<>"",M5<>0),(FV(K5/(2*100),(G5-Q5)*2/365, F5*1000/(2*100), -N5/M5))*M5, "") | W5: =IF(AND(M5<>"",M5<>0),V5-N5,"") | X5: =IF(AND(M5<>"",M5<>0),W5/N5,"") | Y5: =IF(AND(M5<>"", M5<>0), MONTH(G5), "") | Z5: =IF(AND(M5<>"", M5<>0), MONTH(EDATE(G5, 6)), "") | AA5: =IF(AND(M5<>"", M5<>0), F5*1000*M5/(100*2), "") | AB5: =IF(AND(AA5<>"",AA5<>0), IF(E5="Muni", AA5, IF(E5 = "Corp", (1-'Investor Input'!$C$4-'Investor Input'!$C$5)*AA5, (1-'Investor Input'!$C$4)*AA5)), AA5) | AC5: =IF(AND(M5<>"", M5<>0), H5, "") | AD5: =IF(AND(M5<>"", M5<>0), N5/$N$505*MATCH(AC5,'Misc Lists'!$K$2:$K$25,0), "") | AE5: =IF(AND(M5<>"", M5<>0), I5, "") | AF5: =IF(AND(M5<>"", M5<>0), N5/$N$505*MATCH(AE5,'Misc Lists'!$L$2:$L$25,0), "")
B6: 89114XD67 | C6: N/A | D6: TORONTO DOMINION BK ONT SER D MTN 5.30000% 01/03/2028 | E6: Corp | F6: 5.3 | G6: 46755 | H6: A2 | I6: A- | J6: 99.937 | K6: 5.324 | L6: 15(1) | M6: 15 | N6: =IF(AND(M6<>"", M6<>0), IF(L6 <> "N/A", IF(M6>=VALUE(LEFT(L6, FIND("(", L6)-1)), J6*10*M6, 1000*M6), 1000*M6), "") -> 14990.55 | O6: =IF(AND(M6<>"",M6<>0),N6/$N$505, "") -> 0.014989935 | P6: =IF(AND(M6<>"", M6<>0), F6*1000/100, "") -> 53 | Q6: =IF(AND(M6<>"", M6<>0), NOW(), "") -> 45791.491 | R6: =IF(AND(M6<>"", M6<>0), ROUND((G6 - Q6)/365, 0), "") -> 3 | S6: =IF(AND(M6<>"",M6<>0),MDURATION(Q6,G6,F6/100,K6/100,2), "") -> 2.3854552 | T6: =IF(AND(M6<>"",M6<>0),YIELD(Q6,G6,F6/100,N6/(M6*10),100,2),"") -> 0.053230872 | U6: =IF(AND(M6<>"",M6<>0), IF(E6 = "Muni", T6, IF(E6="Corp", T6*(1 -'Investor Input'!$C$4-'Investor Input'!$C$5), T6*(1 -'Investor Input'!$C$4))), T6) -> 0.028744671 | V6: =IF(AND(M6<>"",M6<>0),(FV(K6/(2*100),(G6-Q6)*2/365, F6*1000/(2*100), -N6/M6))*M6, "") -> 14999.204 | W6: =IF(AND(M6<>"",M6<>0),V6-N6,"") -> 8.6543994 | X6: =IF(AND(M6<>"",M6<>0),W6/N6,"") -> 0.00057732367 | Y6: =IF(AND(M6<>"", M6<>0), MONTH(G6), "") -> 1 | Z6: =IF(AND(M6<>"", M6<>0), MONTH(EDATE(G6, 6)), "") -> 7 | AA6: =IF(AND(M6<>"", M6<>0), F6*1000*M6/(100*2), "") -> 397.5 | AB6: =IF(AND(AA6<>"",AA6<>0), IF(E6="Muni", AA6, IF(E6 = "Corp", (1-'Investor Input'!$C$4-'Investor Input'!$C$5)*AA6, (1-'Investor Input'!$C$4)*AA6)), AA6) -> 214.65 | AC6: =IF(AND(M6<>"", M6<>0), H6, "") -> A2 | AD6: =IF(AND(M6<>"", M6<>0), N6/$N$505*MATCH(AC6,'Misc Lists'!$K$2:$K$25,0), "") -> 0.10492954 | AE6: =IF(AND(M6<>"", M6<>0), I6, "") -> A- | AF6: =IF(AND(M6<>"", M6<>0), N6/$N$505*MATCH(AE6,'Misc Lists'!$L$2:$L$25,0), "") -> 0.11991948
B7: 89114XDN0 | C7: N/A | D7: TORONTO DOMINION BK ONT SER D MTN 5.25000% 01/30/2029 | E7: Corp | F7: 5.25 | G7: 47148 | H7: A2 | I7: A- | J7: 99.995 | K7: 5.251 | L7: 41(25) | N7: =IF(AND(M7<>"", M7<>0), IF(L7 <> "N/A", IF(M7>=VALUE(LEFT(L7, FIND("(", L7)-1)), J7*10*M7, 1000*M7), 1000*M7), "") | O7: =IF(AND(M7<>"",M7<>0),N7/$N$505, "") | P7: =IF(AND(M7<>"", M7<>0), F7*1000/100, "") | Q7: =IF(AND(M7<>"", M7<>0), NOW(), "") | R7: =IF(AND(M7<>"", M7<>0), ROUND((G7 - Q7)/365, 0), "") | S7: =IF(AND(M7<>"",M7<>0),MDURATION(Q7,G7,F7/100,K7/100,2), "") | T7: =IF(AND(M7<>"",M7<>0),YIELD(Q7,G7,F7/100,N7/(M7*10),100,2),"") | U7: =IF(AND(M7<>"",M7<>0), IF(E7 = "Muni", T7, IF(E7="Corp", T7*(1 -'Investor Input'!$C$4-'Investor Input'!$C$5), T7*(1 -'Investor Input'!$C$4))), T7) | V7: =IF(AND(M7<>"",M7<>0),(FV(K7/(2*100),(G7-Q7)*2/365, F7*1000/(2*100), -N7/M7))*M7, "") | W7: =IF(AND(M7<>"",M7<>0),V7-N7,"") | X7: =IF(AND(M7<>"",M7<>0),W7/N7,"") | Y7: =IF(AND(M7<>"", M7<>0), MONTH(G7), "") | Z7: =IF(AND(M7<>"", M7<>0), MONTH(EDATE(G7, 6)), "") | AA7: =IF(AND(M7<>"", M7<>0), F7*1000*M7/(100*2), "") | AB7: =IF(AND(AA7<>"",AA7<>0), IF(E7="Muni", AA7, IF(E7 = "Corp", (1-'Investor Input'!$C$4-'Investor Input'!$C$5)*AA7, (1-'Investor Input'!$C$4)*AA7)), AA7) | AC7: =IF(AND(M7<>"", M7<>0), H7, "") | AD7: =IF(AND(M7<>"", M7<>0), N7/$N$505*MATCH(AC7,'Misc Lists'!$K$2:$K$25,0), "") | AE7: =IF(AND(M7<>"", M7<>0), I7, "") | AF7: =IF(AND(M7<>"", M7<>0), N7/$N$505*MATCH(AE7,'Misc Lists'!$L$2:$L$25,0), "")
B8: 00828EEX3 | C8: N/A | D8: AFRICAN DEV BK MTN SB NTS BE NOTE 5.50000% 11/10/2028 | E8: Corp | F8: 5.5 | G8: 47067 | H8: AAA | I8: AAA | J8: 100.918 | K8: 5.209 | L8: 316(100) | N8: =IF(AND(M8<>"", M8<>0), IF(L8 <> "N/A", IF(M8>=VALUE(LEFT(L8, FIND("(", L8)-1)), J8*10*M8, 1000*M8), 1000*M8), "") | O8: =IF(AND(M8<>"",M8<>0),N8/$N$505, "") | P8: =IF(AND(M8<>"", M8<>0), F8*1000/100, "") | Q8: =IF(AND(M8<>"", M8<>0), NOW(), "") | R8: =IF(AND(M8<>"", M8<>0), ROUND((G8 - Q8)/365, 0), "") | S8: =IF(AND(M8<>"",M8<>0),MDURATION(Q8,G8,F8/100,K8/100,2), "") | T8: =IF(AND(M8<>"",M8<>0),YIELD(Q8,G8,F8/100,N8/(M8*10),100,2),"") | U8: =IF(AND(M8<>"",M8<>0), IF(E8 = "Muni", T8, IF(E8="Corp", T8*(1 -'Investor Input'!$C$4-'Investor Input'!$C$5), T8*(1 -'Investor Input'!$C$4))), T8) | V8: =IF(AND(M8<>"",M8<>0),(FV(K8/(2*100),(G8-Q8)*2/365, F8*1000/(2*100), -N8/M8))*M8, "") | W8: =IF(AND(M8<>"",M8<>0),V8-N8,"") | X8: =IF(AND(M8<>"",M8<>0),W8/N8,"") | Y8: =IF(AND(M8<>"", M8<>0), MONTH(G8), "") | Z8: =IF(AND(M8<>"", M8<>0), MONTH(EDATE(G8, 6)), "") | AA8: =IF(AND(M8<>"", M8<>0), F8*1000*M8/(100*2), "") | AB8: =IF(AND(AA8<>"",AA8<>0), IF(E8="Muni", AA8, IF(E8 = "Corp", (1-'Investor Input'!$C$4-'Investor Input'!$C$5)*AA8, (1-'Investor Input'!$C$4)*AA8)), AA8) | AC8: =IF(AND(M8<>"", M8<>0), H8, "") | AD8: =IF(AND(M8<>"", M8<>0), N8/$N$505*MATCH(AC8,'Misc Lists'!$K$2:$K$25,0), "") | AE8: =IF(AND(M8<>"", M8<>0), I8, "") | AF8: =IF(AND(M8<>"", M8<>0), N8/$N$505*MATCH(AE8,'Misc Lists'!$L$2:$L$25,0), "")
B9: 22552XXR9 | C9: N/A | D9: UBS AG LONDON BRANCHMTN 2.00000% 10/29/2029 ISIN #US22552XXR96 | E9: Corp | F9: 2 | G9: 47420 | H9: AA2 | I9: -- | J9: 86.968 | K9: 5.203 | L9: 75(5) | M9: 100 | N9: =IF(AND(M9<>"", M9<>0), IF(L9 <> "N/A", IF(M9>=VALUE(LEFT(L9, FIND("(", L9)-1)), J9*10*M9, 1000*M9), 1000*M9), "") -> 86968 | O9: =IF(AND(M9<>"",M9<>0),N9/$N$505, "") -> 0.08696443 | P9: =IF(AND(M9<>"", M9<>0), F9*1000/100, "") -> 20 | Q9: =IF(AND(M9<>"", M9<>0), NOW(), "") -> 45791.491 | R9: =IF(AND(M9<>"", M9<>0), ROUND((G9 - Q9)/365, 0), "") -> 4 | S9: =IF(AND(M9<>"",M9<>0),MDURATION(Q9,G9,F9/100,K9/100,2), "") -> 4.1605769 | T9: =IF(AND(M9<>"",M9<>0),YIELD(Q9,G9,F9/100,N9/(M9*10),100,2),"") -> 0.053218215 | U9: =IF(AND(M9<>"",M9<>0), IF(E9 = "Muni", T9, IF(E9="Corp", T9*(1 -'Investor Input'!$C$4-'Investor Input'!$C$5), T9*(1 -'Investor Input'!$C$4))), T9) -> 0.028737836 | V9: =IF(AND(M9<>"",M9<>0),(FV(K9/(2*100),(G9-Q9)*2/365, F9*1000/(2*100), -N9/M9))*M9, "") -> 99466.976 | W9: =IF(AND(M9<>"",M9<>0),V9-N9,"") -> 12498.976 | X9: =IF(AND(M9<>"",M9<>0),W9/N9,"") -> 0.14371926 | Y9: =IF(AND(M9<>"", M9<>0), MONTH(G9), "") -> 10 | Z9: =IF(AND(M9<>"", M9<>0), MONTH(EDATE(G9, 6)), "") -> 4 | AA9: =IF(AND(M9<>"", M9<>0), F9*1000*M9/(100*2), "") -> 1000 | AB9: =IF(AND(AA9<>"",AA9<>0), IF(E9="Muni", AA9, IF(E9 = "Corp", (1-'Investor Input'!$C$4-'Investor Input'!$C$5)*AA9, (1-'Investor Input'!$C$4)*AA9)), AA9) -> 540 | AC9: =IF(AND(M9<>"", M9<>0), H9, "") -> AA2 | AD9: =IF(AND(M9<>"", M9<>0), N9/$N$505*MATCH(AC9,'Misc Lists'!$K$2:$K$25,0), "") -> 0.34785772 | AE9: =IF(AND(M9<>"", M9<>0), I9, "") -> -- | AF9: =IF(AND(M9<>"", M9<>0), N9/$N$505*MATCH(AE9,'Misc Lists'!$L$2:$L$25,0), "") -> 2.0001819
B10: 13607XVD6 | C10: N/A | D10: CANADIAN IMPERIAL BKCOMM MTN 5.25000% 01/30/2030 | E10: Corp | F10: 5.25 | G10: 47513 | H10: A2 | I10: A- | J10: 100.379 | K10: 5.16 | L10: 407(1) | N10: =IF(AND(M10<>"", M10<>0), IF(L10 <> "N/A", IF(M10>=VALUE(LEFT(L10, FIND("(", L10)-1)), J10*10*M10, 1000*M10), 1000*M10), "") | O10: =IF(AND(M10<>"",M10<>0),N10/$N$505, "") | P10: =IF(AND(M10<>"", M10<>0), F10*1000/100, "") | Q10: =IF(AND(M10<>"", M10<>0), NOW(), "") | R10: =IF(AND(M10<>"", M10<>0), ROUND((G10 - Q10)/365, 0), "") | S10: =IF(AND(M10<>"",M10<>0),MDURATION(Q10,G10,F10/100,K10/100,2), "") | T10: =IF(AND(M10<>"",M10<>0),YIELD(Q10,G10,F10/100,N10/(M10*10),100,2),"") | U10: =IF(AND(M10<>"",M10<>0), IF(E10 = "Muni", T10, IF(E10="Corp", T10*(1 -'Investor Input'!$C$4-'Investor Input'!$C$5), T10*(1 -'Investor Input'!$C$4))), T10) | V10: =IF(AND(M10<>"",M10<>0),(FV(K10/(2*100),(G10-Q10)*2/365, F10*1000/(2*100), -N10/M10))*M10, "") | W10: =IF(AND(M10<>"",M10<>0),V10-N10,"") | X10: =IF(AND(M10<>"",M10<>0),W10/N10,"") | Y10: =IF(AND(M10<>"", M10<>0), MONTH(G10), "") | Z10: =IF(AND(M10<>"", M10<>0), MONTH(EDATE(G10, 6)), "") | AA10: =IF(AND(M10<>"", M10<>0), F10*1000*M10/(100*2), "") | AB10: =IF(AND(AA10<>"",AA10<>0), IF(E10="Muni", AA10, IF(E10 = "Corp", (1-'Investor Input'!$C$4-'Investor Input'!$C$5)*AA10, (1-'Investor Input'!$C$4)*AA10)), AA10) | AC10: =IF(AND(M10<>"", M10<>0), H10, "") | AD10: =IF(AND(M10<>"", M10<>0), N10/$N$505*MATCH(AC10,'Misc Lists'!$K$2:$K$25,0), "") | AE10: =IF(AND(M10<>"", M10<>0), I10, "") | AF10: =IF(AND(M10<>"", M10<>0), N10/$N$505*MATCH(AE10,'Misc Lists'!$L$2:$L$25,0), "")
B11: 46514Y8A8 | C11: N/A | D11: ISRAEL ST BOND 5.37500% 02/19/2030 | E11: Corp | F11: 5.375 | G11: 47533 | H11: BAA1 | I11: A | J11: 100.958 | K11: 5.152 | L11: 1,000(200) | N11: =IF(AND(M11<>"", M11<>0), IF(L11 <> "N/A", IF(M11>=VALUE(LEFT(L11, FIND("(", L11)-1)), J11*10*M11, 1000*M11), 1000*M11), "") | O11: =IF(AND(M11<>"",M11<>0),N11/$N$505, "") | P11: =IF(AND(M11<>"", M11<>0), F11*1000/100, "") | Q11: =IF(AND(M11<>"", M11<>0), NOW(), "") | R11: =IF(AND(M11<>"", M11<>0), ROUND((G11 - Q11)/365, 0), "") | S11: =IF(AND(M11<>"",M11<>0),MDURATION(Q11,G11,F11/100,K11/100,2), "") | T11: =IF(AND(M11<>"",M11<>0),YIELD(Q11,G11,F11/100,N11/(M11*10),100,2),"") | U11: =IF(AND(M11<>"",M11<>0), IF(E11 = "Muni", T11, IF(E11="Corp", T11*(1 -'Investor Input'!$C$4-'Investor Input'!$C$5), T11*(1 -'Investor Input'!$C$4))), T11) | V11: =IF(AND(M11<>"",M11<>0),(FV(K11/(2*100),(G11-Q11)*2/365, F11*1000/(2*100), -N11/M11))*M11, "") | W11: =IF(AND(M11<>"",M11<>0),V11-N11,"") | X11: =IF(AND(M11<>"",M11<>0),W11/N11,"") | Y11: =IF(AND(M11<>"", M11<>0), MONTH(G11), "") | Z11: =IF(AND(M11<>"", M11<>0), MONTH(EDATE(G11, 6)), "") | AA11: =IF(AND(M11<>"", M11<>0), F11*1000*M11/(100*2), "") | AB11: =IF(AND(AA11<>"",AA11<>0), IF(E11="Muni", AA11, IF(E11 = "Corp", (1-'Investor Input'!$C$4-'Investor Input'!$C$5)*AA11, (1-'Investor Input'!$C$4)*AA11)), AA11) | AC11: =IF(AND(M11<>"", M11<>0), H11, "") | AD11: =IF(AND(M11<>"", M11<>0), N11/$N$505*MATCH(AC11,'Misc Lists'!$K$2:$K$25,0), "") | AE11: =IF(AND(M11<>"", M11<>0), I11, "") | AF11: =IF(AND(M11<>"", M11<>0), N11/$N$505*MATCH(AE11,'Misc Lists'!$L$2:$L$25,0), "")
B12: 25161FKM9 | C12: N/A | D12: DEUTSCHE BK AG SER E NOTE 5.25000% 02/15/2030 | E12: Corp | F12: 5.25 | G12: 47529 | H12: A1 | I12: A | J12: 100.5 | K12: 5.131 | L12: 73(1) | N12: =IF(AND(M12<>"", M12<>0), IF(L12 <> "N/A", IF(M12>=VALUE(LEFT(L12, FIND("(", L12)-1)), J12*10*M12, 1000*M12), 1000*M12), "") | O12: =IF(AND(M12<>"",M12<>0),N12/$N$505, "") | P12: =IF(AND(M12<>"", M12<>0), F12*1000/100, "") | Q12: =IF(AND(M12<>"", M12<>0), NOW(), "") | R12: =IF(AND(M12<>"", M12<>0), ROUND((G12 - Q12)/365, 0), "") | S12: =IF(AND(M12<>"",M12<>0),MDURATION(Q12,G12,F12/100,K12/100,2), "") | T12: =IF(AND(M12<>"",M12<>0),YIELD(Q12,G12,F12/100,N12/(M12*10),100,2),"") | U12: =IF(AND(M12<>"",M12<>0), IF(E12 = "Muni", T12, IF(E12="Corp", T12*(1 -'Investor Input'!$C$4-'Investor Input'!$C$5), T12*(1 -'Investor Input'!$C$4))), T12) | V12: =IF(AND(M12<>"",M12<>0),(FV(K12/(2*100),(G12-Q12)*2/365, F12*1000/(2*100), -N12/M12))*M12, "") | W12: =IF(AND(M12<>"",M12<>0),V12-N12,"") | X12: =IF(AND(M12<>"",M12<>0),W12/N12,"") | Y12: =IF(AND(M12<>"", M12<>0), MONTH(G12), "") | Z12: =IF(AND(M12<>"", M12<>0), MONTH(EDATE(G12, 6)), "") | AA12: =IF(AND(M12<>"", M12<>0), F12*1000*M12/(100*2), "") | AB12: =IF(AND(AA12<>"",AA12<>0), IF(E12="Muni", AA12, IF(E12 = "Corp", (1-'Investor Input'!$C$4-'Investor Input'!$C$5)*AA12, (1-'Investor Input'!$C$4)*AA12)), AA12) | AC12: =IF(AND(M12<>"", M12<>0), H12, "") | AD12: =IF(AND(M12<>"", M12<>0), N12/$N$505*MATCH(AC12,'Misc Lists'!$K$2:$K$25,0), "") | AE12: =IF(AND(M12<>"", M12<>0), I12, "") | AF12: =IF(AND(M12<>"", M12<>0), N12/$N$505*MATCH(AE12,'Misc Lists'!$L$2:$L$25,0), "")
B13: 842400GQ0 | C13: N/A | D13: SOUTHERN CALIF EDISON CO SER 2019A 4.20000% 03/01/2029 BOND CALL MAKE WHOLE | E13: Corp | F13: 4.2 | G13: 47178 | H13: A2 | I13: A- | J13: 96.697 | K13: 5.13 | L13: 200(1) | M13: 200 | N13: =IF(AND(M13<>"", M13<>0), IF(L13 <> "N/A", IF(M13>=VALUE(LEFT(L13, FIND("(", L13)-1)), J13*10*M13, 1000*M13), 1000*M13), "") -> 193394 | O13: =IF(AND(M13<>"",M13<>0),N13/$N$505, "") -> 0.19338606 | P13: =IF(AND(M13<>"", M13<>0), F13*1000/100, "") -> 42 | Q13: =IF(AND(M13<>"", M13<>0), NOW(), "") -> 45791.491 | R13: =IF(AND(M13<>"", M13<>0), ROUND((G13 - Q13)/365, 0), "") -> 4 | S13: =IF(AND(M13<>"",M13<>0),MDURATION(Q13,G13,F13/100,K13/100,2), "") -> 3.4271848 | T13: =IF(AND(M13<>"",M13<>0),YIELD(Q13,G13,F13/100,N13/(M13*10),100,2),"") -> 0.051672327 | U13: =IF(AND(M13<>"",M13<>0), IF(E13 = "Muni", T13, IF(E13="Corp", T13*(1 -'Investor Input'!$C$4-'Investor Input'!$C$5), T13*(1 -'Investor Input'!$C$4))), T13) -> 0.027903057 | V13: =IF(AND(M13<>"",M13<>0),(FV(K13/(2*100),(G13-Q13)*2/365, F13*1000/(2*100), -N13/M13))*M13, "") -> 199685.17 | W13: =IF(AND(M13<>"",M13<>0),V13-N13,"") -> 6291.1727 | X13: =IF(AND(M13<>"",M13<>0),W13/N13,"") -> 0.03253034 | Y13: =IF(AND(M13<>"", M13<>0), MONTH(G13), "") -> 3 | Z13: =IF(AND(M13<>"", M13<>0), MONTH(EDATE(G13, 6)), "") -> 9 | AA13: =IF(AND(M13<>"", M13<>0), F13*1000*M13/(100*2), "") -> 4200 | AB13: =IF(AND(AA13<>"",AA13<>0), IF(E13="Muni", AA13, IF(E13 = "Corp", (1-'Investor Input'!$C$4-'Investor Input'!$C$5)*AA13, (1-'Investor Input'!$C$4)*AA13)), AA13) -> 2268 | AC13: =IF(AND(M13<>"", M13<>0), H13, "") -> A2 | AD13: =IF(AND(M13<>"", M13<>0), N13/$N$505*MATCH(AC13,'Misc Lists'!$K$2:$K$25,0), "") -> 1.3537024 | AE13: =IF(AND(M13<>"", M13<>0), I13, "") -> A- | AF13: =IF(AND(M13<>"", M13<>0), N13/$N$505*MATCH(AE13,'Misc Lists'!$L$2:$L$25,0), "") -> 1.5470885
B14: 91159XBG9 | C14: N/A | D14: US BANCORP SER CC MTN 5.20000% 12/26/2029 | E14: Corp | F14: 5.2 | G14: 47478 | H14: A3 | I14: A | J14: 100.332 | K14: 5.122 | L14: 40(2) | N14: =IF(AND(M14<>"", M14<>0), IF(L14 <> "N/A", IF(M14>=VALUE(LEFT(L14, FIND("(", L14)-1)), J14*10*M14, 1000*M14), 1000*M14), "") | O14: =IF(AND(M14<>"",M14<>0),N14/$N$505, "") | P14: =IF(AND(M14<>"", M14<>0), F14*1000/100, "") | Q14: =IF(AND(M14<>"", M14<>0), NOW(), "") | R14: =IF(AND(M14<>"", M14<>0), ROUND((G14 - Q14)/365, 0), "") | S14: =IF(AND(M14<>"",M14<>0),MDURATION(Q14,G14,F14/100,K14/100,2), "") | T14: =IF(AND(M14<>"",M14<>0),YIELD(Q14,G14,F14/100,N14/(M14*10),100,2),"") | U14: =IF(AND(M14<>"",M14<>0), IF(E14 = "Muni", T14, IF(E14="Corp", T14*(1 -'Investor Input'!$C$4-'Investor Input'!$C$5), T14*(1 -'Investor Input'!$C$4))), T14) | V14: =IF(AND(M14<>"",M14<>0),(FV(K14/(2*100),(G14-Q14)*2/365, F14*1000/(2*100), -N14/M14))*M14, "") | W14: =IF(AND(M14<>"",M14<>0),V14-N14,"") | X14: =IF(AND(M14<>"",M14<>0),W14/N14,"") | Y14: =IF(AND(M14<>"", M14<>0), MONTH(G14), "") | Z14: =IF(AND(M14<>"", M14<>0), MONTH(EDATE(G14, 6)), "") | AA14: =IF(AND(M14<>"", M14<>0), F14*1000*M14/(100*2), "") | AB14: =IF(AND(AA14<>"",AA14<>0), IF(E14="Muni", AA14, IF(E14 = "Corp", (1-'Investor Input'!$C$4-'Investor Input'!$C$5)*AA14, (1-'Investor Input'!$C$4)*AA14)), AA14) | AC14: =IF(AND(M14<>"", M14<>0), H14, "") | AD14: =IF(AND(M14<>"", M14<>0), N14/$N$505*MATCH(AC14,'Misc Lists'!$K$2:$K$25,0), "") | AE14: =IF(AND(M14<>"", M14<>0), I14, "") | AF14: =IF(AND(M14<>"", M14<>0), N14/$N$505*MATCH(AE14,'Misc Lists'!$L$2:$L$25,0), "")
B15: 06055JJV2 | C15: N/A | D15: BANK AMERICA CORP SER P MTN 5.20000% 02/26/2030 | E15: Corp | F15: 5.2 | G15: 47540 | H15: A1 | I15: A- | J15: 100.35 | K15: 5.119 | L15: 1,135(10) | N15: =IF(AND(M15<>"", M15<>0), IF(L15 <> "N/A", IF(M15>=VALUE(LEFT(L15, FIND("(", L15)-1)), J15*10*M15, 1000*M15), 1000*M15), "") | O15: =IF(AND(M15<>"",M15<>0),N15/$N$505, "") | P15: =IF(AND(M15<>"", M15<>0), F15*1000/100, "") | Q15: =IF(AND(M15<>"", M15<>0), NOW(), "") | R15: =IF(AND(M15<>"", M15<>0), ROUND((G15 - Q15)/365, 0), "") | S15: =IF(AND(M15<>"",M15<>0),MDURATION(Q15,G15,F15/100,K15/100,2), "") | T15: =IF(AND(M15<>"",M15<>0),YIELD(Q15,G15,F15/100,N15/(M15*10),100,2),"") | U15: =IF(AND(M15<>"",M15<>0), IF(E15 = "Muni", T15, IF(E15="Corp", T15*(1 -'Investor Input'!$C$4-'Investor Input'!$C$5), T15*(1 -'Investor Input'!$C$4))), T15) | V15: =IF(AND(M15<>"",M15<>0),(FV(K15/(2*100),(G15-Q15)*2/365, F15*1000/(2*100), -N15/M15))*M15, "") | W15: =IF(AND(M15<>"",M15<>0),V15-N15,"") | X15: =IF(AND(M15<>"",M15<>0),W15/N15,"") | Y15: =IF(AND(M15<>"", M15<>0), MONTH(G15), "") | Z15: =IF(AND(M15<>"", M15<>0), MONTH(EDATE(G15, 6)), "") | AA15: =IF(AND(M15<>"", M15<>0), F15*1000*M15/(100*2), "") | AB15: =IF(AND(AA15<>"",AA15<>0), IF(E15="Muni", AA15, IF(E15 = "Corp", (1-'Investor Input'!$C$4-'Investor Input'!$C$5)*AA15, (1-'Investor Input'!$C$4)*AA15)), AA15) | AC15: =IF(AND(M15<>"", M15<>0), H15, "") | AD15: =IF(AND(M15<>"", M15<>0), N15/$N$505*MATCH(AC15,'Misc Lists'!$K$2:$K$25,0), "") | AE15: =IF(AND(M15<>"", M15<>0), I15, "") | AF15: =IF(AND(M15<>"", M15<>0), N15/$N$505*MATCH(AE15,'Misc Lists'!$L$2:$L$25,0), "")
B16: 89788KAA4 | C16: N/A | D16: TRUIST BK NOTE 2.25000% 03/11/2030 | E16: Corp | F16: 2.25 | G16: 47553 | H16: A3 | I16: A- | J16: 87.493 | K16: 5.118 | L16: 500(250) | M16: 500 | N16: =IF(AND(M16<>"", M16<>0), IF(L16 <> "N/A", IF(M16>=VALUE(LEFT(L16, FIND("(", L16)-1)), J16*10*M16, 1000*M16), 1000*M16), "") -> 437465 | O16: =IF(AND(M16<>"",M16<>0),N16/$N$505, "") -> 0.43744704 | P16: =IF(AND(M16<>"", M16<>0), F16*1000/100, "") -> 22.5 | Q16: =IF(AND(M16<>"", M16<>0), NOW(), "") -> 45791.491 | R16: =IF(AND(M16<>"", M16<>0), ROUND((G16 - Q16)/365, 0), "") -> 5 | S16: =IF(AND(M16<>"",M16<>0),MDURATION(Q16,G16,F16/100,K16/100,2), "") -> 4.4470674 | T16: =IF(AND(M16<>"",M16<>0),YIELD(Q16,G16,F16/100,N16/(M16*10),100,2),"") -> 0.052145699 | U16: =IF(AND(M16<>"",M16<>0), IF(E16 = "Muni", T16, IF(E16="Corp", T16*(1 -'Investor Input'!$C$4-'Investor Input'!$C$5), T16*(1 -'Investor Input'!$C$4))), T16) -> 0.028158677 | V16: =IF(AND(M16<>"",M16<>0),(FV(K16/(2*100),(G16-Q16)*2/365, F16*1000/(2*100), -N16/M16))*M16, "") -> 497581.46 | W16: =IF(AND(M16<>"",M16<>0),V16-N16,"") -> 60116.461 | X16: =IF(AND(M16<>"",M16<>0),W16/N16,"") -> 0.13742005 | Y16: =IF(AND(M16<>"", M16<>0), MONTH(G16), "") -> 3 | Z16: =IF(AND(M16<>"", M16<>0), MONTH(EDATE(G16, 6)), "") -> 9 | AA16: =IF(AND(M16<>"", M16<>0), F16*1000*M16/(100*2), "") -> 5625 | AB16: =IF(AND(AA16<>"",AA16<>0), IF(E16="Muni", AA16, IF(E16 = "Corp", (1-'Investor Input'!$C$4-'Investor Input'!$C$5)*AA16, (1-'Investor Input'!$C$4)*AA16)), AA16) -> 3037.5 | AC16: =IF(AND(M16<>"", M16<>0), H16, "") -> A3 | AD16: =IF(AND(M16<>"", M16<>0), N16/$N$505*MATCH(AC16,'Misc Lists'!$K$2:$K$25,0), "") -> 3.4995763 | AE16: =IF(AND(M16<>"", M16<>0), I16, "") -> A- | AF16: =IF(AND(M16<>"", M16<>0), N16/$N$505*MATCH(AE16,'Misc Lists'!$L$2:$L$25,0), "") -> 3.4995763
B17: 46513JXM8 | C17: N/A | D17: ISRAEL(STATE OF) NOTE 2.50000% 01/15/2030 ISIN #US46513JXM88 SEDOL #BKVGCR7 | E17: Corp | F17: 2.5 | G17: 47498 | H17: BAA1 | I17: A | J17: 88.939 | K17: 5.107 | L17: 225(200) | N17: =IF(AND(M17<>"", M17<>0), IF(L17 <> "N/A", IF(M17>=VALUE(LEFT(L17, FIND("(", L17)-1)), J17*10*M17, 1000*M17), 1000*M17), "") | O17: =IF(AND(M17<>"",M17<>0),N17/$N$505, "") | P17: =IF(AND(M17<>"", M17<>0), F17*1000/100, "") | Q17: =IF(AND(M17<>"", M17<>0), NOW(), "") | R17: =IF(AND(M17<>"", M17<>0), ROUND((G17 - Q17)/365, 0), "") | S17: =IF(AND(M17<>"",M17<>0),MDURATION(Q17,G17,F17/100,K17/100,2), "") | T17: =IF(AND(M17<>"",M17<>0),YIELD(Q17,G17,F17/100,N17/(M17*10),100,2),"") | U17: =IF(AND(M17<>"",M17<>0), IF(E17 = "Muni", T17, IF(E17="Corp", T17*(1 -'Investor Input'!$C$4-'Investor Input'!$C$5), T17*(1 -'Investor Input'!$C$4))), T17) | V17: =IF(AND(M17<>"",M17<>0),(FV(K17/(2*100),(G17-Q17)*2/365, F17*1000/(2*100), -N17/M17))*M17, "") | W17: =IF(AND(M17<>"",M17<>0),V17-N17,"") | X17: =IF(AND(M17<>"",M17<>0),W17/N17,"") | Y17: =IF(AND(M17<>"", M17<>0), MONTH(G17), "") | Z17: =IF(AND(M17<>"", M17<>0), MONTH(EDATE(G17, 6)), "") | AA17: =IF(AND(M17<>"", M17<>0), F17*1000*M17/(100*2), "") | AB17: =IF(AND(AA17<>"",AA17<>0), IF(E17="Muni", AA17, IF(E17 = "Corp", (1-'Investor Input'!$C$4-'Investor Input'!$C$5)*AA17, (1-'Investor Input'!$C$4)*AA17)), AA17) | AC17: =IF(AND(M17<>"", M17<>0), H17, "") | AD17: =IF(AND(M17<>"", M17<>0), N17/$N$505*MATCH(AC17,'Misc Lists'!$K$2:$K$25,0), "") | AE17: =IF(AND(M17<>"", M17<>0), I17, "") | AF17: =IF(AND(M17<>"", M17<>0), N17/$N$505*MATCH(AE17,'Misc Lists'!$L$2:$L$25,0), "")
B18: 48135NTR7 | C18: N/A | D18: JPMORGAN CHASE FINL CO LLC SER A MTN 5.25000% 02/28/2030 | E18: Corp | F18: 5.25 | G18: 47542 | H18: A1 | I18: A | J18: 100.648 | K18: 5.1 | L18: 628(1) | N18: =IF(AND(M18<>"", M18<>0), IF(L18 <> "N/A", IF(M18>=VALUE(LEFT(L18, FIND("(", L18)-1)), J18*10*M18, 1000*M18), 1000*M18), "") | O18: =IF(AND(M18<>"",M18<>0),N18/$N$505, "") | P18: =IF(AND(M18<>"", M18<>0), F18*1000/100, "") | Q18: =IF(AND(M18<>"", M18<>0), NOW(), "") | R18: =IF(AND(M18<>"", M18<>0), ROUND((G18 - Q18)/365, 0), "") | S18: =IF(AND(M18<>"",M18<>0),MDURATION(Q18,G18,F18/100,K18/100,2), "") | T18: =IF(AND(M18<>"",M18<>0),YIELD(Q18,G18,F18/100,N18/(M18*10),100,2),"") | U18: =IF(AND(M18<>"",M18<>0), IF(E18 = "Muni", T18, IF(E18="Corp", T18*(1 -'Investor Input'!$C$4-'Investor Input'!$C$5), T18*(1 -'Investor Input'!$C$4))), T18) | V18: =IF(AND(M18<>"",M18<>0),(FV(K18/(2*100),(G18-Q18)*2/365, F18*1000/(2*100), -N18/M18))*M18, "") | W18: =IF(AND(M18<>"",M18<>0),V18-N18,"") | X18: =IF(AND(M18<>"",M18<>0),W18/N18,"") | Y18: =IF(AND(M18<>"", M18<>0), MONTH(G18), "") | Z18: =IF(AND(M18<>"", M18<>0), MONTH(EDATE(G18, 6)), "") | AA18: =IF(AND(M18<>"", M18<>0), F18*1000*M18/(100*2), "") | AB18: =IF(AND(AA18<>"",AA18<>0), IF(E18="Muni", AA18, IF(E18 = "Corp", (1-'Investor Input'!$C$4-'Investor Input'!$C$5)*AA18, (1-'Investor Input'!$C$4)*AA18)), AA18) | AC18: =IF(AND(M18<>"", M18<>0), H18, "") | AD18: =IF(AND(M18<>"", M18<>0), N18/$N$505*MATCH(AC18,'Misc Lists'!$K$2:$K$25,0), "") | AE18: =IF(AND(M18<>"", M18<>0), I18, "") | AF18: =IF(AND(M18<>"", M18<>0), N18/$N$505*MATCH(AE18,'Misc Lists'!$L$2:$L$25,0), "")
B19: 842400JC8 | C19: N/A | D19: SOUTHERN CALIF EDISON CO SER 2024D 5.15000% 06/01/2029 BOND CALL MAKE WHOLE | E19: Corp | F19: 5.15 | G19: 47270 | H19: A2 | I19: A- | J19: 100.205 | K19: 5.093 | L19: 100(10) | M19: 100 | N19: =IF(AND(M19<>"", M19<>0), IF(L19 <> "N/A", IF(M19>=VALUE(LEFT(L19, FIND("(", L19)-1)), J19*10*M19, 1000*M19), 1000*M19), "") -> 100205 | O19: =IF(AND(M19<>"",M19<>0),N19/$N$505, "") -> 0.10020089 | P19: =IF(AND(M19<>"", M19<>0), F19*1000/100, "") -> 51.5 | Q19: =IF(AND(M19<>"", M19<>0), NOW(), "") -> 45791.491 | R19: =IF(AND(M19<>"", M19<>0), ROUND((G19 - Q19)/365, 0), "") -> 4 | S19: =IF(AND(M19<>"",M19<>0),MDURATION(Q19,G19,F19/100,K19/100,2), "") -> 3.5315054 | T19: =IF(AND(M19<>"",M19<>0),YIELD(Q19,G19,F19/100,N19/(M19*10),100,2),"") -> 0.050925408 | U19: =IF(AND(M19<>"",M19<>0), IF(E19 = "Muni", T19, IF(E19="Corp", T19*(1 -'Investor Input'!$C$4-'Investor Input'!$C$5), T19*(1 -'Investor Input'!$C$4))), T19) -> 0.02749972 | V19: =IF(AND(M19<>"",M19<>0),(FV(K19/(2*100),(G19-Q19)*2/365, F19*1000/(2*100), -N19/M19))*M19, "") -> 99998.436 | W19: =IF(AND(M19<>"",M19<>0),V19-N19,"") -> -206.56367 | X19: =IF(AND(M19<>"",M19<>0),W19/N19,"") -> -0.0020614108 | Y19: =IF(AND(M19<>"", M19<>0), MONTH(G19), "") -> 6 | Z19: =IF(AND(M19<>"", M19<>0), MONTH(EDATE(G19, 6)), "") -> 12 | AA19: =IF(AND(M19<>"", M19<>0), F19*1000*M19/(100*2), "") -> 2575 | AB19: =IF(AND(AA19<>"",AA19<>0), IF(E19="Muni", AA19, IF(E19 = "Corp", (1-'Investor Input'!$C$4-'Investor Input'!$C$5)*AA19, (1-'Investor Input'!$C$4)*AA19)), AA19) -> 1390.5 | AC19: =IF(AND(M19<>"", M19<>0), H19, "") -> A2 | AD19: =IF(AND(M19<>"", M19<>0), N19/$N$505*MATCH(AC19,'Misc Lists'!$K$2:$K$25,0), "") -> 0.70140621 | AE19: =IF(AND(M19<>"", M19<>0), I19, "") -> A- | AF19: =IF(AND(M19<>"", M19<>0), N19/$N$505*MATCH(AE19,'Misc Lists'!$L$2:$L$25,0), "") -> 0.80160709
B20: 06055JJQ3 | C20: N/A | D20: BANK AMERICA CORP SER P MTN 5.15000% 02/06/2030 | E20: Corp | F20: 5.15 | G20: 47520 | H20: A1 | I20: A- | J20: 100.25 | K20: 5.092 | L20: 35(5) | N20: =IF(AND(M20<>"", M20<>0), IF(L20 <> "N/A", IF(M20>=VALUE(LEFT(L20, FIND("(", L20)-1)), J20*10*M20, 1000*M20), 1000*M20), "") | O20: =IF(AND(M20<>"",M20<>0),N20/$N$505, "") | P20: =IF(AND(M20<>"", M20<>0), F20*1000/100, "") | Q20: =IF(AND(M20<>"", M20<>0), NOW(), "") | R20: =IF(AND(M20<>"", M20<>0), ROUND((G20 - Q20)/365, 0), "") | S20: =IF(AND(M20<>"",M20<>0),MDURATION(Q20,G20,F20/100,K20/100,2), "") | T20: =IF(AND(M20<>"",M20<>0),YIELD(Q20,G20,F20/100,N20/(M20*10),100,2),"") | U20: =IF(AND(M20<>"",M20<>0), IF(E20 = "Muni", T20, IF(E20="Corp", T20*(1 -'Investor Input'!$C$4-'Investor Input'!$C$5), T20*(1 -'Investor Input'!$C$4))), T20) | V20: =IF(AND(M20<>"",M20<>0),(FV(K20/(2*100),(G20-Q20)*2/365, F20*1000/(2*100), -N20/M20))*M20, "") | W20: =IF(AND(M20<>"",M20<>0),V20-N20,"") | X20: =IF(AND(M20<>"",M20<>0),W20/N20,"") | Y20: =IF(AND(M20<>"", M20<>0), MONTH(G20), "") | Z20: =IF(AND(M20<>"", M20<>0), MONTH(EDATE(G20, 6)), "") | AA20: =IF(AND(M20<>"", M20<>0), F20*1000*M20/(100*2), "") | AB20: =IF(AND(AA20<>"",AA20<>0), IF(E20="Muni", AA20, IF(E20 = "Corp", (1-'Investor Input'!$C$4-'Investor Input'!$C$5)*AA20, (1-'Investor Input'!$C$4)*AA20)), AA20) | AC20: =IF(AND(M20<>"", M20<>0), H20, "") | AD20: =IF(AND(M20<>"", M20<>0), N20/$N$505*MATCH(AC20,'Misc Lists'!$K$2:$K$25,0), "") | AE20: =IF(AND(M20<>"", M20<>0), I20, "") | AF20: =IF(AND(M20<>"", M20<>0), N20/$N$505*MATCH(AE20,'Misc Lists'!$L$2:$L$25,0), "")
B21: 842400GS6 | C21: N/A | D21: SOUTHERN CALIF EDISON CO SER 2019C 2.85000% 08/01/2029 BOND CALL MAKE WHOLE | E21: Corp | F21: 2.85 | G21: 47331 | H21: A2 | I21: A- | J21: 91.299 | K21: 5.088 | L21: 500(1) | N21: =IF(AND(M21<>"", M21<>0), IF(L21 <> "N/A", IF(M21>=VALUE(LEFT(L21, FIND("(", L21)-1)), J21*10*M21, 1000*M21), 1000*M21), "") | O21: =IF(AND(M21<>"",M21<>0),N21/$N$505, "") | P21: =IF(AND(M21<>"", M21<>0), F21*1000/100, "") | Q21: =IF(AND(M21<>"", M21<>0), NOW(), "") | R21: =IF(AND(M21<>"", M21<>0), ROUND((G21 - Q21)/365, 0), "") | S21: =IF(AND(M21<>"",M21<>0),MDURATION(Q21,G21,F21/100,K21/100,2), "") | T21: =IF(AND(M21<>"",M21<>0),YIELD(Q21,G21,F21/100,N21/(M21*10),100,2),"") | U21: =IF(AND(M21<>"",M21<>0), IF(E21 = "Muni", T21, IF(E21="Corp", T21*(1 -'Investor Input'!$C$4-'Investor Input'!$C$5), T21*(1 -'Investor Input'!$C$4))), T21) | V21: =IF(AND(M21<>"",M21<>0),(FV(K21/(2*100),(G21-Q21)*2/365, F21*1000/(2*100), -N21/M21))*M21, "") | W21: =IF(AND(M21<>"",M21<>0),V21-N21,"") | X21: =IF(AND(M21<>"",M21<>0),W21/N21,"") | Y21: =IF(AND(M21<>"", M21<>0), MONTH(G21), "") | Z21: =IF(AND(M21<>"", M21<>0), MONTH(EDATE(G21, 6)), "") | AA21: =IF(AND(M21<>"", M21<>0), F21*1000*M21/(100*2), "") | AB21: =IF(AND(AA21<>"",AA21<>0), IF(E21="Muni", AA21, IF(E21 = "Corp", (1-'Investor Input'!$C$4-'Investor Input'!$C$5)*AA21, (1-'Investor Input'!$C$4)*AA21)), AA21) | AC21: =IF(AND(M21<>"", M21<>0), H21, "") | AD21: =IF(AND(M21<>"", M21<>0), N21/$N$505*MATCH(AC21,'Misc Lists'!$K$2:$K$25,0), "") | AE21: =IF(AND(M21<>"", M21<>0), I21, "") | AF21: =IF(AND(M21<>"", M21<>0), N21/$N$505*MATCH(AE21,'Misc Lists'!$L$2:$L$25,0), "")
B22: 06746AN33 | C22: N/A | D22: BARCLAYS BANK PLC SER A MTN 5.20000% 03/04/2030 | E22: Corp | F22: 5.2 | G22: 47546 | H22: A1 | I22: A+ | J22: 100.5 | K22: 5.085 | L22: 169(1) | N22: =IF(AND(M22<>"", M22<>0), IF(L22 <> "N/A", IF(M22>=VALUE(LEFT(L22, FIND("(", L22)-1)), J22*10*M22, 1000*M22), 1000*M22), "") | O22: =IF(AND(M22<>"",M22<>0),N22/$N$505, "") | P22: =IF(AND(M22<>"", M22<>0), F22*1000/100, "") | Q22: =IF(AND(M22<>"", M22<>0), NOW(), "") | R22: =IF(AND(M22<>"", M22<>0), ROUND((G22 - Q22)/365, 0), "") | S22: =IF(AND(M22<>"",M22<>0),MDURATION(Q22,G22,F22/100,K22/100,2), "") | T22: =IF(AND(M22<>"",M22<>0),YIELD(Q22,G22,F22/100,N22/(M22*10),100,2),"") | U22: =IF(AND(M22<>"",M22<>0), IF(E22 = "Muni", T22, IF(E22="Corp", T22*(1 -'Investor Input'!$C$4-'Investor Input'!$C$5), T22*(1 -'Investor Input'!$C$4))), T22) | V22: =IF(AND(M22<>"",M22<>0),(FV(K22/(2*100),(G22-Q22)*2/365, F22*1000/(2*100), -N22/M22))*M22, "") | W22: =IF(AND(M22<>"",M22<>0),V22-N22,"") | X22: =IF(AND(M22<>"",M22<>0),W22/N22,"") | Y22: =IF(AND(M22<>"", M22<>0), MONTH(G22), "") | Z22: =IF(AND(M22<>"", M22<>0), MONTH(EDATE(G22, 6)), "") | AA22: =IF(AND(M22<>"", M22<>0), F22*1000*M22/(100*2), "") | AB22: =IF(AND(AA22<>"",AA22<>0), IF(E22="Muni", AA22, IF(E22 = "Corp", (1-'Investor Input'!$C$4-'Investor Input'!$C$5)*AA22, (1-'Investor Input'!$C$4)*AA22)), AA22) | AC22: =IF(AND(M22<>"", M22<>0), H22, "") | AD22: =IF(AND(M22<>"", M22<>0), N22/$N$505*MATCH(AC22,'Misc Lists'!$K$2:$K$25,0), "") | AE22: =IF(AND(M22<>"", M22<>0), I22, "") | AF22: =IF(AND(M22<>"", M22<>0), N22/$N$505*MATCH(AE22,'Misc Lists'!$L$2:$L$25,0), "")
B23: 03076CAK2 | C23: N/A | D23: AMERIPRISE FINL INC NOTE 3.00000% 04/02/2025 | E23: Corp | F23: 3 | G23: 45749 | H23: A3 | I23: A- | J23: 99.882 | K23: 5.062 | L23: 250(10) | N23: =IF(AND(M23<>"", M23<>0), IF(L23 <> "N/A", IF(M23>=VALUE(LEFT(L23, FIND("(", L23)-1)), J23*10*M23, 1000*M23), 1000*M23), "") | O23: =IF(AND(M23<>"",M23<>0),N23/$N$505, "") | P23: =IF(AND(M23<>"", M23<>0), F23*1000/100, "") | Q23: =IF(AND(M23<>"", M23<>0), NOW(), "") | R23: =IF(AND(M23<>"", M23<>0), ROUND((G23 - Q23)/365, 0), "") | S23: =IF(AND(M23<>"",M23<>0),MDURATION(Q23,G23,F23/100,K23/100,2), "") | T23: =IF(AND(M23<>"",M23<>0),YIELD(Q23,G23,F23/100,N23/(M23*10),100,2),"") | U23: =IF(AND(M23<>"",M23<>0), IF(E23 = "Muni", T23, IF(E23="Corp", T23*(1 -'Investor Input'!$C$4-'Investor Input'!$C$5), T23*(1 -'Investor Input'!$C$4))), T23) | V23: =IF(AND(M23<>"",M23<>0),(FV(K23/(2*100),(G23-Q23)*2/365, F23*1000/(2*100), -N23/M23))*M23, "") | W23: =IF(AND(M23<>"",M23<>0),V23-N23,"") | X23: =IF(AND(M23<>"",M23<>0),W23/N23,"") | Y23: =IF(AND(M23<>"", M23<>0), MONTH(G23), "") | Z23: =IF(AND(M23<>"", M23<>0), MONTH(EDATE(G23, 6)), "") | AA23: =IF(AND(M23<>"", M23<>0), F23*1000*M23/(100*2), "") | AB23: =IF(AND(AA23<>"",AA23<>0), IF(E23="Muni", AA23, IF(E23 = "Corp", (1-'Investor Input'!$C$4-'Investor Input'!$C$5)*AA23, (1-'Investor Input'!$C$4)*AA23)), AA23) | AC23: =IF(AND(M23<>"", M23<>0), H23, "") | AD23: =IF(AND(M23<>"", M23<>0), N23/$N$505*MATCH(AC23,'Misc Lists'!$K$2:$K$25,0), "") | AE23: =IF(AND(M23<>"", M23<>0), I23, "") | AF23: =IF(AND(M23<>"", M23<>0), N23/$N$505*MATCH(AE23,'Misc Lists'!$L$2:$L$25,0), "")
B24: 25161FA99 | C24: N/A | D24: DEUTSCHE BK AG SER E NOTE 5.05000% 08/16/2029 | E24: Corp | F24: 5.05 | G24: 47346 | H24: A1 | I24: A | J24: 99.992 | K24: 5.051 | L24: 20(20) | M24: 20 | N24: =IF(AND(M24<>"", M24<>0), IF(L24 <> "N/A", IF(M24>=VALUE(LEFT(L24, FIND("(", L24)-1)), J24*10*M24, 1000*M24), 1000*M24), "") -> 19998.4 | O24: =IF(AND(M24<>"",M24<>0),N24/$N$505, "") -> 0.019997579 | P24: =IF(AND(M24<>"", M24<>0), F24*1000/100, "") -> 50.5 | Q24: =IF(AND(M24<>"", M24<>0), NOW(), "") -> 45791.491 | R24: =IF(AND(M24<>"", M24<>0), ROUND((G24 - Q24)/365, 0), "") -> 4 | S24: =IF(AND(M24<>"",M24<>0),MDURATION(Q24,G24,F24/100,K24/100,2), "") -> 3.7422842 | T24: =IF(AND(M24<>"",M24<>0),YIELD(Q24,G24,F24/100,N24/(M24*10),100,2),"") -> 0.050500354 | U24: =IF(AND(M24<>"",M24<>0), IF(E24 = "Muni", T24, IF(E24="Corp", T24*(1 -'Investor Input'!$C$4-'Investor Input'!$C$5), T24*(1 -'Investor Input'!$C$4))), T24) -> 0.027270191 | V24: =IF(AND(M24<>"",M24<>0),(FV(K24/(2*100),(G24-Q24)*2/365, F24*1000/(2*100), -N24/M24))*M24, "") -> 19998.959 | W24: =IF(AND(M24<>"",M24<>0),V24-N24,"") -> 0.55852125 | X24: =IF(AND(M24<>"",M24<>0),W24/N24,"") -> 2.7928297e-05 | Y24: =IF(AND(M24<>"", M24<>0), MONTH(G24), "") -> 8 | Z24: =IF(AND(M24<>"", M24<>0), MONTH(EDATE(G24, 6)), "") -> 2 | AA24: =IF(AND(M24<>"", M24<>0), F24*1000*M24/(100*2), "") -> 505 | AB24: =IF(AND(AA24<>"",AA24<>0), IF(E24="Muni", AA24, IF(E24 = "Corp", (1-'Investor Input'!$C$4-'Investor Input'!$C$5)*AA24, (1-'Investor Input'!$C$4)*AA24)), AA24) -> 272.7 | AC24: =IF(AND(M24<>"", M24<>0), H24, "") -> A1 | AD24: =IF(AND(M24<>"", M24<>0), N24/$N$505*MATCH(AC24,'Misc Lists'!$K$2:$K$25,0), "") -> 0.11998547 | AE24: =IF(AND(M24<>"", M24<>0), I24, "") -> A | AF24: =IF(AND(M24<>"", M24<>0), N24/$N$505*MATCH(AE24,'Misc Lists'!$L$2:$L$25,0), "") -> 0.13998305
B25: 48135NTG1 | C25: N/A | D25: JPMORGAN CHASE FINL CO LLC SER A MTN 5.15000% 02/14/2030 | E25: Corp | F25: 5.15 | G25: 47528 | H25: A1 | I25: A | J25: 100.442 | K25: 5.046 | L25: 980(1) | N25: =IF(AND(M25<>"", M25<>0), IF(L25 <> "N/A", IF(M25>=VALUE(LEFT(L25, FIND("(", L25)-1)), J25*10*M25, 1000*M25), 1000*M25), "") | O25: =IF(AND(M25<>"",M25<>0),N25/$N$505, "") | P25: =IF(AND(M25<>"", M25<>0), F25*1000/100, "") | Q25: =IF(AND(M25<>"", M25<>0), NOW(), "") | R25: =IF(AND(M25<>"", M25<>0), ROUND((G25 - Q25)/365, 0), "") | S25: =IF(AND(M25<>"",M25<>0),MDURATION(Q25,G25,F25/100,K25/100,2), "") | T25: =IF(AND(M25<>"",M25<>0),YIELD(Q25,G25,F25/100,N25/(M25*10),100,2),"") | U25: =IF(AND(M25<>"",M25<>0), IF(E25 = "Muni", T25, IF(E25="Corp", T25*(1 -'Investor Input'!$C$4-'Investor Input'!$C$5), T25*(1 -'Investor Input'!$C$4))), T25) | V25: =IF(AND(M25<>"",M25<>0),(FV(K25/(2*100),(G25-Q25)*2/365, F25*1000/(2*100), -N25/M25))*M25, "") | W25: =IF(AND(M25<>"",M25<>0),V25-N25,"") | X25: =IF(AND(M25<>"",M25<>0),W25/N25,"") | Y25: =IF(AND(M25<>"", M25<>0), MONTH(G25), "") | Z25: =IF(AND(M25<>"", M25<>0), MONTH(EDATE(G25, 6)), "") | AA25: =IF(AND(M25<>"", M25<>0), F25*1000*M25/(100*2), "") | AB25: =IF(AND(AA25<>"",AA25<>0), IF(E25="Muni", AA25, IF(E25 = "Corp", (1-'Investor Input'!$C$4-'Investor Input'!$C$5)*AA25, (1-'Investor Input'!$C$4)*AA25)), AA25) | AC25: =IF(AND(M25<>"", M25<>0), H25, "") | AD25: =IF(AND(M25<>"", M25<>0), N25/$N$505*MATCH(AC25,'Misc Lists'!$K$2:$K$25,0), "") | AE25: =IF(AND(M25<>"", M25<>0), I25, "") | AF25: =IF(AND(M25<>"", M25<>0), N25/$N$505*MATCH(AE25,'Misc Lists'!$L$2:$L$25,0), "")
B26: 89114XDV2 | C26: N/A | D26: TORONTO DOMINION BK ONT SER D MTN 5.10000% 02/15/2027 ISIN #US89114XDV29 | E26: Corp | F26: 5.1 | G26: 46433 | H26: A2 | I26: A- | J26: 100.115 | K26: 5.036 | L26: 75(25) | N26: =IF(AND(M26<>"", M26<>0), IF(L26 <> "N/A", IF(M26>=VALUE(LEFT(L26, FIND("(", L26)-1)), J26*10*M26, 1000*M26), 1000*M26), "") | O26: =IF(AND(M26<>"",M26<>0),N26/$N$505, "") | P26: =IF(AND(M26<>"", M26<>0), F26*1000/100, "") | Q26: =IF(AND(M26<>"", M26<>0), NOW(), "") | R26: =IF(AND(M26<>"", M26<>0), ROUND((G26 - Q26)/365, 0), "") | S26: =IF(AND(M26<>"",M26<>0),MDURATION(Q26,G26,F26/100,K26/100,2), "") | T26: =IF(AND(M26<>"",M26<>0),YIELD(Q26,G26,F26/100,N26/(M26*10),100,2),"") | U26: =IF(AND(M26<>"",M26<>0), IF(E26 = "Muni", T26, IF(E26="Corp", T26*(1 -'Investor Input'!$C$4-'Investor Input'!$C$5), T26*(1 -'Investor Input'!$C$4))), T26) | V26: =IF(AND(M26<>"",M26<>0),(FV(K26/(2*100),(G26-Q26)*2/365, F26*1000/(2*100), -N26/M26))*M26, "") | W26: =IF(AND(M26<>"",M26<>0),V26-N26,"") | X26: =IF(AND(M26<>"",M26<>0),W26/N26,"") | Y26: =IF(AND(M26<>"", M26<>0), MONTH(G26), "") | Z26: =IF(AND(M26<>"", M26<>0), MONTH(EDATE(G26, 6)), "") | AA26: =IF(AND(M26<>"", M26<>0), F26*1000*M26/(100*2), "") | AB26: =IF(AND(AA26<>"",AA26<>0), IF(E26="Muni", AA26, IF(E26 = "Corp", (1-'Investor Input'!$C$4-'Investor Input'!$C$5)*AA26, (1-'Investor Input'!$C$4)*AA26)), AA26) | AC26: =IF(AND(M26<>"", M26<>0), H26, "") | AD26: =IF(AND(M26<>"", M26<>0), N26/$N$505*MATCH(AC26,'Misc Lists'!$K$2:$K$25,0), "") | AE26: =IF(AND(M26<>"", M26<>0), I26, "") | AF26: =IF(AND(M26<>"", M26<>0), N26/$N$505*MATCH(AE26,'Misc Lists'!$L$2:$L$25,0), "")
B27: 06418VKL7 | C27: N/A | D27: BANK NOVA SCOTIA B CSER B NOTE 5.05000% 02/28/2030 | E27: Corp | F27: 5.05 | G27: 47542 | H27: A2 | I27: A- | J27: 100.09 | K27: 5.029 | L27: 975(1) | N27: =IF(AND(M27<>"", M27<>0), IF(L27 <> "N/A", IF(M27>=VALUE(LEFT(L27, FIND("(", L27)-1)), J27*10*M27, 1000*M27), 1000*M27), "") | O27: =IF(AND(M27<>"",M27<>0),N27/$N$505, "") | P27: =IF(AND(M27<>"", M27<>0), F27*1000/100, "") | Q27: =IF(AND(M27<>"", M27<>0), NOW(), "") | R27: =IF(AND(M27<>"", M27<>0), ROUND((G27 - Q27)/365, 0), "") | S27: =IF(AND(M27<>"",M27<>0),MDURATION(Q27,G27,F27/100,K27/100,2), "") | T27: =IF(AND(M27<>"",M27<>0),YIELD(Q27,G27,F27/100,N27/(M27*10),100,2),"") | U27: =IF(AND(M27<>"",M27<>0), IF(E27 = "Muni", T27, IF(E27="Corp", T27*(1 -'Investor Input'!$C$4-'Investor Input'!$C$5), T27*(1 -'Investor Input'!$C$4))), T27) | V27: =IF(AND(M27<>"",M27<>0),(FV(K27/(2*100),(G27-Q27)*2/365, F27*1000/(2*100), -N27/M27))*M27, "") | W27: =IF(AND(M27<>"",M27<>0),V27-N27,"") | X27: =IF(AND(M27<>"",M27<>0),W27/N27,"") | Y27: =IF(AND(M27<>"", M27<>0), MONTH(G27), "") | Z27: =IF(AND(M27<>"", M27<>0), MONTH(EDATE(G27, 6)), "") | AA27: =IF(AND(M27<>"", M27<>0), F27*1000*M27/(100*2), "") | AB27: =IF(AND(AA27<>"",AA27<>0), IF(E27="Muni", AA27, IF(E27 = "Corp", (1-'Investor Input'!$C$4-'Investor Input'!$C$5)*AA27, (1-'Investor Input'!$C$4)*AA27)), AA27) | AC27: =IF(AND(M27<>"", M27<>0), H27, "") | AD27: =IF(AND(M27<>"", M27<>0), N27/$N$505*MATCH(AC27,'Misc Lists'!$K$2:$K$25,0), "") | AE27: =IF(AND(M27<>"", M27<>0), I27, "") | AF27: =IF(AND(M27<>"", M27<>0), N27/$N$505*MATCH(AE27,'Misc Lists'!$L$2:$L$25,0), "")
B28: 63305MDA6 | C28: N/A | D28: NATL BANK OF CANADA NOTE 5.00000% 08/28/2028 | E28: Corp | F28: 5 | G28: 46993 | H28: AA2 | I28: A+ | J28: 99.95 | K28: 5.023 | L28: 725(100) | N28: =IF(AND(M28<>"", M28<>0), IF(L28 <> "N/A", IF(M28>=VALUE(LEFT(L28, FIND("(", L28)-1)), J28*10*M28, 1000*M28), 1000*M28), "") | O28: =IF(AND(M28<>"",M28<>0),N28/$N$505, "") | P28: =IF(AND(M28<>"", M28<>0), F28*1000/100, "") | Q28: =IF(AND(M28<>"", M28<>0), NOW(), "") | R28: =IF(AND(M28<>"", M28<>0), ROUND((G28 - Q28)/365, 0), "") | S28: =IF(AND(M28<>"",M28<>0),MDURATION(Q28,G28,F28/100,K28/100,2), "") | T28: =IF(AND(M28<>"",M28<>0),YIELD(Q28,G28,F28/100,N28/(M28*10),100,2),"") | U28: =IF(AND(M28<>"",M28<>0), IF(E28 = "Muni", T28, IF(E28="Corp", T28*(1 -'Investor Input'!$C$4-'Investor Input'!$C$5), T28*(1 -'Investor Input'!$C$4))), T28) | V28: =IF(AND(M28<>"",M28<>0),(FV(K28/(2*100),(G28-Q28)*2/365, F28*1000/(2*100), -N28/M28))*M28, "") | W28: =IF(AND(M28<>"",M28<>0),V28-N28,"") | X28: =IF(AND(M28<>"",M28<>0),W28/N28,"") | Y28: =IF(AND(M28<>"", M28<>0), MONTH(G28), "") | Z28: =IF(AND(M28<>"", M28<>0), MONTH(EDATE(G28, 6)), "") | AA28: =IF(AND(M28<>"", M28<>0), F28*1000*M28/(100*2), "") | AB28: =IF(AND(AA28<>"",AA28<>0), IF(E28="Muni", AA28, IF(E28 = "Corp", (1-'Investor Input'!$C$4-'Investor Input'!$C$5)*AA28, (1-'Investor Input'!$C$4)*AA28)), AA28) | AC28: =IF(AND(M28<>"", M28<>0), H28, "") | AD28: =IF(AND(M28<>"", M28<>0), N28/$N$505*MATCH(AC28,'Misc Lists'!$K$2:$K$25,0), "") | AE28: =IF(AND(M28<>"", M28<>0), I28, "") | AF28: =IF(AND(M28<>"", M28<>0), N28/$N$505*MATCH(AE28,'Misc Lists'!$L$2:$L$25,0), "")
B29: 854502AL5 | C29: N/A | D29: STANLEY BLACK &DECKER INC NOTE 2.30000% 03/15/2030 CALL MAKE WHOLE | E29: Corp | F29: 2.3 | G29: 47557 | H29: BAA3 | I29: A- | J29: 88.087 | K29: 5.02 | L29: 500(2) | N29: =IF(AND(M29<>"", M29<>0), IF(L29 <> "N/A", IF(M29>=VALUE(LEFT(L29, FIND("(", L29)-1)), J29*10*M29, 1000*M29), 1000*M29), "") | O29: =IF(AND(M29<>"",M29<>0),N29/$N$505, "") | P29: =IF(AND(M29<>"", M29<>0), F29*1000/100, "") | Q29: =IF(AND(M29<>"", M29<>0), NOW(), "") | R29: =IF(AND(M29<>"", M29<>0), ROUND((G29 - Q29)/365, 0), "") | S29: =IF(AND(M29<>"",M29<>0),MDURATION(Q29,G29,F29/100,K29/100,2), "") | T29: =IF(AND(M29<>"",M29<>0),YIELD(Q29,G29,F29/100,N29/(M29*10),100,2),"") | U29: =IF(AND(M29<>"",M29<>0), IF(E29 = "Muni", T29, IF(E29="Corp", T29*(1 -'Investor Input'!$C$4-'Investor Input'!$C$5), T29*(1 -'Investor Input'!$C$4))), T29) | V29: =IF(AND(M29<>"",M29<>0),(FV(K29/(2*100),(G29-Q29)*2/365, F29*1000/(2*100), -N29/M29))*M29, "") | W29: =IF(AND(M29<>"",M29<>0),V29-N29,"") | X29: =IF(AND(M29<>"",M29<>0),W29/N29,"") | Y29: =IF(AND(M29<>"", M29<>0), MONTH(G29), "") | Z29: =IF(AND(M29<>"", M29<>0), MONTH(EDATE(G29, 6)), "") | AA29: =IF(AND(M29<>"", M29<>0), F29*1000*M29/(100*2), "") | AB29: =IF(AND(AA29<>"",AA29<>0), IF(E29="Muni", AA29, IF(E29 = "Corp", (1-'Investor Input'!$C$4-'Investor Input'!$C$5)*AA29, (1-'Investor Input'!$C$4)*AA29)), AA29) | AC29: =IF(AND(M29<>"", M29<>0), H29, "") | AD29: =IF(AND(M29<>"", M29<>0), N29/$N$505*MATCH(AC29,'Misc Lists'!$K$2:$K$25,0), "") | AE29: =IF(AND(M29<>"", M29<>0), I29, "") | AF29: =IF(AND(M29<>"", M29<>0), N29/$N$505*MATCH(AE29,'Misc Lists'!$L$2:$L$25,0), "")
B30: 842400GJ6 | C30: N/A | D30: SOUTHERN CALIF EDISON CO SER 2018B 3.65000% 03/01/2028 BOND CALL MAKE WHOLE | E30: Corp | F30: 3.65 | G30: 46813 | H30: A2 | I30: A- | J30: 96.264 | K30: 5.019 | L30: 500(1) | N30: =IF(AND(M30<>"", M30<>0), IF(L30 <> "N/A", IF(M30>=VALUE(LEFT(L30, FIND("(", L30)-1)), J30*10*M30, 1000*M30), 1000*M30), "") | O30: =IF(AND(M30<>"",M30<>0),N30/$N$505, "") | P30: =IF(AND(M30<>"", M30<>0), F30*1000/100, "") | Q30: =IF(AND(M30<>"", M30<>0), NOW(), "") | R30: =IF(AND(M30<>"", M30<>0), ROUND((G30 - Q30)/365, 0), "") | S30: =IF(AND(M30<>"",M30<>0),MDURATION(Q30,G30,F30/100,K30/100,2), "") | T30: =IF(AND(M30<>"",M30<>0),YIELD(Q30,G30,F30/100,N30/(M30*10),100,2),"") | U30: =IF(AND(M30<>"",M30<>0), IF(E30 = "Muni", T30, IF(E30="Corp", T30*(1 -'Investor Input'!$C$4-'Investor Input'!$C$5), T30*(1 -'Investor Input'!$C$4))), T30) | V30: =IF(AND(M30<>"",M30<>0),(FV(K30/(2*100),(G30-Q30)*2/365, F30*1000/(2*100), -N30/M30))*M30, "") | W30: =IF(AND(M30<>"",M30<>0),V30-N30,"") | X30: =IF(AND(M30<>"",M30<>0),W30/N30,"") | Y30: =IF(AND(M30<>"", M30<>0), MONTH(G30), "") | Z30: =IF(AND(M30<>"", M30<>0), MONTH(EDATE(G30, 6)), "") | AA30: =IF(AND(M30<>"", M30<>0), F30*1000*M30/(100*2), "") | AB30: =IF(AND(AA30<>"",AA30<>0), IF(E30="Muni", AA30, IF(E30 = "Corp", (1-'Investor Input'!$C$4-'Investor Input'!$C$5)*AA30, (1-'Investor Input'!$C$4)*AA30)), AA30) | AC30: =IF(AND(M30<>"", M30<>0), H30, "") | AD30: =IF(AND(M30<>"", M30<>0), N30/$N$505*MATCH(AC30,'Misc Lists'!$K$2:$K$25,0), "") | AE30: =IF(AND(M30<>"", M30<>0), I30, "") | AF30: =IF(AND(M30<>"", M30<>0), N30/$N$505*MATCH(AE30,'Misc Lists'!$L$2:$L$25,0), "")
B31: 06418VHG2 | C31: N/A | D31: BANK NOVA SCOTIA B CSER B NOTE 5.10000% 02/14/2030 | E31: Corp | F31: 5.1 | G31: 47528 | H31: A2 | I31: A- | J31: 100.358 | K31: 5.016 | L31: 999(1) | N31: =IF(AND(M31<>"", M31<>0), IF(L31 <> "N/A", IF(M31>=VALUE(LEFT(L31, FIND("(", L31)-1)), J31*10*M31, 1000*M31), 1000*M31), "") | O31: =IF(AND(M31<>"",M31<>0),N31/$N$505, "") | P31: =IF(AND(M31<>"", M31<>0), F31*1000/100, "") | Q31: =IF(AND(M31<>"", M31<>0), NOW(), "") | R31: =IF(AND(M31<>"", M31<>0), ROUND((G31 - Q31)/365, 0), "") | S31: =IF(AND(M31<>"",M31<>0),MDURATION(Q31,G31,F31/100,K31/100,2), "") | T31: =IF(AND(M31<>"",M31<>0),YIELD(Q31,G31,F31/100,N31/(M31*10),100,2),"") | U31: =IF(AND(M31<>"",M31<>0), IF(E31 = "Muni", T31, IF(E31="Corp", T31*(1 -'Investor Input'!$C$4-'Investor Input'!$C$5), T31*(1 -'Investor Input'!$C$4))), T31) | V31: =IF(AND(M31<>"",M31<>0),(FV(K31/(2*100),(G31-Q31)*2/365, F31*1000/(2*100), -N31/M31))*M31, "") | W31: =IF(AND(M31<>"",M31<>0),V31-N31,"") | X31: =IF(AND(M31<>"",M31<>0),W31/N31,"") | Y31: =IF(AND(M31<>"", M31<>0), MONTH(G31), "") | Z31: =IF(AND(M31<>"", M31<>0), MONTH(EDATE(G31, 6)), "") | AA31: =IF(AND(M31<>"", M31<>0), F31*1000*M31/(100*2), "") | AB31: =IF(AND(AA31<>"",AA31<>0), IF(E31="Muni", AA31, IF(E31 = "Corp", (1-'Investor Input'!$C$4-'Investor Input'!$C$5)*AA31, (1-'Investor Input'!$C$4)*AA31)), AA31) | AC31: =IF(AND(M31<>"", M31<>0), H31, "") | AD31: =IF(AND(M31<>"", M31<>0), N31/$N$505*MATCH(AC31,'Misc Lists'!$K$2:$K$25,0), "") | AE31: =IF(AND(M31<>"", M31<>0), I31, "") | AF31: =IF(AND(M31<>"", M31<>0), N31/$N$505*MATCH(AE31,'Misc Lists'!$L$2:$L$25,0), "")
B32: 842400HU0 | C32: N/A | D32: SOUTHERN CALIF EDISON CO SER 2023A 5.30000% 03/01/2028 BOND CALL MAKE WHOLE | E32: Corp | F32: 5.3 | G32: 46813 | H32: A2 | I32: A- | J32: 100.778 | K32: 5.014 | L32: 500(1) | N32: =IF(AND(M32<>"", M32<>0), IF(L32 <> "N/A", IF(M32>=VALUE(LEFT(L32, FIND("(", L32)-1)), J32*10*M32, 1000*M32), 1000*M32), "") | O32: =IF(AND(M32<>"",M32<>0),N32/$N$505, "") | P32: =IF(AND(M32<>"", M32<>0), F32*1000/100, "") | Q32: =IF(AND(M32<>"", M32<>0), NOW(), "") | R32: =IF(AND(M32<>"", M32<>0), ROUND((G32 - Q32)/365, 0), "") | S32: =IF(AND(M32<>"",M32<>0),MDURATION(Q32,G32,F32/100,K32/100,2), "") | T32: =IF(AND(M32<>"",M32<>0),YIELD(Q32,G32,F32/100,N32/(M32*10),100,2),"") | U32: =IF(AND(M32<>"",M32<>0), IF(E32 = "Muni", T32, IF(E32="Corp", T32*(1 -'Investor Input'!$C$4-'Investor Input'!$C$5), T32*(1 -'Investor Input'!$C$4))), T32) | V32: =IF(AND(M32<>"",M32<>0),(FV(K32/(2*100),(G32-Q32)*2/365, F32*1000/(2*100), -N32/M32))*M32, "") | W32: =IF(AND(M32<>"",M32<>0),V32-N32,"") | X32: =IF(AND(M32<>"",M32<>0),W32/N32,"") | Y32: =IF(AND(M32<>"", M32<>0), MONTH(G32), "") | Z32: =IF(AND(M32<>"", M32<>0), MONTH(EDATE(G32, 6)), "") | AA32: =IF(AND(M32<>"", M32<>0), F32*1000*M32/(100*2), "") | AB32: =IF(AND(AA32<>"",AA32<>0), IF(E32="Muni", AA32, IF(E32 = "Corp", (1-'Investor Input'!$C$4-'Investor Input'!$C$5)*AA32, (1-'Investor Input'!$C$4)*AA32)), AA32) | AC32: =IF(AND(M32<>"", M32<>0), H32, "") | AD32: =IF(AND(M32<>"", M32<>0), N32/$N$505*MATCH(AC32,'Misc Lists'!$K$2:$K$25,0), "") | AE32: =IF(AND(M32<>"", M32<>0), I32, "") | AF32: =IF(AND(M32<>"", M32<>0), N32/$N$505*MATCH(AE32,'Misc Lists'!$L$2:$L$25,0), "")
B33: 756109BQ6 | C33: N/A | D33: REALTY INCOME CORP NOTE 5.05000% 01/13/2026 | E33: Corp | F33: 5.05 | G33: 46035 | H33: A3 | I33: A- | J33: 100.03 | K33: 5.004 | L33: 18(18) | N33: =IF(AND(M33<>"", M33<>0), IF(L33 <> "N/A", IF(M33>=VALUE(LEFT(L33, FIND("(", L33)-1)), J33*10*M33, 1000*M33), 1000*M33), "") | O33: =IF(AND(M33<>"",M33<>0),N33/$N$505, "") | P33: =IF(AND(M33<>"", M33<>0), F33*1000/100, "") | Q33: =IF(AND(M33<>"", M33<>0), NOW(), "") | R33: =IF(AND(M33<>"", M33<>0), ROUND((G33 - Q33)/365, 0), "") | S33: =IF(AND(M33<>"",M33<>0),MDURATION(Q33,G33,F33/100,K33/100,2), "") | T33: =IF(AND(M33<>"",M33<>0),YIELD(Q33,G33,F33/100,N33/(M33*10),100,2),"") | U33: =IF(AND(M33<>"",M33<>0), IF(E33 = "Muni", T33, IF(E33="Corp", T33*(1 -'Investor Input'!$C$4-'Investor Input'!$C$5), T33*(1 -'Investor Input'!$C$4))), T33) | V33: =IF(AND(M33<>"",M33<>0),(FV(K33/(2*100),(G33-Q33)*2/365, F33*1000/(2*100), -N33/M33))*M33, "") | W33: =IF(AND(M33<>"",M33<>0),V33-N33,"") | X33: =IF(AND(M33<>"",M33<>0),W33/N33,"") | Y33: =IF(AND(M33<>"", M33<>0), MONTH(G33), "") | Z33: =IF(AND(M33<>"", M33<>0), MONTH(EDATE(G33, 6)), "") | AA33: =IF(AND(M33<>"", M33<>0), F33*1000*M33/(100*2), "") | AB33: =IF(AND(AA33<>"",AA33<>0), IF(E33="Muni", AA33, IF(E33 = "Corp", (1-'Investor Input'!$C$4-'Investor Input'!$C$5)*AA33, (1-'Investor Input'!$C$4)*AA33)), AA33) | AC33: =IF(AND(M33<>"", M33<>0), H33, "") | AD33: =IF(AND(M33<>"", M33<>0), N33/$N$505*MATCH(AC33,'Misc Lists'!$K$2:$K$25,0), "") | AE33: =IF(AND(M33<>"", M33<>0), I33, "") | AF33: =IF(AND(M33<>"", M33<>0), N33/$N$505*MATCH(AE33,'Misc Lists'!$L$2:$L$25,0), "")
B34: 06376CHS8 | C34: N/A | D34: BANK MONTREAL MEDIUMSER I MTN 5.00000% 08/24/2028 | E34: Corp | F34: 5 | G34: 46989 | H34: A2 | I34: A- | J34: 99.99 | K34: 5.002 | L34: 940(1) | N34: =IF(AND(M34<>"", M34<>0), IF(L34 <> "N/A", IF(M34>=VALUE(LEFT(L34, FIND("(", L34)-1)), J34*10*M34, 1000*M34), 1000*M34), "") | O34: =IF(AND(M34<>"",M34<>0),N34/$N$505, "") | P34: =IF(AND(M34<>"", M34<>0), F34*1000/100, "") | Q34: =IF(AND(M34<>"", M34<>0), NOW(), "") | R34: =IF(AND(M34<>"", M34<>0), ROUND((G34 - Q34)/365, 0), "") | S34: =IF(AND(M34<>"",M34<>0),MDURATION(Q34,G34,F34/100,K34/100,2), "") | T34: =IF(AND(M34<>"",M34<>0),YIELD(Q34,G34,F34/100,N34/(M34*10),100,2),"") | U34: =IF(AND(M34<>"",M34<>0), IF(E34 = "Muni", T34, IF(E34="Corp", T34*(1 -'Investor Input'!$C$4-'Investor Input'!$C$5), T34*(1 -'Investor Input'!$C$4))), T34) | V34: =IF(AND(M34<>"",M34<>0),(FV(K34/(2*100),(G34-Q34)*2/365, F34*1000/(2*100), -N34/M34))*M34, "") | W34: =IF(AND(M34<>"",M34<>0),V34-N34,"") | X34: =IF(AND(M34<>"",M34<>0),W34/N34,"") | Y34: =IF(AND(M34<>"", M34<>0), MONTH(G34), "") | Z34: =IF(AND(M34<>"", M34<>0), MONTH(EDATE(G34, 6)), "") | AA34: =IF(AND(M34<>"", M34<>0), F34*1000*M34/(100*2), "") | AB34: =IF(AND(AA34<>"",AA34<>0), IF(E34="Muni", AA34, IF(E34 = "Corp", (1-'Investor Input'!$C$4-'Investor Input'!$C$5)*AA34, (1-'Investor Input'!$C$4)*AA34)), AA34) | AC34: =IF(AND(M34<>"", M34<>0), H34, "") | AD34: =IF(AND(M34<>"", M34<>0), N34/$N$505*MATCH(AC34,'Misc Lists'!$K$2:$K$25,0), "") | AE34: =IF(AND(M34<>"", M34<>0), I34, "") | AF34: =IF(AND(M34<>"", M34<>0), N34/$N$505*MATCH(AE34,'Misc Lists'!$L$2:$L$25,0), "")
B35: 05964HBJ3 | C35: N/A | D35: BANCO SANTANDER S.A.SER 241 NOTE 5.56500% 01/17/2030 | E35: Corp | F35: 5.565 | G35: 47500 | H35: BAA1 | I35: A- | J35: 102.396 | K35: 5.001 | L35: 500(200) | N35: =IF(AND(M35<>"", M35<>0), IF(L35 <> "N/A", IF(M35>=VALUE(LEFT(L35, FIND("(", L35)-1)), J35*10*M35, 1000*M35), 1000*M35), "") | O35: =IF(AND(M35<>"",M35<>0),N35/$N$505, "") | P35: =IF(AND(M35<>"", M35<>0), F35*1000/100, "") | Q35: =IF(AND(M35<>"", M35<>0), NOW(), "") | R35: =IF(AND(M35<>"", M35<>0), ROUND((G35 - Q35)/365, 0), "") | S35: =IF(AND(M35<>"",M35<>0),MDURATION(Q35,G35,F35/100,K35/100,2), "") | T35: =IF(AND(M35<>"",M35<>0),YIELD(Q35,G35,F35/100,N35/(M35*10),100,2),"") | U35: =IF(AND(M35<>"",M35<>0), IF(E35 = "Muni", T35, IF(E35="Corp", T35*(1 -'Investor Input'!$C$4-'Investor Input'!$C$5), T35*(1 -'Investor Input'!$C$4))), T35) | V35: =IF(AND(M35<>"",M35<>0),(FV(K35/(2*100),(G35-Q35)*2/365, F35*1000/(2*100), -N35/M35))*M35, "") | W35: =IF(AND(M35<>"",M35<>0),V35-N35,"") | X35: =IF(AND(M35<>"",M35<>0),W35/N35,"") | Y35: =IF(AND(M35<>"", M35<>0), MONTH(G35), "") | Z35: =IF(AND(M35<>"", M35<>0), MONTH(EDATE(G35, 6)), "") | AA35: =IF(AND(M35<>"", M35<>0), F35*1000*M35/(100*2), "") | AB35: =IF(AND(AA35<>"",AA35<>0), IF(E35="Muni", AA35, IF(E35 = "Corp", (1-'Investor Input'!$C$4-'Investor Input'!$C$5)*AA35, (1-'Investor Input'!$C$4)*AA35)), AA35) | AC35: =IF(AND(M35<>"", M35<>0), H35, "") | AD35: =IF(AND(M35<>"", M35<>0), N35/$N$505*MATCH(AC35,'Misc Lists'!$K$2:$K$25,0), "") | AE35: =IF(AND(M35<>"", M35<>0), I35, "") | AF35: =IF(AND(M35<>"", M35<>0), N35/$N$505*MATCH(AE35,'Misc Lists'!$L$2:$L$25,0), "")
B36: 842400HY2 | C36: N/A | D36: SOUTHERN CALIF EDISON CO SER 2023E 5.65000% 10/01/2028 BOND CALL MAKE WHOLE | E36: Corp | F36: 5.65 | G36: 47027 | H36: A2 | I36: A- | J36: 102.106 | K36: 4.995 | L36: 200(1) | N36: =IF(AND(M36<>"", M36<>0), IF(L36 <> "N/A", IF(M36>=VALUE(LEFT(L36, FIND("(", L36)-1)), J36*10*M36, 1000*M36), 1000*M36), "") | O36: =IF(AND(M36<>"",M36<>0),N36/$N$505, "") | P36: =IF(AND(M36<>"", M36<>0), F36*1000/100, "") | Q36: =IF(AND(M36<>"", M36<>0), NOW(), "") | R36: =IF(AND(M36<>"", M36<>0), ROUND((G36 - Q36)/365, 0), "") | S36: =IF(AND(M36<>"",M36<>0),MDURATION(Q36,G36,F36/100,K36/100,2), "") | T36: =IF(AND(M36<>"",M36<>0),YIELD(Q36,G36,F36/100,N36/(M36*10),100,2),"") | U36: =IF(AND(M36<>"",M36<>0), IF(E36 = "Muni", T36, IF(E36="Corp", T36*(1 -'Investor Input'!$C$4-'Investor Input'!$C$5), T36*(1 -'Investor Input'!$C$4))), T36) | V36: =IF(AND(M36<>"",M36<>0),(FV(K36/(2*100),(G36-Q36)*2/365, F36*1000/(2*100), -N36/M36))*M36, "") | W36: =IF(AND(M36<>"",M36<>0),V36-N36,"") | X36: =IF(AND(M36<>"",M36<>0),W36/N36,"") | Y36: =IF(AND(M36<>"", M36<>0), MONTH(G36), "") | Z36: =IF(AND(M36<>"", M36<>0), MONTH(EDATE(G36, 6)), "") | AA36: =IF(AND(M36<>"", M36<>0), F36*1000*M36/(100*2), "") | AB36: =IF(AND(AA36<>"",AA36<>0), IF(E36="Muni", AA36, IF(E36 = "Corp", (1-'Investor Input'!$C$4-'Investor Input'!$C$5)*AA36, (1-'Investor Input'!$C$4)*AA36)), AA36) | AC36: =IF(AND(M36<>"", M36<>0), H36, "") | AD36: =IF(AND(M36<>"", M36<>0), N36/$N$505*MATCH(AC36,'Misc Lists'!$K$2:$K$25,0), "") | AE36: =IF(AND(M36<>"", M36<>0), I36, "") | AF36: =IF(AND(M36<>"", M36<>0), N36/$N$505*MATCH(AE36,'Misc Lists'!$L$2:$L$25,0), "")
... B43: 04686JAB7 | C43: N/A | D43: ATHENE HOLDING LTD NOTE CALL MAKE WHOLE6.15000% 04/03/2030 | E43: Corp | F43: 6.15 | G43: 47576 | H43: BAA1 | I43: A- | J43: 105.323 | K43: 4.947 | L43: 500(9) | N43: =IF(AND(M43<>"", M43<>0), IF(L43 <> "N/A", IF(M43>=VALUE(LEFT(L43, FIND("(", L43)-1)), J43*10*M43, 1000*M43), 1000*M43), "") | O43: =IF(AND(M43<>"",M43<>0),N43/$N$505, "") | P43: =IF(AND(M43<>"", M43<>0), F43*1000/100, "") | Q43: =IF(AND(M43<>"", M43<>0), NOW(), "") | R43: =IF(AND(M43<>"", M43<>0), ROUND((G43 - Q43)/365, 0), "") | S43: =IF(AND(M43<>"",M43<>0),MDURATION(Q43,G43,F43/100,K43/100,2), "") | T43: =IF(AND(M43<>"",M43<>0),YIELD(Q43,G43,F43/100,N43/(M43*10),100,2),"") | U43: =IF(AND(M43<>"",M43<>0), IF(E43 = "Muni", T43, IF(E43="Corp", T43*(1 -'Investor Input'!$C$4-'Investor Input'!$C$5), T43*(1 -'Investor Input'!$C$4))), T43) | V43: =IF(AND(M43<>"",M43<>0),(FV(K43/(2*100),(G43-Q43)*2/365, F43*1000/(2*100), -N43/M43))*M43, "") | W43: =IF(AND(M43<>"",M43<>0),V43-N43,"") | X43: =IF(AND(M43<>"",M43<>0),W43/N43,"") | Y43: =IF(AND(M43<>"", M43<>0), MONTH(G43), "") | Z43: =IF(AND(M43<>"", M43<>0), MONTH(EDATE(G43, 6)), "") | AA43: =IF(AND(M43<>"", M43<>0), F43*1000*M43/(100*2), "") | AB43: =IF(AND(AA43<>"",AA43<>0), IF(E43="Muni", AA43, IF(E43 = "Corp", (1-'Investor Input'!$C$4-'Investor Input'!$C$5)*AA43, (1-'Investor Input'!$C$4)*AA43)), AA43) | AC43: =IF(AND(M43<>"", M43<>0), H43, "") | AD43: =IF(AND(M43<>"", M43<>0), N43/$N$505*MATCH(AC43,'Misc Lists'!$K$2:$K$25,0), "") | AE43: =IF(AND(M43<>"", M43<>0), I43, "") | AF43: =IF(AND(M43<>"", M43<>0), N43/$N$505*MATCH(AE43,'Misc Lists'!$L$2:$L$25,0), "")
B44: 48130CGM1 | C44: N/A | D44: JPMORGAN CHASE &CO SER E MTN 5.00000% 02/15/2029 | E44: Corp | F44: 5 | G44: 47164 | H44: A1 | I44: A | J44: 100.201 | K44: 4.942 | L44: 1(1) | M44: 10 | N44: =IF(AND(M44<>"", M44<>0), IF(L44 <> "N/A", IF(M44>=VALUE(LEFT(L44, FIND("(", L44)-1)), J44*10*M44, 1000*M44), 1000*M44), "") -> 10020.1 | O44: =IF(AND(M44<>"",M44<>0),N44/$N$505, "") -> 0.010019689 | P44: =IF(AND(M44<>"", M44<>0), F44*1000/100, "") -> 50 | Q44: =IF(AND(M44<>"", M44<>0), NOW(), "") -> 45791.491 | R44: =IF(AND(M44<>"", M44<>0), ROUND((G44 - Q44)/365, 0), "") -> 4 | S44: =IF(AND(M44<>"",M44<>0),MDURATION(Q44,G44,F44/100,K44/100,2), "") -> 3.3452195 | T44: =IF(AND(M44<>"",M44<>0),YIELD(Q44,G44,F44/100,N44/(M44*10),100,2),"") -> 0.049384169 | U44: =IF(AND(M44<>"",M44<>0), IF(E44 = "Muni", T44, IF(E44="Corp", T44*(1 -'Investor Input'!$C$4-'Investor Input'!$C$5), T44*(1 -'Investor Input'!$C$4))), T44) -> 0.026667451 | V44: =IF(AND(M44<>"",M44<>0),(FV(K44/(2*100),(G44-Q44)*2/365, F44*1000/(2*100), -N44/M44))*M44, "") -> 10000.501 | W44: =IF(AND(M44<>"",M44<>0),V44-N44,"") -> -19.598672 | X44: =IF(AND(M44<>"",M44<>0),W44/N44,"") -> -0.0019559358 | Y44: =IF(AND(M44<>"", M44<>0), MONTH(G44), "") -> 2 | Z44: =IF(AND(M44<>"", M44<>0), MONTH(EDATE(G44, 6)), "") -> 8 | AA44: =IF(AND(M44<>"", M44<>0), F44*1000*M44/(100*2), "") -> 250 | AB44: =IF(AND(AA44<>"",AA44<>0), IF(E44="Muni", AA44, IF(E44 = "Corp", (1-'Investor Input'!$C$4-'Investor Input'!$C$5)*AA44, (1-'Investor Input'!$C$4)*AA44)), AA44) -> 135 | AC44: =IF(AND(M44<>"", M44<>0), H44, "") -> A1 | AD44: =IF(AND(M44<>"", M44<>0), N44/$N$505*MATCH(AC44,'Misc Lists'!$K$2:$K$25,0), "") -> 0.060118132 | AE44: =IF(AND(M44<>"", M44<>0), I44, "") -> A | AF44: =IF(AND(M44<>"", M44<>0), N44/$N$505*MATCH(AE44,'Misc Lists'!$L$2:$L$25,0), "") -> 0.070137821
B45: 89114XHB2 | C45: N/A | D45: TORONTO DOMINION BK ONT SER D MTN 5.00000% 02/27/2028 | E45: Corp | F45: 5 | G45: 46810 | H45: A2 | I45: A- | J45: 100.175 | K45: 4.935 | L45: 798(1) | N45: =IF(AND(M45<>"", M45<>0), IF(L45 <> "N/A", IF(M45>=VALUE(LEFT(L45, FIND("(", L45)-1)), J45*10*M45, 1000*M45), 1000*M45), "") | O45: =IF(AND(M45<>"",M45<>0),N45/$N$505, "") | P45: =IF(AND(M45<>"", M45<>0), F45*1000/100, "") | Q45: =IF(AND(M45<>"", M45<>0), NOW(), "") | R45: =IF(AND(M45<>"", M45<>0), ROUND((G45 - Q45)/365, 0), "") | S45: =IF(AND(M45<>"",M45<>0),MDURATION(Q45,G45,F45/100,K45/100,2), "") | T45: =IF(AND(M45<>"",M45<>0),YIELD(Q45,G45,F45/100,N45/(M45*10),100,2),"") | U45: =IF(AND(M45<>"",M45<>0), IF(E45 = "Muni", T45, IF(E45="Corp", T45*(1 -'Investor Input'!$C$4-'Investor Input'!$C$5), T45*(1 -'Investor Input'!$C$4))), T45) | V45: =IF(AND(M45<>"",M45<>0),(FV(K45/(2*100),(G45-Q45)*2/365, F45*1000/(2*100), -N45/M45))*M45, "") | W45: =IF(AND(M45<>"",M45<>0),V45-N45,"") | X45: =IF(AND(M45<>"",M45<>0),W45/N45,"") | Y45: =IF(AND(M45<>"", M45<>0), MONTH(G45), "") | Z45: =IF(AND(M45<>"", M45<>0), MONTH(EDATE(G45, 6)), "") | AA45: =IF(AND(M45<>"", M45<>0), F45*1000*M45/(100*2), "") | AB45: =IF(AND(AA45<>"",AA45<>0), IF(E45="Muni", AA45, IF(E45 = "Corp", (1-'Investor Input'!$C$4-'Investor Input'!$C$5)*AA45, (1-'Investor Input'!$C$4)*AA45)), AA45) | AC45: =IF(AND(M45<>"", M45<>0), H45, "") | AD45: =IF(AND(M45<>"", M45<>0), N45/$N$505*MATCH(AC45,'Misc Lists'!$K$2:$K$25,0), "") | AE45: =IF(AND(M45<>"", M45<>0), I45, "") | AF45: =IF(AND(M45<>"", M45<>0), N45/$N$505*MATCH(AE45,'Misc Lists'!$L$2:$L$25,0), "")
B46: 06418VKK9 | C46: N/A | D46: BANK NOVA SCOTIA B CSER B NOTE 5.00000% 02/28/2029 | E46: Corp | F46: 5 | G46: 47177 | H46: A2 | I46: A- | J46: 100.23 | K46: 4.935 | L46: 871(1) | N46: =IF(AND(M46<>"", M46<>0), IF(L46 <> "N/A", IF(M46>=VALUE(LEFT(L46, FIND("(", L46)-1)), J46*10*M46, 1000*M46), 1000*M46), "") | O46: =IF(AND(M46<>"",M46<>0),N46/$N$505, "") | P46: =IF(AND(M46<>"", M46<>0), F46*1000/100, "") | Q46: =IF(AND(M46<>"", M46<>0), NOW(), "") | R46: =IF(AND(M46<>"", M46<>0), ROUND((G46 - Q46)/365, 0), "") | S46: =IF(AND(M46<>"",M46<>0),MDURATION(Q46,G46,F46/100,K46/100,2), "") | T46: =IF(AND(M46<>"",M46<>0),YIELD(Q46,G46,F46/100,N46/(M46*10),100,2),"") | U46: =IF(AND(M46<>"",M46<>0), IF(E46 = "Muni", T46, IF(E46="Corp", T46*(1 -'Investor Input'!$C$4-'Investor Input'!$C$5), T46*(1 -'Investor Input'!$C$4))), T46) | V46: =IF(AND(M46<>"",M46<>0),(FV(K46/(2*100),(G46-Q46)*2/365, F46*1000/(2*100), -N46/M46))*M46, "") | W46: =IF(AND(M46<>"",M46<>0),V46-N46,"") | X46: =IF(AND(M46<>"",M46<>0),W46/N46,"") | Y46: =IF(AND(M46<>"", M46<>0), MONTH(G46), "") | Z46: =IF(AND(M46<>"", M46<>0), MONTH(EDATE(G46, 6)), "") | AA46: =IF(AND(M46<>"", M46<>0), F46*1000*M46/(100*2), "") | AB46: =IF(AND(AA46<>"",AA46<>0), IF(E46="Muni", AA46, IF(E46 = "Corp", (1-'Investor Input'!$C$4-'Investor Input'!$C$5)*AA46, (1-'Investor Input'!$C$4)*AA46)), AA46) | AC46: =IF(AND(M46<>"", M46<>0), H46, "") | AD46: =IF(AND(M46<>"", M46<>0), N46/$N$505*MATCH(AC46,'Misc Lists'!$K$2:$K$25,0), "") | AE46: =IF(AND(M46<>"", M46<>0), I46, "") | AF46: =IF(AND(M46<>"", M46<>0), N46/$N$505*MATCH(AE46,'Misc Lists'!$L$2:$L$25,0), "")
B47: 05463HAB7 | C47: N/A | D47: AXIS SPECIALTY FINANCE LLC NOTE 3.90000% 07/15/2029 CALL MAKE WHOLE | E47: Corp | F47: 3.9 | G47: 47314 | H47: BAA1 | I47: A- | J47: 96.062 | K47: 4.917 | L47: 25(2) | N47: =IF(AND(M47<>"", M47<>0), IF(L47 <> "N/A", IF(M47>=VALUE(LEFT(L47, FIND("(", L47)-1)), J47*10*M47, 1000*M47), 1000*M47), "") | O47: =IF(AND(M47<>"",M47<>0),N47/$N$505, "") | P47: =IF(AND(M47<>"", M47<>0), F47*1000/100, "") | Q47: =IF(AND(M47<>"", M47<>0), NOW(), "") | R47: =IF(AND(M47<>"", M47<>0), ROUND((G47 - Q47)/365, 0), "") | S47: =IF(AND(M47<>"",M47<>0),MDURATION(Q47,G47,F47/100,K47/100,2), "") | T47: =IF(AND(M47<>"",M47<>0),YIELD(Q47,G47,F47/100,N47/(M47*10),100,2),"") | U47: =IF(AND(M47<>"",M47<>0), IF(E47 = "Muni", T47, IF(E47="Corp", T47*(1 -'Investor Input'!$C$4-'Investor Input'!$C$5), T47*(1 -'Investor Input'!$C$4))), T47) | V47: =IF(AND(M47<>"",M47<>0),(FV(K47/(2*100),(G47-Q47)*2/365, F47*1000/(2*100), -N47/M47))*M47, "") | W47: =IF(AND(M47<>"",M47<>0),V47-N47,"") | X47: =IF(AND(M47<>"",M47<>0),W47/N47,"") | Y47: =IF(AND(M47<>"", M47<>0), MONTH(G47), "") | Z47: =IF(AND(M47<>"", M47<>0), MONTH(EDATE(G47, 6)), "") | AA47: =IF(AND(M47<>"", M47<>0), F47*1000*M47/(100*2), "") | AB47: =IF(AND(AA47<>"",AA47<>0), IF(E47="Muni", AA47, IF(E47 = "Corp", (1-'Investor Input'!$C$4-'Investor Input'!$C$5)*AA47, (1-'Investor Input'!$C$4)*AA47)), AA47) | AC47: =IF(AND(M47<>"", M47<>0), H47, "") | AD47: =IF(AND(M47<>"", M47<>0), N47/$N$505*MATCH(AC47,'Misc Lists'!$K$2:$K$25,0), "") | AE47: =IF(AND(M47<>"", M47<>0), I47, "") | AF47: =IF(AND(M47<>"", M47<>0), N47/$N$505*MATCH(AE47,'Misc Lists'!$L$2:$L$25,0), "")
B48: 842400HS5 | C48: N/A | D48: SOUTHERN CALIF EDISON CO SER 2022F 5.85000% 11/01/2027 BOND CALL MAKE WHOLE | E48: Corp | F48: 5.85 | G48: 46692 | H48: A2 | I48: A- | J48: 102.279 | K48: 4.915 | L48: 1,000(1) | N48: =IF(AND(M48<>"", M48<>0), IF(L48 <> "N/A", IF(M48>=VALUE(LEFT(L48, FIND("(", L48)-1)), J48*10*M48, 1000*M48), 1000*M48), "") | O48: =IF(AND(M48<>"",M48<>0),N48/$N$505, "") | P48: =IF(AND(M48<>"", M48<>0), F48*1000/100, "") | Q48: =IF(AND(M48<>"", M48<>0), NOW(), "") | R48: =IF(AND(M48<>"", M48<>0), ROUND((G48 - Q48)/365, 0), "") | S48: =IF(AND(M48<>"",M48<>0),MDURATION(Q48,G48,F48/100,K48/100,2), "") | T48: =IF(AND(M48<>"",M48<>0),YIELD(Q48,G48,F48/100,N48/(M48*10),100,2),"") | U48: =IF(AND(M48<>"",M48<>0), IF(E48 = "Muni", T48, IF(E48="Corp", T48*(1 -'Investor Input'!$C$4-'Investor Input'!$C$5), T48*(1 -'Investor Input'!$C$4))), T48) | V48: =IF(AND(M48<>"",M48<>0),(FV(K48/(2*100),(G48-Q48)*2/365, F48*1000/(2*100), -N48/M48))*M48, "") | W48: =IF(AND(M48<>"",M48<>0),V48-N48,"") | X48: =IF(AND(M48<>"",M48<>0),W48/N48,"") | Y48: =IF(AND(M48<>"", M48<>0), MONTH(G48), "") | Z48: =IF(AND(M48<>"", M48<>0), MONTH(EDATE(G48, 6)), "") | AA48: =IF(AND(M48<>"", M48<>0), F48*1000*M48/(100*2), "") | AB48: =IF(AND(AA48<>"",AA48<>0), IF(E48="Muni", AA48, IF(E48 = "Corp", (1-'Investor Input'!$C$4-'Investor Input'!$C$5)*AA48, (1-'Investor Input'!$C$4)*AA48)), AA48) | AC48: =IF(AND(M48<>"", M48<>0), H48, "") | AD48: =IF(AND(M48<>"", M48<>0), N48/$N$505*MATCH(AC48,'Misc Lists'!$K$2:$K$25,0), "") | AE48: =IF(AND(M48<>"", M48<>0), I48, "") | AF48: =IF(AND(M48<>"", M48<>0), N48/$N$505*MATCH(AE48,'Misc Lists'!$L$2:$L$25,0), "")
B49: 512807AN8 | C49: N/A | D49: LAM RESEARCH CORP NOTE 3.80000% 03/15/2025 | E49: Corp | F49: 3.8 | G49: 45731 | H49: A2 | I49: A- | J49: 99.99 | K49: 4.909 | L49: 500(10) | N49: =IF(AND(M49<>"", M49<>0), IF(L49 <> "N/A", IF(M49>=VALUE(LEFT(L49, FIND("(", L49)-1)), J49*10*M49, 1000*M49), 1000*M49), "") | O49: =IF(AND(M49<>"",M49<>0),N49/$N$505, "") | P49: =IF(AND(M49<>"", M49<>0), F49*1000/100, "") | Q49: =IF(AND(M49<>"", M49<>0), NOW(), "") | R49: =IF(AND(M49<>"", M49<>0), ROUND((G49 - Q49)/365, 0), "") | S49: =IF(AND(M49<>"",M49<>0),MDURATION(Q49,G49,F49/100,K49/100,2), "") | T49: =IF(AND(M49<>"",M49<>0),YIELD(Q49,G49,F49/100,N49/(M49*10),100,2),"") | U49: =IF(AND(M49<>"",M49<>0), IF(E49 = "Muni", T49, IF(E49="Corp", T49*(1 -'Investor Input'!$C$4-'Investor Input'!$C$5), T49*(1 -'Investor Input'!$C$4))), T49) | V49: =IF(AND(M49<>"",M49<>0),(FV(K49/(2*100),(G49-Q49)*2/365, F49*1000/(2*100), -N49/M49))*M49, "") | W49: =IF(AND(M49<>"",M49<>0),V49-N49,"") | X49: =IF(AND(M49<>"",M49<>0),W49/N49,"") | Y49: =IF(AND(M49<>"", M49<>0), MONTH(G49), "") | Z49: =IF(AND(M49<>"", M49<>0), MONTH(EDATE(G49, 6)), "") | AA49: =IF(AND(M49<>"", M49<>0), F49*1000*M49/(100*2), "") | AB49: =IF(AND(AA49<>"",AA49<>0), IF(E49="Muni", AA49, IF(E49 = "Corp", (1-'Investor Input'!$C$4-'Investor Input'!$C$5)*AA49, (1-'Investor Input'!$C$4)*AA49)), AA49) | AC49: =IF(AND(M49<>"", M49<>0), H49, "") | AD49: =IF(AND(M49<>"", M49<>0), N49/$N$505*MATCH(AC49,'Misc Lists'!$K$2:$K$25,0), "") | AE49: =IF(AND(M49<>"", M49<>0), I49, "") | AF49: =IF(AND(M49<>"", M49<>0), N49/$N$505*MATCH(AE49,'Misc Lists'!$L$2:$L$25,0), "")
B50: 48135NTF3 | C50: N/A | D50: JPMORGAN CHASE FINL CO LLC SER A MTN 5.00000% 02/14/2030 | E50: Corp | F50: 5 | G50: 47528 | H50: A1 | I50: A | J50: 100.398 | K50: 4.907 | L50: 1,454(1) | N50: =IF(AND(M50<>"", M50<>0), IF(L50 <> "N/A", IF(M50>=VALUE(LEFT(L50, FIND("(", L50)-1)), J50*10*M50, 1000*M50), 1000*M50), "") | O50: =IF(AND(M50<>"",M50<>0),N50/$N$505, "") | P50: =IF(AND(M50<>"", M50<>0), F50*1000/100, "") | Q50: =IF(AND(M50<>"", M50<>0), NOW(), "") | R50: =IF(AND(M50<>"", M50<>0), ROUND((G50 - Q50)/365, 0), "") | S50: =IF(AND(M50<>"",M50<>0),MDURATION(Q50,G50,F50/100,K50/100,2), "") | T50: =IF(AND(M50<>"",M50<>0),YIELD(Q50,G50,F50/100,N50/(M50*10),100,2),"") | U50: =IF(AND(M50<>"",M50<>0), IF(E50 = "Muni", T50, IF(E50="Corp", T50*(1 -'Investor Input'!$C$4-'Investor Input'!$C$5), T50*(1 -'Investor Input'!$C$4))), T50) | V50: =IF(AND(M50<>"",M50<>0),(FV(K50/(2*100),(G50-Q50)*2/365, F50*1000/(2*100), -N50/M50))*M50, "") | W50: =IF(AND(M50<>"",M50<>0),V50-N50,"") | X50: =IF(AND(M50<>"",M50<>0),W50/N50,"") | Y50: =IF(AND(M50<>"", M50<>0), MONTH(G50), "") | Z50: =IF(AND(M50<>"", M50<>0), MONTH(EDATE(G50, 6)), "") | AA50: =IF(AND(M50<>"", M50<>0), F50*1000*M50/(100*2), "") | AB50: =IF(AND(AA50<>"",AA50<>0), IF(E50="Muni", AA50, IF(E50 = "Corp", (1-'Investor Input'!$C$4-'Investor Input'!$C$5)*AA50, (1-'Investor Input'!$C$4)*AA50)), AA50) | AC50: =IF(AND(M50<>"", M50<>0), H50, "") | AD50: =IF(AND(M50<>"", M50<>0), N50/$N$505*MATCH(AC50,'Misc Lists'!$K$2:$K$25,0), "") | AE50: =IF(AND(M50<>"", M50<>0), I50, "") | AF50: =IF(AND(M50<>"", M50<>0), N50/$N$505*MATCH(AE50,'Misc Lists'!$L$2:$L$25,0), "")
B51: 48135NTT3 | C51: N/A | D51: JPMORGAN CHASE FINL CO LLC SER A MTN 5.00000% 02/28/2030 | E51: Corp | F51: 5 | G51: 47542 | H51: A1 | I51: A | J51: 100.417 | K51: 4.904 | L51: 723(1) | N51: =IF(AND(M51<>"", M51<>0), IF(L51 <> "N/A", IF(M51>=VALUE(LEFT(L51, FIND("(", L51)-1)), J51*10*M51, 1000*M51), 1000*M51), "") | O51: =IF(AND(M51<>"",M51<>0),N51/$N$505, "") | P51: =IF(AND(M51<>"", M51<>0), F51*1000/100, "") | Q51: =IF(AND(M51<>"", M51<>0), NOW(), "") | R51: =IF(AND(M51<>"", M51<>0), ROUND((G51 - Q51)/365, 0), "") | S51: =IF(AND(M51<>"",M51<>0),MDURATION(Q51,G51,F51/100,K51/100,2), "") | T51: =IF(AND(M51<>"",M51<>0),YIELD(Q51,G51,F51/100,N51/(M51*10),100,2),"") | U51: =IF(AND(M51<>"",M51<>0), IF(E51 = "Muni", T51, IF(E51="Corp", T51*(1 -'Investor Input'!$C$4-'Investor Input'!$C$5), T51*(1 -'Investor Input'!$C$4))), T51) | V51: =IF(AND(M51<>"",M51<>0),(FV(K51/(2*100),(G51-Q51)*2/365, F51*1000/(2*100), -N51/M51))*M51, "") | W51: =IF(AND(M51<>"",M51<>0),V51-N51,"") | X51: =IF(AND(M51<>"",M51<>0),W51/N51,"") | Y51: =IF(AND(M51<>"", M51<>0), MONTH(G51), "") | Z51: =IF(AND(M51<>"", M51<>0), MONTH(EDATE(G51, 6)), "") | AA51: =IF(AND(M51<>"", M51<>0), F51*1000*M51/(100*2), "") | AB51: =IF(AND(AA51<>"",AA51<>0), IF(E51="Muni", AA51, IF(E51 = "Corp", (1-'Investor Input'!$C$4-'Investor Input'!$C$5)*AA51, (1-'Investor Input'!$C$4)*AA51)), AA51) | AC51: =IF(AND(M51<>"", M51<>0), H51, "") | AD51: =IF(AND(M51<>"", M51<>0), N51/$N$505*MATCH(AC51,'Misc Lists'!$K$2:$K$25,0), "") | AE51: =IF(AND(M51<>"", M51<>0), I51, "") | AF51: =IF(AND(M51<>"", M51<>0), N51/$N$505*MATCH(AE51,'Misc Lists'!$L$2:$L$25,0), "")
B52: 75968NAD3 | C52: N/A | D52: RENAISSANCERE HLDGS LTD NOTE 3.60000% 04/15/2029 CALL MAKE WHOLE | E52: Corp | F52: 3.6 | G52: 47223 | H52: A3 | I52: A- | J52: 95.243 | K52: 4.896 | L52: 475(10) | N52: =IF(AND(M52<>"", M52<>0), IF(L52 <> "N/A", IF(M52>=VALUE(LEFT(L52, FIND("(", L52)-1)), J52*10*M52, 1000*M52), 1000*M52), "") | O52: =IF(AND(M52<>"",M52<>0),N52/$N$505, "") | P52: =IF(AND(M52<>"", M52<>0), F52*1000/100, "") | Q52: =IF(AND(M52<>"", M52<>0), NOW(), "") | R52: =IF(AND(M52<>"", M52<>0), ROUND((G52 - Q52)/365, 0), "") | S52: =IF(AND(M52<>"",M52<>0),MDURATION(Q52,G52,F52/100,K52/100,2), "") | T52: =IF(AND(M52<>"",M52<>0),YIELD(Q52,G52,F52/100,N52/(M52*10),100,2),"") | U52: =IF(AND(M52<>"",M52<>0), IF(E52 = "Muni", T52, IF(E52="Corp", T52*(1 -'Investor Input'!$C$4-'Investor Input'!$C$5), T52*(1 -'Investor Input'!$C$4))), T52) | V52: =IF(AND(M52<>"",M52<>0),(FV(K52/(2*100),(G52-Q52)*2/365, F52*1000/(2*100), -N52/M52))*M52, "") | W52: =IF(AND(M52<>"",M52<>0),V52-N52,"") | X52: =IF(AND(M52<>"",M52<>0),W52/N52,"") | Y52: =IF(AND(M52<>"", M52<>0), MONTH(G52), "") | Z52: =IF(AND(M52<>"", M52<>0), MONTH(EDATE(G52, 6)), "") | AA52: =IF(AND(M52<>"", M52<>0), F52*1000*M52/(100*2), "") | AB52: =IF(AND(AA52<>"",AA52<>0), IF(E52="Muni", AA52, IF(E52 = "Corp", (1-'Investor Input'!$C$4-'Investor Input'!$C$5)*AA52, (1-'Investor Input'!$C$4)*AA52)), AA52) | AC52: =IF(AND(M52<>"", M52<>0), H52, "") | AD52: =IF(AND(M52<>"", M52<>0), N52/$N$505*MATCH(AC52,'Misc Lists'!$K$2:$K$25,0), "") | AE52: =IF(AND(M52<>"", M52<>0), I52, "") | AF52: =IF(AND(M52<>"", M52<>0), N52/$N$505*MATCH(AE52,'Misc Lists'!$L$2:$L$25,0), "")
B53: 26875PAM3 | C53: N/A | D53: EOG RES INC NOTE 3.15000% 04/01/2025 | E53: Corp | F53: 3.15 | G53: 45748 | H53: A3 | I53: A- | J53: 99.905 | K53: 4.886 | L53: 310(5) | N53: =IF(AND(M53<>"", M53<>0), IF(L53 <> "N/A", IF(M53>=VALUE(LEFT(L53, FIND("(", L53)-1)), J53*10*M53, 1000*M53), 1000*M53), "") | O53: =IF(AND(M53<>"",M53<>0),N53/$N$505, "") | P53: =IF(AND(M53<>"", M53<>0), F53*1000/100, "") | Q53: =IF(AND(M53<>"", M53<>0), NOW(), "") | R53: =IF(AND(M53<>"", M53<>0), ROUND((G53 - Q53)/365, 0), "") | S53: =IF(AND(M53<>"",M53<>0),MDURATION(Q53,G53,F53/100,K53/100,2), "") | T53: =IF(AND(M53<>"",M53<>0),YIELD(Q53,G53,F53/100,N53/(M53*10),100,2),"") | U53: =IF(AND(M53<>"",M53<>0), IF(E53 = "Muni", T53, IF(E53="Corp", T53*(1 -'Investor Input'!$C$4-'Investor Input'!$C$5), T53*(1 -'Investor Input'!$C$4))), T53) | V53: =IF(AND(M53<>"",M53<>0),(FV(K53/(2*100),(G53-Q53)*2/365, F53*1000/(2*100), -N53/M53))*M53, "") | W53: =IF(AND(M53<>"",M53<>0),V53-N53,"") | X53: =IF(AND(M53<>"",M53<>0),W53/N53,"") | Y53: =IF(AND(M53<>"", M53<>0), MONTH(G53), "") | Z53: =IF(AND(M53<>"", M53<>0), MONTH(EDATE(G53, 6)), "") | AA53: =IF(AND(M53<>"", M53<>0), F53*1000*M53/(100*2), "") | AB53: =IF(AND(AA53<>"",AA53<>0), IF(E53="Muni", AA53, IF(E53 = "Corp", (1-'Investor Input'!$C$4-'Investor Input'!$C$5)*AA53, (1-'Investor Input'!$C$4)*AA53)), AA53) | AC53: =IF(AND(M53<>"", M53<>0), H53, "") | AD53: =IF(AND(M53<>"", M53<>0), N53/$N$505*MATCH(AC53,'Misc Lists'!$K$2:$K$25,0), "") | AE53: =IF(AND(M53<>"", M53<>0), I53, "") | AF53: =IF(AND(M53<>"", M53<>0), N53/$N$505*MATCH(AE53,'Misc Lists'!$L$2:$L$25,0), "")
B54: 759351AN9 | C54: N/A | D54: REINSURANCE GROUP AMER INC SER 6.45 3.90000% 05/15/2029 NOTE CALL MAKE WHOLE | E54: Corp | F54: 3.9 | G54: 47253 | H54: BAA1 | I54: A | J54: 96.346 | K54: 4.876 | L54: 200(2) | N54: =IF(AND(M54<>"", M54<>0), IF(L54 <> "N/A", IF(M54>=VALUE(LEFT(L54, FIND("(", L54)-1)), J54*10*M54, 1000*M54), 1000*M54), "") | O54: =IF(AND(M54<>"",M54<>0),N54/$N$505, "") | P54: =IF(AND(M54<>"", M54<>0), F54*1000/100, "") | Q54: =IF(AND(M54<>"", M54<>0), NOW(), "") | R54: =IF(AND(M54<>"", M54<>0), ROUND((G54 - Q54)/365, 0), "") | S54: =IF(AND(M54<>"",M54<>0),MDURATION(Q54,G54,F54/100,K54/100,2), "") | T54: =IF(AND(M54<>"",M54<>0),YIELD(Q54,G54,F54/100,N54/(M54*10),100,2),"") | U54: =IF(AND(M54<>"",M54<>0), IF(E54 = "Muni", T54, IF(E54="Corp", T54*(1 -'Investor Input'!$C$4-'Investor Input'!$C$5), T54*(1 -'Investor Input'!$C$4))), T54) | V54: =IF(AND(M54<>"",M54<>0),(FV(K54/(2*100),(G54-Q54)*2/365, F54*1000/(2*100), -N54/M54))*M54, "") | W54: =IF(AND(M54<>"",M54<>0),V54-N54,"") | X54: =IF(AND(M54<>"",M54<>0),W54/N54,"") | Y54: =IF(AND(M54<>"", M54<>0), MONTH(G54), "") | Z54: =IF(AND(M54<>"", M54<>0), MONTH(EDATE(G54, 6)), "") | AA54: =IF(AND(M54<>"", M54<>0), F54*1000*M54/(100*2), "") | AB54: =IF(AND(AA54<>"",AA54<>0), IF(E54="Muni", AA54, IF(E54 = "Corp", (1-'Investor Input'!$C$4-'Investor Input'!$C$5)*AA54, (1-'Investor Input'!$C$4)*AA54)), AA54) | AC54: =IF(AND(M54<>"", M54<>0), H54, "") | AD54: =IF(AND(M54<>"", M54<>0), N54/$N$505*MATCH(AC54,'Misc Lists'!$K$2:$K$25,0), "") | AE54: =IF(AND(M54<>"", M54<>0), I54, "") | AF54: =IF(AND(M54<>"", M54<>0), N54/$N$505*MATCH(AE54,'Misc Lists'!$L$2:$L$25,0), "")
B55: 86562MDS6 | C55: N/A | D55: SUMITOMO MITSUI FIN GRP INC NOTE 5.24000% 04/15/2030 | E55: Corp | F55: 5.24 | G55: 47588 | H55: A1 | I55: A- | J55: 101.635 | K55: 4.874 | L55: 500(200) | N55: =IF(AND(M55<>"", M55<>0), IF(L55 <> "N/A", IF(M55>=VALUE(LEFT(L55, FIND("(", L55)-1)), J55*10*M55, 1000*M55), 1000*M55), "") | O55: =IF(AND(M55<>"",M55<>0),N55/$N$505, "") | P55: =IF(AND(M55<>"", M55<>0), F55*1000/100, "") | Q55: =IF(AND(M55<>"", M55<>0), NOW(), "") | R55: =IF(AND(M55<>"", M55<>0), ROUND((G55 - Q55)/365, 0), "") | S55: =IF(AND(M55<>"",M55<>0),MDURATION(Q55,G55,F55/100,K55/100,2), "") | T55: =IF(AND(M55<>"",M55<>0),YIELD(Q55,G55,F55/100,N55/(M55*10),100,2),"") | U55: =IF(AND(M55<>"",M55<>0), IF(E55 = "Muni", T55, IF(E55="Corp", T55*(1 -'Investor Input'!$C$4-'Investor Input'!$C$5), T55*(1 -'Investor Input'!$C$4))), T55) | V55: =IF(AND(M55<>"",M55<>0),(FV(K55/(2*100),(G55-Q55)*2/365, F55*1000/(2*100), -N55/M55))*M55, "") | W55: =IF(AND(M55<>"",M55<>0),V55-N55,"") | X55: =IF(AND(M55<>"",M55<>0),W55/N55,"") | Y55: =IF(AND(M55<>"", M55<>0), MONTH(G55), "") | Z55: =IF(AND(M55<>"", M55<>0), MONTH(EDATE(G55, 6)), "") | AA55: =IF(AND(M55<>"", M55<>0), F55*1000*M55/(100*2), "") | AB55: =IF(AND(AA55<>"",AA55<>0), IF(E55="Muni", AA55, IF(E55 = "Corp", (1-'Investor Input'!$C$4-'Investor Input'!$C$5)*AA55, (1-'Investor Input'!$C$4)*AA55)), AA55) | AC55: =IF(AND(M55<>"", M55<>0), H55, "") | AD55: =IF(AND(M55<>"", M55<>0), N55/$N$505*MATCH(AC55,'Misc Lists'!$K$2:$K$25,0), "") | AE55: =IF(AND(M55<>"", M55<>0), I55, "") | AF55: =IF(AND(M55<>"", M55<>0), N55/$N$505*MATCH(AE55,'Misc Lists'!$L$2:$L$25,0), "")
B56: 02364WBJ3 | C56: N/A | D56: AMERICA MOVIL SAB DECV NOTE 2.87500% 05/07/2030 CALL MAKE WHOLE | E56: Corp | F56: 2.875 | G56: 47610 | H56: BAA1 | I56: A- | J56: 91.007 | K56: 4.869 | L56: 500(200) | N56: =IF(AND(M56<>"", M56<>0), IF(L56 <> "N/A", IF(M56>=VALUE(LEFT(L56, FIND("(", L56)-1)), J56*10*M56, 1000*M56), 1000*M56), "") | O56: =IF(AND(M56<>"",M56<>0),N56/$N$505, "") | P56: =IF(AND(M56<>"", M56<>0), F56*1000/100, "") | Q56: =IF(AND(M56<>"", M56<>0), NOW(), "") | R56: =IF(AND(M56<>"", M56<>0), ROUND((G56 - Q56)/365, 0), "") | S56: =IF(AND(M56<>"",M56<>0),MDURATION(Q56,G56,F56/100,K56/100,2), "") | T56: =IF(AND(M56<>"",M56<>0),YIELD(Q56,G56,F56/100,N56/(M56*10),100,2),"") | U56: =IF(AND(M56<>"",M56<>0), IF(E56 = "Muni", T56, IF(E56="Corp", T56*(1 -'Investor Input'!$C$4-'Investor Input'!$C$5), T56*(1 -'Investor Input'!$C$4))), T56) | V56: =IF(AND(M56<>"",M56<>0),(FV(K56/(2*100),(G56-Q56)*2/365, F56*1000/(2*100), -N56/M56))*M56, "") | W56: =IF(AND(M56<>"",M56<>0),V56-N56,"") | X56: =IF(AND(M56<>"",M56<>0),W56/N56,"") | Y56: =IF(AND(M56<>"", M56<>0), MONTH(G56), "") | Z56: =IF(AND(M56<>"", M56<>0), MONTH(EDATE(G56, 6)), "") | AA56: =IF(AND(M56<>"", M56<>0), F56*1000*M56/(100*2), "") | AB56: =IF(AND(AA56<>"",AA56<>0), IF(E56="Muni", AA56, IF(E56 = "Corp", (1-'Investor Input'!$C$4-'Investor Input'!$C$5)*AA56, (1-'Investor Input'!$C$4)*AA56)), AA56) | AC56: =IF(AND(M56<>"", M56<>0), H56, "") | AD56: =IF(AND(M56<>"", M56<>0), N56/$N$505*MATCH(AC56,'Misc Lists'!$K$2:$K$25,0), "") | AE56: =IF(AND(M56<>"", M56<>0), I56, "") | AF56: =IF(AND(M56<>"", M56<>0), N56/$N$505*MATCH(AE56,'Misc Lists'!$L$2:$L$25,0), "")
... B65: 91159HHW3 | C65: N/A | D65: US BANCORP SER Y MTN 3.00000% 07/30/2029 | E65: Corp | F65: 3 | G65: 47329 | H65: A3 | I65: A- | J65: 92.826 | K65: 4.835 | L65: 200(5) | N65: =IF(AND(M65<>"", M65<>0), IF(L65 <> "N/A", IF(M65>=VALUE(LEFT(L65, FIND("(", L65)-1)), J65*10*M65, 1000*M65), 1000*M65), "") | O65: =IF(AND(M65<>"",M65<>0),N65/$N$505, "") | P65: =IF(AND(M65<>"", M65<>0), F65*1000/100, "") | Q65: =IF(AND(M65<>"", M65<>0), NOW(), "") | R65: =IF(AND(M65<>"", M65<>0), ROUND((G65 - Q65)/365, 0), "") | S65: =IF(AND(M65<>"",M65<>0),MDURATION(Q65,G65,F65/100,K65/100,2), "") | T65: =IF(AND(M65<>"",M65<>0),YIELD(Q65,G65,F65/100,N65/(M65*10),100,2),"") | U65: =IF(AND(M65<>"",M65<>0), IF(E65 = "Muni", T65, IF(E65="Corp", T65*(1 -'Investor Input'!$C$4-'Investor Input'!$C$5), T65*(1 -'Investor Input'!$C$4))), T65) | V65: =IF(AND(M65<>"",M65<>0),(FV(K65/(2*100),(G65-Q65)*2/365, F65*1000/(2*100), -N65/M65))*M65, "") | W65: =IF(AND(M65<>"",M65<>0),V65-N65,"") | X65: =IF(AND(M65<>"",M65<>0),W65/N65,"") | Y65: =IF(AND(M65<>"", M65<>0), MONTH(G65), "") | Z65: =IF(AND(M65<>"", M65<>0), MONTH(EDATE(G65, 6)), "") | AA65: =IF(AND(M65<>"", M65<>0), F65*1000*M65/(100*2), "") | AB65: =IF(AND(AA65<>"",AA65<>0), IF(E65="Muni", AA65, IF(E65 = "Corp", (1-'Investor Input'!$C$4-'Investor Input'!$C$5)*AA65, (1-'Investor Input'!$C$4)*AA65)), AA65) | AC65: =IF(AND(M65<>"", M65<>0), H65, "") | AD65: =IF(AND(M65<>"", M65<>0), N65/$N$505*MATCH(AC65,'Misc Lists'!$K$2:$K$25,0), "") | AE65: =IF(AND(M65<>"", M65<>0), I65, "") | AF65: =IF(AND(M65<>"", M65<>0), N65/$N$505*MATCH(AE65,'Misc Lists'!$L$2:$L$25,0), "")
B66: 251526CW7 | C66: N/A | D66: DEUTSCHE BK AG N Y NOTE 5.41400% 05/10/2029 | E66: Corp | F66: 5.414 | G66: 47248 | H66: A1 | I66: A | J66: 102.169 | K66: 4.83 | L66: 500(150) | M66: 15 | N66: =IF(AND(M66<>"", M66<>0), IF(L66 <> "N/A", IF(M66>=VALUE(LEFT(L66, FIND("(", L66)-1)), J66*10*M66, 1000*M66), 1000*M66), "") -> 15000 | O66: =IF(AND(M66<>"",M66<>0),N66/$N$505, "") -> 0.014999384 | P66: =IF(AND(M66<>"", M66<>0), F66*1000/100, "") -> 54.14 | Q66: =IF(AND(M66<>"", M66<>0), NOW(), "") -> 45791.491 | R66: =IF(AND(M66<>"", M66<>0), ROUND((G66 - Q66)/365, 0), "") -> 4 | S66: =IF(AND(M66<>"",M66<>0),MDURATION(Q66,G66,F66/100,K66/100,2), "") -> 3.5571539 | T66: =IF(AND(M66<>"",M66<>0),YIELD(Q66,G66,F66/100,N66/(M66*10),100,2),"") -> 0.054137794 | U66: =IF(AND(M66<>"",M66<>0), IF(E66 = "Muni", T66, IF(E66="Corp", T66*(1 -'Investor Input'!$C$4-'Investor Input'!$C$5), T66*(1 -'Investor Input'!$C$4))), T66) -> 0.029234408 | V66: =IF(AND(M66<>"",M66<>0),(FV(K66/(2*100),(G66-Q66)*2/365, F66*1000/(2*100), -N66/M66))*M66, "") -> 14619.51 | W66: =IF(AND(M66<>"",M66<>0),V66-N66,"") -> -380.49022 | X66: =IF(AND(M66<>"",M66<>0),W66/N66,"") -> -0.025366015 | Y66: =IF(AND(M66<>"", M66<>0), MONTH(G66), "") -> 5 | Z66: =IF(AND(M66<>"", M66<>0), MONTH(EDATE(G66, 6)), "") -> 11 | AA66: =IF(AND(M66<>"", M66<>0), F66*1000*M66/(100*2), "") -> 406.05 | AB66: =IF(AND(AA66<>"",AA66<>0), IF(E66="Muni", AA66, IF(E66 = "Corp", (1-'Investor Input'!$C$4-'Investor Input'!$C$5)*AA66, (1-'Investor Input'!$C$4)*AA66)), AA66) -> 219.267 | AC66: =IF(AND(M66<>"", M66<>0), H66, "") -> A1 | AD66: =IF(AND(M66<>"", M66<>0), N66/$N$505*MATCH(AC66,'Misc Lists'!$K$2:$K$25,0), "") -> 0.089996306 | AE66: =IF(AND(M66<>"", M66<>0), I66, "") -> A | AF66: =IF(AND(M66<>"", M66<>0), N66/$N$505*MATCH(AE66,'Misc Lists'!$L$2:$L$25,0), "") -> 0.10499569
B67: 125523CL2 | C67: N/A | D67: THE CIGNA GROUP NOTE CALL MAKE WHOLE2.40000% 03/15/2030 | E67: Corp | F67: 2.4 | G67: 47557 | H67: BAA1 | I67: A- | J67: 89.305 | K67: 4.83 | L67: 250(10) | N67: =IF(AND(M67<>"", M67<>0), IF(L67 <> "N/A", IF(M67>=VALUE(LEFT(L67, FIND("(", L67)-1)), J67*10*M67, 1000*M67), 1000*M67), "") | O67: =IF(AND(M67<>"",M67<>0),N67/$N$505, "") | P67: =IF(AND(M67<>"", M67<>0), F67*1000/100, "") | Q67: =IF(AND(M67<>"", M67<>0), NOW(), "") | R67: =IF(AND(M67<>"", M67<>0), ROUND((G67 - Q67)/365, 0), "") | S67: =IF(AND(M67<>"",M67<>0),MDURATION(Q67,G67,F67/100,K67/100,2), "") | T67: =IF(AND(M67<>"",M67<>0),YIELD(Q67,G67,F67/100,N67/(M67*10),100,2),"") | U67: =IF(AND(M67<>"",M67<>0), IF(E67 = "Muni", T67, IF(E67="Corp", T67*(1 -'Investor Input'!$C$4-'Investor Input'!$C$5), T67*(1 -'Investor Input'!$C$4))), T67) | V67: =IF(AND(M67<>"",M67<>0),(FV(K67/(2*100),(G67-Q67)*2/365, F67*1000/(2*100), -N67/M67))*M67, "") | W67: =IF(AND(M67<>"",M67<>0),V67-N67,"") | X67: =IF(AND(M67<>"",M67<>0),W67/N67,"") | Y67: =IF(AND(M67<>"", M67<>0), MONTH(G67), "") | Z67: =IF(AND(M67<>"", M67<>0), MONTH(EDATE(G67, 6)), "") | AA67: =IF(AND(M67<>"", M67<>0), F67*1000*M67/(100*2), "") | AB67: =IF(AND(AA67<>"",AA67<>0), IF(E67="Muni", AA67, IF(E67 = "Corp", (1-'Investor Input'!$C$4-'Investor Input'!$C$5)*AA67, (1-'Investor Input'!$C$4)*AA67)), AA67) | AC67: =IF(AND(M67<>"", M67<>0), H67, "") | AD67: =IF(AND(M67<>"", M67<>0), N67/$N$505*MATCH(AC67,'Misc Lists'!$K$2:$K$25,0), "") | AE67: =IF(AND(M67<>"", M67<>0), I67, "") | AF67: =IF(AND(M67<>"", M67<>0), N67/$N$505*MATCH(AE67,'Misc Lists'!$L$2:$L$25,0), "")
B68: 46513YJH2 | C68: N/A | D68: ISRAEL(STATE OF) NOTE 3.25000% 01/17/2028 | E68: Corp | F68: 3.25 | G68: 46769 | H68: BAA1 | I68: A | J68: 95.855 | K68: 4.824 | L68: 200(200) | N68: =IF(AND(M68<>"", M68<>0), IF(L68 <> "N/A", IF(M68>=VALUE(LEFT(L68, FIND("(", L68)-1)), J68*10*M68, 1000*M68), 1000*M68), "") | O68: =IF(AND(M68<>"",M68<>0),N68/$N$505, "") | P68: =IF(AND(M68<>"", M68<>0), F68*1000/100, "") | Q68: =IF(AND(M68<>"", M68<>0), NOW(), "") | R68: =IF(AND(M68<>"", M68<>0), ROUND((G68 - Q68)/365, 0), "") | S68: =IF(AND(M68<>"",M68<>0),MDURATION(Q68,G68,F68/100,K68/100,2), "") | T68: =IF(AND(M68<>"",M68<>0),YIELD(Q68,G68,F68/100,N68/(M68*10),100,2),"") | U68: =IF(AND(M68<>"",M68<>0), IF(E68 = "Muni", T68, IF(E68="Corp", T68*(1 -'Investor Input'!$C$4-'Investor Input'!$C$5), T68*(1 -'Investor Input'!$C$4))), T68) | V68: =IF(AND(M68<>"",M68<>0),(FV(K68/(2*100),(G68-Q68)*2/365, F68*1000/(2*100), -N68/M68))*M68, "") | W68: =IF(AND(M68<>"",M68<>0),V68-N68,"") | X68: =IF(AND(M68<>"",M68<>0),W68/N68,"") | Y68: =IF(AND(M68<>"", M68<>0), MONTH(G68), "") | Z68: =IF(AND(M68<>"", M68<>0), MONTH(EDATE(G68, 6)), "") | AA68: =IF(AND(M68<>"", M68<>0), F68*1000*M68/(100*2), "") | AB68: =IF(AND(AA68<>"",AA68<>0), IF(E68="Muni", AA68, IF(E68 = "Corp", (1-'Investor Input'!$C$4-'Investor Input'!$C$5)*AA68, (1-'Investor Input'!$C$4)*AA68)), AA68) | AC68: =IF(AND(M68<>"", M68<>0), H68, "") | AD68: =IF(AND(M68<>"", M68<>0), N68/$N$505*MATCH(AC68,'Misc Lists'!$K$2:$K$25,0), "") | AE68: =IF(AND(M68<>"", M68<>0), I68, "") | AF68: =IF(AND(M68<>"", M68<>0), N68/$N$505*MATCH(AE68,'Misc Lists'!$L$2:$L$25,0), "")
B69: 86562MBW9 | C69: N/A | D69: SUMITOMO MITSUI FIN GRP INC NOTE 2.75000% 01/15/2030 | E69: Corp | F69: 2.75 | G69: 47498 | H69: A1 | I69: A- | J69: 91.14 | K69: 4.823 | L69: 200(200) | N69: =IF(AND(M69<>"", M69<>0), IF(L69 <> "N/A", IF(M69>=VALUE(LEFT(L69, FIND("(", L69)-1)), J69*10*M69, 1000*M69), 1000*M69), "") | O69: =IF(AND(M69<>"",M69<>0),N69/$N$505, "") | P69: =IF(AND(M69<>"", M69<>0), F69*1000/100, "") | Q69: =IF(AND(M69<>"", M69<>0), NOW(), "") | R69: =IF(AND(M69<>"", M69<>0), ROUND((G69 - Q69)/365, 0), "") | S69: =IF(AND(M69<>"",M69<>0),MDURATION(Q69,G69,F69/100,K69/100,2), "") | T69: =IF(AND(M69<>"",M69<>0),YIELD(Q69,G69,F69/100,N69/(M69*10),100,2),"") | U69: =IF(AND(M69<>"",M69<>0), IF(E69 = "Muni", T69, IF(E69="Corp", T69*(1 -'Investor Input'!$C$4-'Investor Input'!$C$5), T69*(1 -'Investor Input'!$C$4))), T69) | V69: =IF(AND(M69<>"",M69<>0),(FV(K69/(2*100),(G69-Q69)*2/365, F69*1000/(2*100), -N69/M69))*M69, "") | W69: =IF(AND(M69<>"",M69<>0),V69-N69,"") | X69: =IF(AND(M69<>"",M69<>0),W69/N69,"") | Y69: =IF(AND(M69<>"", M69<>0), MONTH(G69), "") | Z69: =IF(AND(M69<>"", M69<>0), MONTH(EDATE(G69, 6)), "") | AA69: =IF(AND(M69<>"", M69<>0), F69*1000*M69/(100*2), "") | AB69: =IF(AND(AA69<>"",AA69<>0), IF(E69="Muni", AA69, IF(E69 = "Corp", (1-'Investor Input'!$C$4-'Investor Input'!$C$5)*AA69, (1-'Investor Input'!$C$4)*AA69)), AA69) | AC69: =IF(AND(M69<>"", M69<>0), H69, "") | AD69: =IF(AND(M69<>"", M69<>0), N69/$N$505*MATCH(AC69,'Misc Lists'!$K$2:$K$25,0), "") | AE69: =IF(AND(M69<>"", M69<>0), I69, "") | AF69: =IF(AND(M69<>"", M69<>0), N69/$N$505*MATCH(AE69,'Misc Lists'!$L$2:$L$25,0), "")
B70: 842400GV9 | C70: N/A | D70: SOUTHERN CALIF EDISON CO SER 2020C 1.20000% 02/01/2026 BOND CALL MAKE WHOLE | E70: Corp | F70: 1.2 | G70: 46054 | H70: A2 | I70: A- | J70: 96.893 | K70: 4.822 | L70: 700(15) | N70: =IF(AND(M70<>"", M70<>0), IF(L70 <> "N/A", IF(M70>=VALUE(LEFT(L70, FIND("(", L70)-1)), J70*10*M70, 1000*M70), 1000*M70), "") | O70: =IF(AND(M70<>"",M70<>0),N70/$N$505, "") | P70: =IF(AND(M70<>"", M70<>0), F70*1000/100, "") | Q70: =IF(AND(M70<>"", M70<>0), NOW(), "") | R70: =IF(AND(M70<>"", M70<>0), ROUND((G70 - Q70)/365, 0), "") | S70: =IF(AND(M70<>"",M70<>0),MDURATION(Q70,G70,F70/100,K70/100,2), "") | T70: =IF(AND(M70<>"",M70<>0),YIELD(Q70,G70,F70/100,N70/(M70*10),100,2),"") | U70: =IF(AND(M70<>"",M70<>0), IF(E70 = "Muni", T70, IF(E70="Corp", T70*(1 -'Investor Input'!$C$4-'Investor Input'!$C$5), T70*(1 -'Investor Input'!$C$4))), T70) | V70: =IF(AND(M70<>"",M70<>0),(FV(K70/(2*100),(G70-Q70)*2/365, F70*1000/(2*100), -N70/M70))*M70, "") | W70: =IF(AND(M70<>"",M70<>0),V70-N70,"") | X70: =IF(AND(M70<>"",M70<>0),W70/N70,"") | Y70: =IF(AND(M70<>"", M70<>0), MONTH(G70), "") | Z70: =IF(AND(M70<>"", M70<>0), MONTH(EDATE(G70, 6)), "") | AA70: =IF(AND(M70<>"", M70<>0), F70*1000*M70/(100*2), "") | AB70: =IF(AND(AA70<>"",AA70<>0), IF(E70="Muni", AA70, IF(E70 = "Corp", (1-'Investor Input'!$C$4-'Investor Input'!$C$5)*AA70, (1-'Investor Input'!$C$4)*AA70)), AA70) | AC70: =IF(AND(M70<>"", M70<>0), H70, "") | AD70: =IF(AND(M70<>"", M70<>0), N70/$N$505*MATCH(AC70,'Misc Lists'!$K$2:$K$25,0), "") | AE70: =IF(AND(M70<>"", M70<>0), I70, "") | AF70: =IF(AND(M70<>"", M70<>0), N70/$N$505*MATCH(AE70,'Misc Lists'!$L$2:$L$25,0), "")
B71: 89115A3C4 | C71: N/A | D71: TORONTO DOMINION BK ONT SER C MTN 4.78300% 12/17/2029 CALL MAKE WHOLE | E71: Corp | F71: 4.783 | G71: 47469 | H71: A2 | I71: A- | J71: 99.843 | K71: 4.819 | L71: 500(2) | N71: =IF(AND(M71<>"", M71<>0), IF(L71 <> "N/A", IF(M71>=VALUE(LEFT(L71, FIND("(", L71)-1)), J71*10*M71, 1000*M71), 1000*M71), "") | O71: =IF(AND(M71<>"",M71<>0),N71/$N$505, "") | P71: =IF(AND(M71<>"", M71<>0), F71*1000/100, "") | Q71: =IF(AND(M71<>"", M71<>0), NOW(), "") | R71: =IF(AND(M71<>"", M71<>0), ROUND((G71 - Q71)/365, 0), "") | S71: =IF(AND(M71<>"",M71<>0),MDURATION(Q71,G71,F71/100,K71/100,2), "") | T71: =IF(AND(M71<>"",M71<>0),YIELD(Q71,G71,F71/100,N71/(M71*10),100,2),"") | U71: =IF(AND(M71<>"",M71<>0), IF(E71 = "Muni", T71, IF(E71="Corp", T71*(1 -'Investor Input'!$C$4-'Investor Input'!$C$5), T71*(1 -'Investor Input'!$C$4))), T71) | V71: =IF(AND(M71<>"",M71<>0),(FV(K71/(2*100),(G71-Q71)*2/365, F71*1000/(2*100), -N71/M71))*M71, "") | W71: =IF(AND(M71<>"",M71<>0),V71-N71,"") | X71: =IF(AND(M71<>"",M71<>0),W71/N71,"") | Y71: =IF(AND(M71<>"", M71<>0), MONTH(G71), "") | Z71: =IF(AND(M71<>"", M71<>0), MONTH(EDATE(G71, 6)), "") | AA71: =IF(AND(M71<>"", M71<>0), F71*1000*M71/(100*2), "") | AB71: =IF(AND(AA71<>"",AA71<>0), IF(E71="Muni", AA71, IF(E71 = "Corp", (1-'Investor Input'!$C$4-'Investor Input'!$C$5)*AA71, (1-'Investor Input'!$C$4)*AA71)), AA71) | AC71: =IF(AND(M71<>"", M71<>0), H71, "") | AD71: =IF(AND(M71<>"", M71<>0), N71/$N$505*MATCH(AC71,'Misc Lists'!$K$2:$K$25,0), "") | AE71: =IF(AND(M71<>"", M71<>0), I71, "") | AF71: =IF(AND(M71<>"", M71<>0), N71/$N$505*MATCH(AE71,'Misc Lists'!$L$2:$L$25,0), "")
B72: 06418GAK3 | C72: N/A | D72: BANK NOVA SCOTIA B CSER I MTN 5.45000% 08/01/2029 CALL MAKE WHOLE | E72: Corp | F72: 5.45 | G72: 47331 | H72: A2 | I72: A- | J72: 102.467 | K72: 4.818 | L72: 500(2) | N72: =IF(AND(M72<>"", M72<>0), IF(L72 <> "N/A", IF(M72>=VALUE(LEFT(L72, FIND("(", L72)-1)), J72*10*M72, 1000*M72), 1000*M72), "") | O72: =IF(AND(M72<>"",M72<>0),N72/$N$505, "") | P72: =IF(AND(M72<>"", M72<>0), F72*1000/100, "") | Q72: =IF(AND(M72<>"", M72<>0), NOW(), "") | R72: =IF(AND(M72<>"", M72<>0), ROUND((G72 - Q72)/365, 0), "") | S72: =IF(AND(M72<>"",M72<>0),MDURATION(Q72,G72,F72/100,K72/100,2), "") | T72: =IF(AND(M72<>"",M72<>0),YIELD(Q72,G72,F72/100,N72/(M72*10),100,2),"") | U72: =IF(AND(M72<>"",M72<>0), IF(E72 = "Muni", T72, IF(E72="Corp", T72*(1 -'Investor Input'!$C$4-'Investor Input'!$C$5), T72*(1 -'Investor Input'!$C$4))), T72) | V72: =IF(AND(M72<>"",M72<>0),(FV(K72/(2*100),(G72-Q72)*2/365, F72*1000/(2*100), -N72/M72))*M72, "") | W72: =IF(AND(M72<>"",M72<>0),V72-N72,"") | X72: =IF(AND(M72<>"",M72<>0),W72/N72,"") | Y72: =IF(AND(M72<>"", M72<>0), MONTH(G72), "") | Z72: =IF(AND(M72<>"", M72<>0), MONTH(EDATE(G72, 6)), "") | AA72: =IF(AND(M72<>"", M72<>0), F72*1000*M72/(100*2), "") | AB72: =IF(AND(AA72<>"",AA72<>0), IF(E72="Muni", AA72, IF(E72 = "Corp", (1-'Investor Input'!$C$4-'Investor Input'!$C$5)*AA72, (1-'Investor Input'!$C$4)*AA72)), AA72) | AC72: =IF(AND(M72<>"", M72<>0), H72, "") | AD72: =IF(AND(M72<>"", M72<>0), N72/$N$505*MATCH(AC72,'Misc Lists'!$K$2:$K$25,0), "") | AE72: =IF(AND(M72<>"", M72<>0), I72, "") | AF72: =IF(AND(M72<>"", M72<>0), N72/$N$505*MATCH(AE72,'Misc Lists'!$L$2:$L$25,0), "")
B73: 02665WEH0 | C73: N/A | D73: AMERICAN HONDA FIN CORP SER A MTN 4.60000% 04/17/2030 CALL MAKE WHOLE | E73: Corp | F73: 4.6 | G73: 47590 | H73: A3 | I73: A- | J73: 99.026 | K73: 4.817 | L73: 1,000(2) | N73: =IF(AND(M73<>"", M73<>0), IF(L73 <> "N/A", IF(M73>=VALUE(LEFT(L73, FIND("(", L73)-1)), J73*10*M73, 1000*M73), 1000*M73), "") | O73: =IF(AND(M73<>"",M73<>0),N73/$N$505, "") | P73: =IF(AND(M73<>"", M73<>0), F73*1000/100, "") | Q73: =IF(AND(M73<>"", M73<>0), NOW(), "") | R73: =IF(AND(M73<>"", M73<>0), ROUND((G73 - Q73)/365, 0), "") | S73: =IF(AND(M73<>"",M73<>0),MDURATION(Q73,G73,F73/100,K73/100,2), "") | T73: =IF(AND(M73<>"",M73<>0),YIELD(Q73,G73,F73/100,N73/(M73*10),100,2),"") | U73: =IF(AND(M73<>"",M73<>0), IF(E73 = "Muni", T73, IF(E73="Corp", T73*(1 -'Investor Input'!$C$4-'Investor Input'!$C$5), T73*(1 -'Investor Input'!$C$4))), T73) | V73: =IF(AND(M73<>"",M73<>0),(FV(K73/(2*100),(G73-Q73)*2/365, F73*1000/(2*100), -N73/M73))*M73, "") | W73: =IF(AND(M73<>"",M73<>0),V73-N73,"") | X73: =IF(AND(M73<>"",M73<>0),W73/N73,"") | Y73: =IF(AND(M73<>"", M73<>0), MONTH(G73), "") | Z73: =IF(AND(M73<>"", M73<>0), MONTH(EDATE(G73, 6)), "") | AA73: =IF(AND(M73<>"", M73<>0), F73*1000*M73/(100*2), "") | AB73: =IF(AND(AA73<>"",AA73<>0), IF(E73="Muni", AA73, IF(E73 = "Corp", (1-'Investor Input'!$C$4-'Investor Input'!$C$5)*AA73, (1-'Investor Input'!$C$4)*AA73)), AA73) | AC73: =IF(AND(M73<>"", M73<>0), H73, "") | AD73: =IF(AND(M73<>"", M73<>0), N73/$N$505*MATCH(AC73,'Misc Lists'!$K$2:$K$25,0), "") | AE73: =IF(AND(M73<>"", M73<>0), I73, "") | AF73: =IF(AND(M73<>"", M73<>0), N73/$N$505*MATCH(AE73,'Misc Lists'!$L$2:$L$25,0), "")
B74: 559222BA1 | C74: N/A | D74: MAGNA INTL INC NOTE CALL MAKE WHOLE5.05000% 03/14/2029 ISIN #US559222BA12 | E74: Corp | F74: 5.05 | G74: 47191 | H74: A3 | I74: A- | J74: 100.845 | K74: 4.815 | L74: 1,000(2) | N74: =IF(AND(M74<>"", M74<>0), IF(L74 <> "N/A", IF(M74>=VALUE(LEFT(L74, FIND("(", L74)-1)), J74*10*M74, 1000*M74), 1000*M74), "") | O74: =IF(AND(M74<>"",M74<>0),N74/$N$505, "") | P74: =IF(AND(M74<>"", M74<>0), F74*1000/100, "") | Q74: =IF(AND(M74<>"", M74<>0), NOW(), "") | R74: =IF(AND(M74<>"", M74<>0), ROUND((G74 - Q74)/365, 0), "") | S74: =IF(AND(M74<>"",M74<>0),MDURATION(Q74,G74,F74/100,K74/100,2), "") | T74: =IF(AND(M74<>"",M74<>0),YIELD(Q74,G74,F74/100,N74/(M74*10),100,2),"") | U74: =IF(AND(M74<>"",M74<>0), IF(E74 = "Muni", T74, IF(E74="Corp", T74*(1 -'Investor Input'!$C$4-'Investor Input'!$C$5), T74*(1 -'Investor Input'!$C$4))), T74) | V74: =IF(AND(M74<>"",M74<>0),(FV(K74/(2*100),(G74-Q74)*2/365, F74*1000/(2*100), -N74/M74))*M74, "") | W74: =IF(AND(M74<>"",M74<>0),V74-N74,"") | X74: =IF(AND(M74<>"",M74<>0),W74/N74,"") | Y74: =IF(AND(M74<>"", M74<>0), MONTH(G74), "") | Z74: =IF(AND(M74<>"", M74<>0), MONTH(EDATE(G74, 6)), "") | AA74: =IF(AND(M74<>"", M74<>0), F74*1000*M74/(100*2), "") | AB74: =IF(AND(AA74<>"",AA74<>0), IF(E74="Muni", AA74, IF(E74 = "Corp", (1-'Investor Input'!$C$4-'Investor Input'!$C$5)*AA74, (1-'Investor Input'!$C$4)*AA74)), AA74) | AC74: =IF(AND(M74<>"", M74<>0), H74, "") | AD74: =IF(AND(M74<>"", M74<>0), N74/$N$505*MATCH(AC74,'Misc Lists'!$K$2:$K$25,0), "") | AE74: =IF(AND(M74<>"", M74<>0), I74, "") | AF74: =IF(AND(M74<>"", M74<>0), N74/$N$505*MATCH(AE74,'Misc Lists'!$L$2:$L$25,0), "")
B75: 59523UAR8 | C75: N/A | D75: MID-AMERICA APTS LP NOTE CALL MAKE WHOLE2.75000% 03/15/2030 | E75: Corp | F75: 2.75 | G75: 47557 | H75: A3 | I75: A- | J75: 90.927 | K75: 4.81 | L75: 30(9) | N75: =IF(AND(M75<>"", M75<>0), IF(L75 <> "N/A", IF(M75>=VALUE(LEFT(L75, FIND("(", L75)-1)), J75*10*M75, 1000*M75), 1000*M75), "") | O75: =IF(AND(M75<>"",M75<>0),N75/$N$505, "") | P75: =IF(AND(M75<>"", M75<>0), F75*1000/100, "") | Q75: =IF(AND(M75<>"", M75<>0), NOW(), "") | R75: =IF(AND(M75<>"", M75<>0), ROUND((G75 - Q75)/365, 0), "") | S75: =IF(AND(M75<>"",M75<>0),MDURATION(Q75,G75,F75/100,K75/100,2), "") | T75: =IF(AND(M75<>"",M75<>0),YIELD(Q75,G75,F75/100,N75/(M75*10),100,2),"") | U75: =IF(AND(M75<>"",M75<>0), IF(E75 = "Muni", T75, IF(E75="Corp", T75*(1 -'Investor Input'!$C$4-'Investor Input'!$C$5), T75*(1 -'Investor Input'!$C$4))), T75) | V75: =IF(AND(M75<>"",M75<>0),(FV(K75/(2*100),(G75-Q75)*2/365, F75*1000/(2*100), -N75/M75))*M75, "") | W75: =IF(AND(M75<>"",M75<>0),V75-N75,"") | X75: =IF(AND(M75<>"",M75<>0),W75/N75,"") | Y75: =IF(AND(M75<>"", M75<>0), MONTH(G75), "") | Z75: =IF(AND(M75<>"", M75<>0), MONTH(EDATE(G75, 6)), "") | AA75: =IF(AND(M75<>"", M75<>0), F75*1000*M75/(100*2), "") | AB75: =IF(AND(AA75<>"",AA75<>0), IF(E75="Muni", AA75, IF(E75 = "Corp", (1-'Investor Input'!$C$4-'Investor Input'!$C$5)*AA75, (1-'Investor Input'!$C$4)*AA75)), AA75) | AC75: =IF(AND(M75<>"", M75<>0), H75, "") | AD75: =IF(AND(M75<>"", M75<>0), N75/$N$505*MATCH(AC75,'Misc Lists'!$K$2:$K$25,0), "") | AE75: =IF(AND(M75<>"", M75<>0), I75, "") | AF75: =IF(AND(M75<>"", M75<>0), N75/$N$505*MATCH(AE75,'Misc Lists'!$L$2:$L$25,0), "")
B76: 05964HAJ4 | C76: N/A | D76: BANCO SANTANDER SA SER 38 NOTE 4.37900% 04/12/2028 | E76: Corp | F76: 4.379 | G76: 46855 | H76: BAA1 | I76: A- | J76: 98.789 | K76: 4.805 | L76: 200(200) | N76: =IF(AND(M76<>"", M76<>0), IF(L76 <> "N/A", IF(M76>=VALUE(LEFT(L76, FIND("(", L76)-1)), J76*10*M76, 1000*M76), 1000*M76), "") | O76: =IF(AND(M76<>"",M76<>0),N76/$N$505, "") | P76: =IF(AND(M76<>"", M76<>0), F76*1000/100, "") | Q76: =IF(AND(M76<>"", M76<>0), NOW(), "") | R76: =IF(AND(M76<>"", M76<>0), ROUND((G76 - Q76)/365, 0), "") | S76: =IF(AND(M76<>"",M76<>0),MDURATION(Q76,G76,F76/100,K76/100,2), "") | T76: =IF(AND(M76<>"",M76<>0),YIELD(Q76,G76,F76/100,N76/(M76*10),100,2),"") | U76: =IF(AND(M76<>"",M76<>0), IF(E76 = "Muni", T76, IF(E76="Corp", T76*(1 -'Investor Input'!$C$4-'Investor Input'!$C$5), T76*(1 -'Investor Input'!$C$4))), T76) | V76: =IF(AND(M76<>"",M76<>0),(FV(K76/(2*100),(G76-Q76)*2/365, F76*1000/(2*100), -N76/M76))*M76, "") | W76: =IF(AND(M76<>"",M76<>0),V76-N76,"") | X76: =IF(AND(M76<>"",M76<>0),W76/N76,"") | Y76: =IF(AND(M76<>"", M76<>0), MONTH(G76), "") | Z76: =IF(AND(M76<>"", M76<>0), MONTH(EDATE(G76, 6)), "") | AA76: =IF(AND(M76<>"", M76<>0), F76*1000*M76/(100*2), "") | AB76: =IF(AND(AA76<>"",AA76<>0), IF(E76="Muni", AA76, IF(E76 = "Corp", (1-'Investor Input'!$C$4-'Investor Input'!$C$5)*AA76, (1-'Investor Input'!$C$4)*AA76)), AA76) | AC76: =IF(AND(M76<>"", M76<>0), H76, "") | AD76: =IF(AND(M76<>"", M76<>0), N76/$N$505*MATCH(AC76,'Misc Lists'!$K$2:$K$25,0), "") | AE76: =IF(AND(M76<>"", M76<>0), I76, "") | AF76: =IF(AND(M76<>"", M76<>0), N76/$N$505*MATCH(AE76,'Misc Lists'!$L$2:$L$25,0), "")
B77: 03740MAB6 | C77: N/A | D77: AON NORTH AMERICA INC. NOTE 5.15000% 03/01/2029 CALL MAKE WHOLE | E77: Corp | F77: 5.15 | G77: 47178 | H77: BAA2 | I77: A- | J77: 101.232 | K77: 4.805 | L77: 250(10) | N77: =IF(AND(M77<>"", M77<>0), IF(L77 <> "N/A", IF(M77>=VALUE(LEFT(L77, FIND("(", L77)-1)), J77*10*M77, 1000*M77), 1000*M77), "") | O77: =IF(AND(M77<>"",M77<>0),N77/$N$505, "") | P77: =IF(AND(M77<>"", M77<>0), F77*1000/100, "") | Q77: =IF(AND(M77<>"", M77<>0), NOW(), "") | R77: =IF(AND(M77<>"", M77<>0), ROUND((G77 - Q77)/365, 0), "") | S77: =IF(AND(M77<>"",M77<>0),MDURATION(Q77,G77,F77/100,K77/100,2), "") | T77: =IF(AND(M77<>"",M77<>0),YIELD(Q77,G77,F77/100,N77/(M77*10),100,2),"") | U77: =IF(AND(M77<>"",M77<>0), IF(E77 = "Muni", T77, IF(E77="Corp", T77*(1 -'Investor Input'!$C$4-'Investor Input'!$C$5), T77*(1 -'Investor Input'!$C$4))), T77) | V77: =IF(AND(M77<>"",M77<>0),(FV(K77/(2*100),(G77-Q77)*2/365, F77*1000/(2*100), -N77/M77))*M77, "") | W77: =IF(AND(M77<>"",M77<>0),V77-N77,"") | X77: =IF(AND(M77<>"",M77<>0),W77/N77,"") | Y77: =IF(AND(M77<>"", M77<>0), MONTH(G77), "") | Z77: =IF(AND(M77<>"", M77<>0), MONTH(EDATE(G77, 6)), "") | AA77: =IF(AND(M77<>"", M77<>0), F77*1000*M77/(100*2), "") | AB77: =IF(AND(AA77<>"",AA77<>0), IF(E77="Muni", AA77, IF(E77 = "Corp", (1-'Investor Input'!$C$4-'Investor Input'!$C$5)*AA77, (1-'Investor Input'!$C$4)*AA77)), AA77) | AC77: =IF(AND(M77<>"", M77<>0), H77, "") | AD77: =IF(AND(M77<>"", M77<>0), N77/$N$505*MATCH(AC77,'Misc Lists'!$K$2:$K$25,0), "") | AE77: =IF(AND(M77<>"", M77<>0), I77, "") | AF77: =IF(AND(M77<>"", M77<>0), N77/$N$505*MATCH(AE77,'Misc Lists'!$L$2:$L$25,0), "")
B78: 06417XAP6 | C78: N/A | D78: BANK NOVA SCOTIA B CSER I MTN 4.85000% 02/01/2030 CALL MAKE WHOLE ISIN #US06417XAP69 | E78: Corp | F78: 4.85 | G78: 47515 | H78: A2 | I78: A- | J78: 100.193 | K78: 4.804 | L78: 500(9) | N78: =IF(AND(M78<>"", M78<>0), IF(L78 <> "N/A", IF(M78>=VALUE(LEFT(L78, FIND("(", L78)-1)), J78*10*M78, 1000*M78), 1000*M78), "") | O78: =IF(AND(M78<>"",M78<>0),N78/$N$505, "") | P78: =IF(AND(M78<>"", M78<>0), F78*1000/100, "") | Q78: =IF(AND(M78<>"", M78<>0), NOW(), "") | R78: =IF(AND(M78<>"", M78<>0), ROUND((G78 - Q78)/365, 0), "") | S78: =IF(AND(M78<>"",M78<>0),MDURATION(Q78,G78,F78/100,K78/100,2), "") | T78: =IF(AND(M78<>"",M78<>0),YIELD(Q78,G78,F78/100,N78/(M78*10),100,2),"") | U78: =IF(AND(M78<>"",M78<>0), IF(E78 = "Muni", T78, IF(E78="Corp", T78*(1 -'Investor Input'!$C$4-'Investor Input'!$C$5), T78*(1 -'Investor Input'!$C$4))), T78) | V78: =IF(AND(M78<>"",M78<>0),(FV(K78/(2*100),(G78-Q78)*2/365, F78*1000/(2*100), -N78/M78))*M78, "") | W78: =IF(AND(M78<>"",M78<>0),V78-N78,"") | X78: =IF(AND(M78<>"",M78<>0),W78/N78,"") | Y78: =IF(AND(M78<>"", M78<>0), MONTH(G78), "") | Z78: =IF(AND(M78<>"", M78<>0), MONTH(EDATE(G78, 6)), "") | AA78: =IF(AND(M78<>"", M78<>0), F78*1000*M78/(100*2), "") | AB78: =IF(AND(AA78<>"",AA78<>0), IF(E78="Muni", AA78, IF(E78 = "Corp", (1-'Investor Input'!$C$4-'Investor Input'!$C$5)*AA78, (1-'Investor Input'!$C$4)*AA78)), AA78) | AC78: =IF(AND(M78<>"", M78<>0), H78, "") | AD78: =IF(AND(M78<>"", M78<>0), N78/$N$505*MATCH(AC78,'Misc Lists'!$K$2:$K$25,0), "") | AE78: =IF(AND(M78<>"", M78<>0), I78, "") | AF78: =IF(AND(M78<>"", M78<>0), N78/$N$505*MATCH(AE78,'Misc Lists'!$L$2:$L$25,0), "")
... B92: 456837AQ6 | C92: N/A | D92: ING GROEP N.V. NOTE 4.05000% 04/09/2029 | E92: Corp | F92: 4.05 | G92: 47217 | H92: BAA1 | I92: A- | J92: 97.307 | K92: 4.784 | L92: 200(200) | N92: =IF(AND(M92<>"", M92<>0), IF(L92 <> "N/A", IF(M92>=VALUE(LEFT(L92, FIND("(", L92)-1)), J92*10*M92, 1000*M92), 1000*M92), "") | O92: =IF(AND(M92<>"",M92<>0),N92/$N$505, "") | P92: =IF(AND(M92<>"", M92<>0), F92*1000/100, "") | Q92: =IF(AND(M92<>"", M92<>0), NOW(), "") | R92: =IF(AND(M92<>"", M92<>0), ROUND((G92 - Q92)/365, 0), "") | S92: =IF(AND(M92<>"",M92<>0),MDURATION(Q92,G92,F92/100,K92/100,2), "") | T92: =IF(AND(M92<>"",M92<>0),YIELD(Q92,G92,F92/100,N92/(M92*10),100,2),"") | U92: =IF(AND(M92<>"",M92<>0), IF(E92 = "Muni", T92, IF(E92="Corp", T92*(1 -'Investor Input'!$C$4-'Investor Input'!$C$5), T92*(1 -'Investor Input'!$C$4))), T92) | V92: =IF(AND(M92<>"",M92<>0),(FV(K92/(2*100),(G92-Q92)*2/365, F92*1000/(2*100), -N92/M92))*M92, "") | W92: =IF(AND(M92<>"",M92<>0),V92-N92,"") | X92: =IF(AND(M92<>"",M92<>0),W92/N92,"") | Y92: =IF(AND(M92<>"", M92<>0), MONTH(G92), "") | Z92: =IF(AND(M92<>"", M92<>0), MONTH(EDATE(G92, 6)), "") | AA92: =IF(AND(M92<>"", M92<>0), F92*1000*M92/(100*2), "") | AB92: =IF(AND(AA92<>"",AA92<>0), IF(E92="Muni", AA92, IF(E92 = "Corp", (1-'Investor Input'!$C$4-'Investor Input'!$C$5)*AA92, (1-'Investor Input'!$C$4)*AA92)), AA92) | AC92: =IF(AND(M92<>"", M92<>0), H92, "") | AD92: =IF(AND(M92<>"", M92<>0), N92/$N$505*MATCH(AC92,'Misc Lists'!$K$2:$K$25,0), "") | AE92: =IF(AND(M92<>"", M92<>0), I92, "") | AF92: =IF(AND(M92<>"", M92<>0), N92/$N$505*MATCH(AE92,'Misc Lists'!$L$2:$L$25,0), "")
B93: 842400GN7 | C93: N/A | D93: SOUTHERN CALIF EDISON CO SER 2018E 3.70000% 08/01/2025 BOND CALL MAKE WHOLE | E93: Corp | F93: 3.7 | G93: 45870 | H93: A2 | I93: A- | J93: 99.583 | K93: 4.78 | L93: 625(1) | M93: 10 | N93: =IF(AND(M93<>"", M93<>0), IF(L93 <> "N/A", IF(M93>=VALUE(LEFT(L93, FIND("(", L93)-1)), J93*10*M93, 1000*M93), 1000*M93), "") -> 10000 | O93: =IF(AND(M93<>"",M93<>0),N93/$N$505, "") -> 0.0099995895 | P93: =IF(AND(M93<>"", M93<>0), F93*1000/100, "") -> 37 | Q93: =IF(AND(M93<>"", M93<>0), NOW(), "") -> 45791.491 | R93: =IF(AND(M93<>"", M93<>0), ROUND((G93 - Q93)/365, 0), "") -> 0 | S93: =IF(AND(M93<>"",M93<>0),MDURATION(Q93,G93,F93/100,K93/100,2), "") -> 0.20889627 | T93: =IF(AND(M93<>"",M93<>0),YIELD(Q93,G93,F93/100,N93/(M93*10),100,2),"") -> 0.036612417 | U93: =IF(AND(M93<>"",M93<>0), IF(E93 = "Muni", T93, IF(E93="Corp", T93*(1 -'Investor Input'!$C$4-'Investor Input'!$C$5), T93*(1 -'Investor Input'!$C$4))), T93) -> 0.019770705 | V93: =IF(AND(M93<>"",M93<>0),(FV(K93/(2*100),(G93-Q93)*2/365, F93*1000/(2*100), -N93/M93))*M93, "") -> 10023.074 | W93: =IF(AND(M93<>"",M93<>0),V93-N93,"") -> 23.073721 | X93: =IF(AND(M93<>"",M93<>0),W93/N93,"") -> 0.0023073721 | Y93: =IF(AND(M93<>"", M93<>0), MONTH(G93), "") -> 8 | Z93: =IF(AND(M93<>"", M93<>0), MONTH(EDATE(G93, 6)), "") -> 2 | AA93: =IF(AND(M93<>"", M93<>0), F93*1000*M93/(100*2), "") -> 185 | AB93: =IF(AND(AA93<>"",AA93<>0), IF(E93="Muni", AA93, IF(E93 = "Corp", (1-'Investor Input'!$C$4-'Investor Input'!$C$5)*AA93, (1-'Investor Input'!$C$4)*AA93)), AA93) -> 99.9 | AC93: =IF(AND(M93<>"", M93<>0), H93, "") -> A2 | AD93: =IF(AND(M93<>"", M93<>0), N93/$N$505*MATCH(AC93,'Misc Lists'!$K$2:$K$25,0), "") -> 0.069997127 | AE93: =IF(AND(M93<>"", M93<>0), I93, "") -> A- | AF93: =IF(AND(M93<>"", M93<>0), N93/$N$505*MATCH(AE93,'Misc Lists'!$L$2:$L$25,0), "") -> 0.079996716
B94: 67021CAX5 | C94: N/A | D94: NSTAR ELEC CO BOND CALL MAKE WHOLE4.85000% 03/01/2030 | E94: Corp | F94: 4.85 | G94: 47543 | H94: A2 | I94: A- | J94: 100.304 | K94: 4.78 | L94: 1,000(2) | N94: =IF(AND(M94<>"", M94<>0), IF(L94 <> "N/A", IF(M94>=VALUE(LEFT(L94, FIND("(", L94)-1)), J94*10*M94, 1000*M94), 1000*M94), "") | O94: =IF(AND(M94<>"",M94<>0),N94/$N$505, "") | P94: =IF(AND(M94<>"", M94<>0), F94*1000/100, "") | Q94: =IF(AND(M94<>"", M94<>0), NOW(), "") | R94: =IF(AND(M94<>"", M94<>0), ROUND((G94 - Q94)/365, 0), "") | S94: =IF(AND(M94<>"",M94<>0),MDURATION(Q94,G94,F94/100,K94/100,2), "") | T94: =IF(AND(M94<>"",M94<>0),YIELD(Q94,G94,F94/100,N94/(M94*10),100,2),"") | U94: =IF(AND(M94<>"",M94<>0), IF(E94 = "Muni", T94, IF(E94="Corp", T94*(1 -'Investor Input'!$C$4-'Investor Input'!$C$5), T94*(1 -'Investor Input'!$C$4))), T94) | V94: =IF(AND(M94<>"",M94<>0),(FV(K94/(2*100),(G94-Q94)*2/365, F94*1000/(2*100), -N94/M94))*M94, "") | W94: =IF(AND(M94<>"",M94<>0),V94-N94,"") | X94: =IF(AND(M94<>"",M94<>0),W94/N94,"") | Y94: =IF(AND(M94<>"", M94<>0), MONTH(G94), "") | Z94: =IF(AND(M94<>"", M94<>0), MONTH(EDATE(G94, 6)), "") | AA94: =IF(AND(M94<>"", M94<>0), F94*1000*M94/(100*2), "") | AB94: =IF(AND(AA94<>"",AA94<>0), IF(E94="Muni", AA94, IF(E94 = "Corp", (1-'Investor Input'!$C$4-'Investor Input'!$C$5)*AA94, (1-'Investor Input'!$C$4)*AA94)), AA94) | AC94: =IF(AND(M94<>"", M94<>0), H94, "") | AD94: =IF(AND(M94<>"", M94<>0), N94/$N$505*MATCH(AC94,'Misc Lists'!$K$2:$K$25,0), "") | AE94: =IF(AND(M94<>"", M94<>0), I94, "") | AF94: =IF(AND(M94<>"", M94<>0), N94/$N$505*MATCH(AE94,'Misc Lists'!$L$2:$L$25,0), "")
B95: 054561AJ4 | C95: N/A | D95: EQUITABLE HLDGS INC SER B NOTE 4.35000% 04/20/2028 CALL MAKE WHOLE | E95: Corp | F95: 4.35 | G95: 46863 | H95: BAA1 | I95: A- | J95: 98.774 | K95: 4.778 | L95: 200(2) | N95: =IF(AND(M95<>"", M95<>0), IF(L95 <> "N/A", IF(M95>=VALUE(LEFT(L95, FIND("(", L95)-1)), J95*10*M95, 1000*M95), 1000*M95), "") | O95: =IF(AND(M95<>"",M95<>0),N95/$N$505, "") | P95: =IF(AND(M95<>"", M95<>0), F95*1000/100, "") | Q95: =IF(AND(M95<>"", M95<>0), NOW(), "") | R95: =IF(AND(M95<>"", M95<>0), ROUND((G95 - Q95)/365, 0), "") | S95: =IF(AND(M95<>"",M95<>0),MDURATION(Q95,G95,F95/100,K95/100,2), "") | T95: =IF(AND(M95<>"",M95<>0),YIELD(Q95,G95,F95/100,N95/(M95*10),100,2),"") | U95: =IF(AND(M95<>"",M95<>0), IF(E95 = "Muni", T95, IF(E95="Corp", T95*(1 -'Investor Input'!$C$4-'Investor Input'!$C$5), T95*(1 -'Investor Input'!$C$4))), T95) | V95: =IF(AND(M95<>"",M95<>0),(FV(K95/(2*100),(G95-Q95)*2/365, F95*1000/(2*100), -N95/M95))*M95, "") | W95: =IF(AND(M95<>"",M95<>0),V95-N95,"") | X95: =IF(AND(M95<>"",M95<>0),W95/N95,"") | Y95: =IF(AND(M95<>"", M95<>0), MONTH(G95), "") | Z95: =IF(AND(M95<>"", M95<>0), MONTH(EDATE(G95, 6)), "") | AA95: =IF(AND(M95<>"", M95<>0), F95*1000*M95/(100*2), "") | AB95: =IF(AND(AA95<>"",AA95<>0), IF(E95="Muni", AA95, IF(E95 = "Corp", (1-'Investor Input'!$C$4-'Investor Input'!$C$5)*AA95, (1-'Investor Input'!$C$4)*AA95)), AA95) | AC95: =IF(AND(M95<>"", M95<>0), H95, "") | AD95: =IF(AND(M95<>"", M95<>0), N95/$N$505*MATCH(AC95,'Misc Lists'!$K$2:$K$25,0), "") | AE95: =IF(AND(M95<>"", M95<>0), I95, "") | AF95: =IF(AND(M95<>"", M95<>0), N95/$N$505*MATCH(AE95,'Misc Lists'!$L$2:$L$25,0), "")
B96: 06406YAA0 | C96: N/A | D96: BANK NEW YORK MELLONCORP SER K MTN 3.30000% 08/23/2029 | E96: Corp | F96: 3.3 | G96: 47353 | H96: A2 | I96: A- | J96: 94.145 | K96: 4.776 | L96: 200(1) | N96: =IF(AND(M96<>"", M96<>0), IF(L96 <> "N/A", IF(M96>=VALUE(LEFT(L96, FIND("(", L96)-1)), J96*10*M96, 1000*M96), 1000*M96), "") | O96: =IF(AND(M96<>"",M96<>0),N96/$N$505, "") | P96: =IF(AND(M96<>"", M96<>0), F96*1000/100, "") | Q96: =IF(AND(M96<>"", M96<>0), NOW(), "") | R96: =IF(AND(M96<>"", M96<>0), ROUND((G96 - Q96)/365, 0), "") | S96: =IF(AND(M96<>"",M96<>0),MDURATION(Q96,G96,F96/100,K96/100,2), "") | T96: =IF(AND(M96<>"",M96<>0),YIELD(Q96,G96,F96/100,N96/(M96*10),100,2),"") | U96: =IF(AND(M96<>"",M96<>0), IF(E96 = "Muni", T96, IF(E96="Corp", T96*(1 -'Investor Input'!$C$4-'Investor Input'!$C$5), T96*(1 -'Investor Input'!$C$4))), T96) | V96: =IF(AND(M96<>"",M96<>0),(FV(K96/(2*100),(G96-Q96)*2/365, F96*1000/(2*100), -N96/M96))*M96, "") | W96: =IF(AND(M96<>"",M96<>0),V96-N96,"") | X96: =IF(AND(M96<>"",M96<>0),W96/N96,"") | Y96: =IF(AND(M96<>"", M96<>0), MONTH(G96), "") | Z96: =IF(AND(M96<>"", M96<>0), MONTH(EDATE(G96, 6)), "") | AA96: =IF(AND(M96<>"", M96<>0), F96*1000*M96/(100*2), "") | AB96: =IF(AND(AA96<>"",AA96<>0), IF(E96="Muni", AA96, IF(E96 = "Corp", (1-'Investor Input'!$C$4-'Investor Input'!$C$5)*AA96, (1-'Investor Input'!$C$4)*AA96)), AA96) | AC96: =IF(AND(M96<>"", M96<>0), H96, "") | AD96: =IF(AND(M96<>"", M96<>0), N96/$N$505*MATCH(AC96,'Misc Lists'!$K$2:$K$25,0), "") | AE96: =IF(AND(M96<>"", M96<>0), I96, "") | AF96: =IF(AND(M96<>"", M96<>0), N96/$N$505*MATCH(AE96,'Misc Lists'!$L$2:$L$25,0), "")
B97: 05964HAS4 | C97: N/A | D97: BANCO SANTANDER S.A.SER 164 NOTE 5.29400% 08/18/2027 ISIN #US05964HAS40 | E97: Corp | F97: 5.294 | G97: 46617 | H97: BAA1 | I97: A- | J97: 101.177 | K97: 4.774 | L97: 200(200) | N97: =IF(AND(M97<>"", M97<>0), IF(L97 <> "N/A", IF(M97>=VALUE(LEFT(L97, FIND("(", L97)-1)), J97*10*M97, 1000*M97), 1000*M97), "") | O97: =IF(AND(M97<>"",M97<>0),N97/$N$505, "") | P97: =IF(AND(M97<>"", M97<>0), F97*1000/100, "") | Q97: =IF(AND(M97<>"", M97<>0), NOW(), "") | R97: =IF(AND(M97<>"", M97<>0), ROUND((G97 - Q97)/365, 0), "") | S97: =IF(AND(M97<>"",M97<>0),MDURATION(Q97,G97,F97/100,K97/100,2), "") | T97: =IF(AND(M97<>"",M97<>0),YIELD(Q97,G97,F97/100,N97/(M97*10),100,2),"") | U97: =IF(AND(M97<>"",M97<>0), IF(E97 = "Muni", T97, IF(E97="Corp", T97*(1 -'Investor Input'!$C$4-'Investor Input'!$C$5), T97*(1 -'Investor Input'!$C$4))), T97) | V97: =IF(AND(M97<>"",M97<>0),(FV(K97/(2*100),(G97-Q97)*2/365, F97*1000/(2*100), -N97/M97))*M97, "") | W97: =IF(AND(M97<>"",M97<>0),V97-N97,"") | X97: =IF(AND(M97<>"",M97<>0),W97/N97,"") | Y97: =IF(AND(M97<>"", M97<>0), MONTH(G97), "") | Z97: =IF(AND(M97<>"", M97<>0), MONTH(EDATE(G97, 6)), "") | AA97: =IF(AND(M97<>"", M97<>0), F97*1000*M97/(100*2), "") | AB97: =IF(AND(AA97<>"",AA97<>0), IF(E97="Muni", AA97, IF(E97 = "Corp", (1-'Investor Input'!$C$4-'Investor Input'!$C$5)*AA97, (1-'Investor Input'!$C$4)*AA97)), AA97) | AC97: =IF(AND(M97<>"", M97<>0), H97, "") | AD97: =IF(AND(M97<>"", M97<>0), N97/$N$505*MATCH(AC97,'Misc Lists'!$K$2:$K$25,0), "") | AE97: =IF(AND(M97<>"", M97<>0), I97, "") | AF97: =IF(AND(M97<>"", M97<>0), N97/$N$505*MATCH(AE97,'Misc Lists'!$L$2:$L$25,0), "")
B98: 10373QBL3 | C98: N/A | D98: BP CAP MKTS AMER INCNOTE CALL MAKE WHOLE3.63300% 04/06/2030 | E98: Corp | F98: 3.633 | G98: 47579 | H98: A1 | I98: A- | J98: 94.922 | K98: 4.773 | L98: 35(5) | N98: =IF(AND(M98<>"", M98<>0), IF(L98 <> "N/A", IF(M98>=VALUE(LEFT(L98, FIND("(", L98)-1)), J98*10*M98, 1000*M98), 1000*M98), "") | O98: =IF(AND(M98<>"",M98<>0),N98/$N$505, "") | P98: =IF(AND(M98<>"", M98<>0), F98*1000/100, "") | Q98: =IF(AND(M98<>"", M98<>0), NOW(), "") | R98: =IF(AND(M98<>"", M98<>0), ROUND((G98 - Q98)/365, 0), "") | S98: =IF(AND(M98<>"",M98<>0),MDURATION(Q98,G98,F98/100,K98/100,2), "") | T98: =IF(AND(M98<>"",M98<>0),YIELD(Q98,G98,F98/100,N98/(M98*10),100,2),"") | U98: =IF(AND(M98<>"",M98<>0), IF(E98 = "Muni", T98, IF(E98="Corp", T98*(1 -'Investor Input'!$C$4-'Investor Input'!$C$5), T98*(1 -'Investor Input'!$C$4))), T98) | V98: =IF(AND(M98<>"",M98<>0),(FV(K98/(2*100),(G98-Q98)*2/365, F98*1000/(2*100), -N98/M98))*M98, "") | W98: =IF(AND(M98<>"",M98<>0),V98-N98,"") | X98: =IF(AND(M98<>"",M98<>0),W98/N98,"") | Y98: =IF(AND(M98<>"", M98<>0), MONTH(G98), "") | Z98: =IF(AND(M98<>"", M98<>0), MONTH(EDATE(G98, 6)), "") | AA98: =IF(AND(M98<>"", M98<>0), F98*1000*M98/(100*2), "") | AB98: =IF(AND(AA98<>"",AA98<>0), IF(E98="Muni", AA98, IF(E98 = "Corp", (1-'Investor Input'!$C$4-'Investor Input'!$C$5)*AA98, (1-'Investor Input'!$C$4)*AA98)), AA98) | AC98: =IF(AND(M98<>"", M98<>0), H98, "") | AD98: =IF(AND(M98<>"", M98<>0), N98/$N$505*MATCH(AC98,'Misc Lists'!$K$2:$K$25,0), "") | AE98: =IF(AND(M98<>"", M98<>0), I98, "") | AF98: =IF(AND(M98<>"", M98<>0), N98/$N$505*MATCH(AE98,'Misc Lists'!$L$2:$L$25,0), "")
B99: 15189XBG2 | C99: N/A | D99: CENTERPOINT ENERGY HOUSTON ELE SER AP 4.80000% 03/15/2030 BOND CALL MAKE WHOLE | E99: Corp | F99: 4.8 | G99: 47557 | H99: A2 | I99: A | J99: 100.136 | K99: 4.768 | L99: 500(2) | N99: =IF(AND(M99<>"", M99<>0), IF(L99 <> "N/A", IF(M99>=VALUE(LEFT(L99, FIND("(", L99)-1)), J99*10*M99, 1000*M99), 1000*M99), "") | O99: =IF(AND(M99<>"",M99<>0),N99/$N$505, "") | P99: =IF(AND(M99<>"", M99<>0), F99*1000/100, "") | Q99: =IF(AND(M99<>"", M99<>0), NOW(), "") | R99: =IF(AND(M99<>"", M99<>0), ROUND((G99 - Q99)/365, 0), "") | S99: =IF(AND(M99<>"",M99<>0),MDURATION(Q99,G99,F99/100,K99/100,2), "") | T99: =IF(AND(M99<>"",M99<>0),YIELD(Q99,G99,F99/100,N99/(M99*10),100,2),"") | U99: =IF(AND(M99<>"",M99<>0), IF(E99 = "Muni", T99, IF(E99="Corp", T99*(1 -'Investor Input'!$C$4-'Investor Input'!$C$5), T99*(1 -'Investor Input'!$C$4))), T99) | V99: =IF(AND(M99<>"",M99<>0),(FV(K99/(2*100),(G99-Q99)*2/365, F99*1000/(2*100), -N99/M99))*M99, "") | W99: =IF(AND(M99<>"",M99<>0),V99-N99,"") | X99: =IF(AND(M99<>"",M99<>0),W99/N99,"") | Y99: =IF(AND(M99<>"", M99<>0), MONTH(G99), "") | Z99: =IF(AND(M99<>"", M99<>0), MONTH(EDATE(G99, 6)), "") | AA99: =IF(AND(M99<>"", M99<>0), F99*1000*M99/(100*2), "") | AB99: =IF(AND(AA99<>"",AA99<>0), IF(E99="Muni", AA99, IF(E99 = "Corp", (1-'Investor Input'!$C$4-'Investor Input'!$C$5)*AA99, (1-'Investor Input'!$C$4)*AA99)), AA99) | AC99: =IF(AND(M99<>"", M99<>0), H99, "") | AD99: =IF(AND(M99<>"", M99<>0), N99/$N$505*MATCH(AC99,'Misc Lists'!$K$2:$K$25,0), "") | AE99: =IF(AND(M99<>"", M99<>0), I99, "") | AF99: =IF(AND(M99<>"", M99<>0), N99/$N$505*MATCH(AE99,'Misc Lists'!$L$2:$L$25,0), "")
B100: 756109BK9 | C100: N/A | D100: REALTY INCOME CORP NOTE CALL MAKE WHOLE3.10000% 12/15/2029 | E100: Corp | F100: 3.1 | G100: 47467 | H100: A3 | I100: A- | J100: 92.973 | K100: 4.767 | L100: 750(2) | N100: =IF(AND(M100<>"", M100<>0), IF(L100 <> "N/A", IF(M100>=VALUE(LEFT(L100, FIND("(", L100)-1)), J100*10*M100, 1000*M100), 1000*M100), "") | O100: =IF(AND(M100<>"",M100<>0),N100/$N$505, "") | P100: =IF(AND(M100<>"", M100<>0), F100*1000/100, "") | Q100: =IF(AND(M100<>"", M100<>0), NOW(), "") | R100: =IF(AND(M100<>"", M100<>0), ROUND((G100 - Q100)/365, 0), "") | S100: =IF(AND(M100<>"",M100<>0),MDURATION(Q100,G100,F100/100,K100/100,2), "") | T100: =IF(AND(M100<>"",M100<>0),YIELD(Q100,G100,F100/100,N100/(M100*10),100,2),"") | U100: =IF(AND(M100<>"",M100<>0), IF(E100 = "Muni", T100, IF(E100="Corp", T100*(1 -'Investor Input'!$C$4-'Investor Input'!$C$5), T100*(1 -'Investor Input'!$C$4))), T100) | V100: =IF(AND(M100<>"",M100<>0),(FV(K100/(2*100),(G100-Q100)*2/365, F100*1000/(2*100), -N100/M100))*M100, "") | W100: =IF(AND(M100<>"",M100<>0),V100-N100,"") | X100: =IF(AND(M100<>"",M100<>0),W100/N100,"") | Y100: =IF(AND(M100<>"", M100<>0), MONTH(G100), "") | Z100: =IF(AND(M100<>"", M100<>0), MONTH(EDATE(G100, 6)), "") | AA100: =IF(AND(M100<>"", M100<>0), F100*1000*M100/(100*2), "") | AB100: =IF(AND(AA100<>"",AA100<>0), IF(E100="Muni", AA100, IF(E100 = "Corp", (1-'Investor Input'!$C$4-'Investor Input'!$C$5)*AA100, (1-'Investor Input'!$C$4)*AA100)), AA100) | AC100: =IF(AND(M100<>"", M100<>0), H100, "") | AD100: =IF(AND(M100<>"", M100<>0), N100/$N$505*MATCH(AC100,'Misc Lists'!$K$2:$K$25,0), "") | AE100: =IF(AND(M100<>"", M100<>0), I100, "") | AF100: =IF(AND(M100<>"", M100<>0), N100/$N$505*MATCH(AE100,'Misc Lists'!$L$2:$L$25,0), "")
B101: 26884ABM4 | C101: N/A | D101: ERP OPER LTD PARTNERSHIP NOTE 2.50000% 02/15/2030 CALL MAKE WHOLE | E101: Corp | F101: 2.5 | G101: 47529 | H101: A3 | I101: A- | J101: 90.149 | K101: 4.767 | L101: 500(1) | N101: =IF(AND(M101<>"", M101<>0), IF(L101 <> "N/A", IF(M101>=VALUE(LEFT(L101, FIND("(", L101)-1)), J101*10*M101, 1000*M101), 1000*M101), "") | O101: =IF(AND(M101<>"",M101<>0),N101/$N$505, "") | P101: =IF(AND(M101<>"", M101<>0), F101*1000/100, "") | Q101: =IF(AND(M101<>"", M101<>0), NOW(), "") | R101: =IF(AND(M101<>"", M101<>0), ROUND((G101 - Q101)/365, 0), "") | S101: =IF(AND(M101<>"",M101<>0),MDURATION(Q101,G101,F101/100,K101/100,2), "") | T101: =IF(AND(M101<>"",M101<>0),YIELD(Q101,G101,F101/100,N101/(M101*10),100,2),"") | U101: =IF(AND(M101<>"",M101<>0), IF(E101 = "Muni", T101, IF(E101="Corp", T101*(1 -'Investor Input'!$C$4-'Investor Input'!$C$5), T101*(1 -'Investor Input'!$C$4))), T101) | V101: =IF(AND(M101<>"",M101<>0),(FV(K101/(2*100),(G101-Q101)*2/365, F101*1000/(2*100), -N101/M101))*M101, "") | W101: =IF(AND(M101<>"",M101<>0),V101-N101,"") | X101: =IF(AND(M101<>"",M101<>0),W101/N101,"") | Y101: =IF(AND(M101<>"", M101<>0), MONTH(G101), "") | Z101: =IF(AND(M101<>"", M101<>0), MONTH(EDATE(G101, 6)), "") | AA101: =IF(AND(M101<>"", M101<>0), F101*1000*M101/(100*2), "") | AB101: =IF(AND(AA101<>"",AA101<>0), IF(E101="Muni", AA101, IF(E101 = "Corp", (1-'Investor Input'!$C$4-'Investor Input'!$C$5)*AA101, (1-'Investor Input'!$C$4)*AA101)), AA101) | AC101: =IF(AND(M101<>"", M101<>0), H101, "") | AD101: =IF(AND(M101<>"", M101<>0), N101/$N$505*MATCH(AC101,'Misc Lists'!$K$2:$K$25,0), "") | AE101: =IF(AND(M101<>"", M101<>0), I101, "") | AF101: =IF(AND(M101<>"", M101<>0), N101/$N$505*MATCH(AE101,'Misc Lists'!$L$2:$L$25,0), "")
B102: 678858BU4 | C102: N/A | D102: OKLAHOMA GAS &ELEC CO NOTE 3.30000% 03/15/2030 CALL MAKE WHOLE | E102: Corp | F102: 3.3 | G102: 47557 | H102: A3 | I102: A- | J102: 93.54 | K102: 4.765 | L102: 500(2) | N102: =IF(AND(M102<>"", M102<>0), IF(L102 <> "N/A", IF(M102>=VALUE(LEFT(L102, FIND("(", L102)-1)), J102*10*M102, 1000*M102), 1000*M102), "") | O102: =IF(AND(M102<>"",M102<>0),N102/$N$505, "") | P102: =IF(AND(M102<>"", M102<>0), F102*1000/100, "") | Q102: =IF(AND(M102<>"", M102<>0), NOW(), "") | R102: =IF(AND(M102<>"", M102<>0), ROUND((G102 - Q102)/365, 0), "") | S102: =IF(AND(M102<>"",M102<>0),MDURATION(Q102,G102,F102/100,K102/100,2), "") | T102: =IF(AND(M102<>"",M102<>0),YIELD(Q102,G102,F102/100,N102/(M102*10),100,2),"") | U102: =IF(AND(M102<>"",M102<>0), IF(E102 = "Muni", T102, IF(E102="Corp", T102*(1 -'Investor Input'!$C$4-'Investor Input'!$C$5), T102*(1 -'Investor Input'!$C$4))), T102) | V102: =IF(AND(M102<>"",M102<>0),(FV(K102/(2*100),(G102-Q102)*2/365, F102*1000/(2*100), -N102/M102))*M102, "") | W102: =IF(AND(M102<>"",M102<>0),V102-N102,"") | X102: =IF(AND(M102<>"",M102<>0),W102/N102,"") | Y102: =IF(AND(M102<>"", M102<>0), MONTH(G102), "") | Z102: =IF(AND(M102<>"", M102<>0), MONTH(EDATE(G102, 6)), "") | AA102: =IF(AND(M102<>"", M102<>0), F102*1000*M102/(100*2), "") | AB102: =IF(AND(AA102<>"",AA102<>0), IF(E102="Muni", AA102, IF(E102 = "Corp", (1-'Investor Input'!$C$4-'Investor Input'!$C$5)*AA102, (1-'Investor Input'!$C$4)*AA102)), AA102) | AC102: =IF(AND(M102<>"", M102<>0), H102, "") | AD102: =IF(AND(M102<>"", M102<>0), N102/$N$505*MATCH(AC102,'Misc Lists'!$K$2:$K$25,0), "") | AE102: =IF(AND(M102<>"", M102<>0), I102, "") | AF102: =IF(AND(M102<>"", M102<>0), N102/$N$505*MATCH(AE102,'Misc Lists'!$L$2:$L$25,0), "")
B103: 20030NDG3 | C103: N/A | D103: COMCAST CORP NEW NOTE CALL MAKE WHOLE3.40000% 04/01/2030 | E103: Corp | F103: 3.4 | G103: 47574 | H103: A3 | I103: A- | J103: 93.937 | K103: 4.764 | L103: 500(2) | N103: =IF(AND(M103<>"", M103<>0), IF(L103 <> "N/A", IF(M103>=VALUE(LEFT(L103, FIND("(", L103)-1)), J103*10*M103, 1000*M103), 1000*M103), "") | O103: =IF(AND(M103<>"",M103<>0),N103/$N$505, "") | P103: =IF(AND(M103<>"", M103<>0), F103*1000/100, "") | Q103: =IF(AND(M103<>"", M103<>0), NOW(), "") | R103: =IF(AND(M103<>"", M103<>0), ROUND((G103 - Q103)/365, 0), "") | S103: =IF(AND(M103<>"",M103<>0),MDURATION(Q103,G103,F103/100,K103/100,2), "") | T103: =IF(AND(M103<>"",M103<>0),YIELD(Q103,G103,F103/100,N103/(M103*10),100,2),"") | U103: =IF(AND(M103<>"",M103<>0), IF(E103 = "Muni", T103, IF(E103="Corp", T103*(1 -'Investor Input'!$C$4-'Investor Input'!$C$5), T103*(1 -'Investor Input'!$C$4))), T103) | V103: =IF(AND(M103<>"",M103<>0),(FV(K103/(2*100),(G103-Q103)*2/365, F103*1000/(2*100), -N103/M103))*M103, "") | W103: =IF(AND(M103<>"",M103<>0),V103-N103,"") | X103: =IF(AND(M103<>"",M103<>0),W103/N103,"") | Y103: =IF(AND(M103<>"", M103<>0), MONTH(G103), "") | Z103: =IF(AND(M103<>"", M103<>0), MONTH(EDATE(G103, 6)), "") | AA103: =IF(AND(M103<>"", M103<>0), F103*1000*M103/(100*2), "") | AB103: =IF(AND(AA103<>"",AA103<>0), IF(E103="Muni", AA103, IF(E103 = "Corp", (1-'Investor Input'!$C$4-'Investor Input'!$C$5)*AA103, (1-'Investor Input'!$C$4)*AA103)), AA103) | AC103: =IF(AND(M103<>"", M103<>0), H103, "") | AD103: =IF(AND(M103<>"", M103<>0), N103/$N$505*MATCH(AC103,'Misc Lists'!$K$2:$K$25,0), "") | AE103: =IF(AND(M103<>"", M103<>0), I103, "") | AF103: =IF(AND(M103<>"", M103<>0), N103/$N$505*MATCH(AE103,'Misc Lists'!$L$2:$L$25,0), "")
B104: 842400HQ9 | C104: N/A | D104: SOUTHERN CALIFORNIA EDISON CO SER 2022D 4.70000% 06/01/2027 BOND CALL MAKE WHOLE | E104: Corp | F104: 4.7 | G104: 46539 | H104: A2 | I104: A- | J104: 99.862 | K104: 4.763 | L104: 550(1) | N104: =IF(AND(M104<>"", M104<>0), IF(L104 <> "N/A", IF(M104>=VALUE(LEFT(L104, FIND("(", L104)-1)), J104*10*M104, 1000*M104), 1000*M104), "") | O104: =IF(AND(M104<>"",M104<>0),N104/$N$505, "") | P104: =IF(AND(M104<>"", M104<>0), F104*1000/100, "") | Q104: =IF(AND(M104<>"", M104<>0), NOW(), "") | R104: =IF(AND(M104<>"", M104<>0), ROUND((G104 - Q104)/365, 0), "") | S104: =IF(AND(M104<>"",M104<>0),MDURATION(Q104,G104,F104/100,K104/100,2), "") | T104: =IF(AND(M104<>"",M104<>0),YIELD(Q104,G104,F104/100,N104/(M104*10),100,2),"") | U104: =IF(AND(M104<>"",M104<>0), IF(E104 = "Muni", T104, IF(E104="Corp", T104*(1 -'Investor Input'!$C$4-'Investor Input'!$C$5), T104*(1 -'Investor Input'!$C$4))), T104) | V104: =IF(AND(M104<>"",M104<>0),(FV(K104/(2*100),(G104-Q104)*2/365, F104*1000/(2*100), -N104/M104))*M104, "") | W104: =IF(AND(M104<>"",M104<>0),V104-N104,"") | X104: =IF(AND(M104<>"",M104<>0),W104/N104,"") | Y104: =IF(AND(M104<>"", M104<>0), MONTH(G104), "") | Z104: =IF(AND(M104<>"", M104<>0), MONTH(EDATE(G104, 6)), "") | AA104: =IF(AND(M104<>"", M104<>0), F104*1000*M104/(100*2), "") | AB104: =IF(AND(AA104<>"",AA104<>0), IF(E104="Muni", AA104, IF(E104 = "Corp", (1-'Investor Input'!$C$4-'Investor Input'!$C$5)*AA104, (1-'Investor Input'!$C$4)*AA104)), AA104) | AC104: =IF(AND(M104<>"", M104<>0), H104, "") | AD104: =IF(AND(M104<>"", M104<>0), N104/$N$505*MATCH(AC104,'Misc Lists'!$K$2:$K$25,0), "") | AE104: =IF(AND(M104<>"", M104<>0), I104, "") | AF104: =IF(AND(M104<>"", M104<>0), N104/$N$505*MATCH(AE104,'Misc Lists'!$L$2:$L$25,0), "")
B105: 257375AP0 | C105: N/A | D105: DOMINION ENERGY GAS HLDGS LLC SER B NOTE3.00000% 11/15/2029 CALL MAKE WHOLE | E105: Corp | F105: 3 | G105: 47437 | H105: BAA1 | I105: A- | J105: 92.685 | K105: 4.763 | L105: 184(2) | N105: =IF(AND(M105<>"", M105<>0), IF(L105 <> "N/A", IF(M105>=VALUE(LEFT(L105, FIND("(", L105)-1)), J105*10*M105, 1000*M105), 1000*M105), "") | O105: =IF(AND(M105<>"",M105<>0),N105/$N$505, "") | P105: =IF(AND(M105<>"", M105<>0), F105*1000/100, "") | Q105: =IF(AND(M105<>"", M105<>0), NOW(), "") | R105: =IF(AND(M105<>"", M105<>0), ROUND((G105 - Q105)/365, 0), "") | S105: =IF(AND(M105<>"",M105<>0),MDURATION(Q105,G105,F105/100,K105/100,2), "") | T105: =IF(AND(M105<>"",M105<>0),YIELD(Q105,G105,F105/100,N105/(M105*10),100,2),"") | U105: =IF(AND(M105<>"",M105<>0), IF(E105 = "Muni", T105, IF(E105="Corp", T105*(1 -'Investor Input'!$C$4-'Investor Input'!$C$5), T105*(1 -'Investor Input'!$C$4))), T105) | V105: =IF(AND(M105<>"",M105<>0),(FV(K105/(2*100),(G105-Q105)*2/365, F105*1000/(2*100), -N105/M105))*M105, "") | W105: =IF(AND(M105<>"",M105<>0),V105-N105,"") | X105: =IF(AND(M105<>"",M105<>0),W105/N105,"") | Y105: =IF(AND(M105<>"", M105<>0), MONTH(G105), "") | Z105: =IF(AND(M105<>"", M105<>0), MONTH(EDATE(G105, 6)), "") | AA105: =IF(AND(M105<>"", M105<>0), F105*1000*M105/(100*2), "") | AB105: =IF(AND(AA105<>"",AA105<>0), IF(E105="Muni", AA105, IF(E105 = "Corp", (1-'Investor Input'!$C$4-'Investor Input'!$C$5)*AA105, (1-'Investor Input'!$C$4)*AA105)), AA105) | AC105: =IF(AND(M105<>"", M105<>0), H105, "") | AD105: =IF(AND(M105<>"", M105<>0), N105/$N$505*MATCH(AC105,'Misc Lists'!$K$2:$K$25,0), "") | AE105: =IF(AND(M105<>"", M105<>0), I105, "") | AF105: =IF(AND(M105<>"", M105<>0), N105/$N$505*MATCH(AE105,'Misc Lists'!$L$2:$L$25,0), "")
... B109: 718172DA4 | C109: N/A | D109: PHILIP MORRIS INTL INC NOTE 5.12500% 02/15/2030 CALL MAKE WHOLE | E109: Corp | F109: 5.125 | G109: 47529 | H109: A2 | I109: A- | J109: 101.589 | K109: 4.758 | L109: 500(2) | N109: =IF(AND(M109<>"", M109<>0), IF(L109 <> "N/A", IF(M109>=VALUE(LEFT(L109, FIND("(", L109)-1)), J109*10*M109, 1000*M109), 1000*M109), "") | O109: =IF(AND(M109<>"",M109<>0),N109/$N$505, "") | P109: =IF(AND(M109<>"", M109<>0), F109*1000/100, "") | Q109: =IF(AND(M109<>"", M109<>0), NOW(), "") | R109: =IF(AND(M109<>"", M109<>0), ROUND((G109 - Q109)/365, 0), "") | S109: =IF(AND(M109<>"",M109<>0),MDURATION(Q109,G109,F109/100,K109/100,2), "") | T109: =IF(AND(M109<>"",M109<>0),YIELD(Q109,G109,F109/100,N109/(M109*10),100,2),"") | U109: =IF(AND(M109<>"",M109<>0), IF(E109 = "Muni", T109, IF(E109="Corp", T109*(1 -'Investor Input'!$C$4-'Investor Input'!$C$5), T109*(1 -'Investor Input'!$C$4))), T109) | V109: =IF(AND(M109<>"",M109<>0),(FV(K109/(2*100),(G109-Q109)*2/365, F109*1000/(2*100), -N109/M109))*M109, "") | W109: =IF(AND(M109<>"",M109<>0),V109-N109,"") | X109: =IF(AND(M109<>"",M109<>0),W109/N109,"") | Y109: =IF(AND(M109<>"", M109<>0), MONTH(G109), "") | Z109: =IF(AND(M109<>"", M109<>0), MONTH(EDATE(G109, 6)), "") | AA109: =IF(AND(M109<>"", M109<>0), F109*1000*M109/(100*2), "") | AB109: =IF(AND(AA109<>"",AA109<>0), IF(E109="Muni", AA109, IF(E109 = "Corp", (1-'Investor Input'!$C$4-'Investor Input'!$C$5)*AA109, (1-'Investor Input'!$C$4)*AA109)), AA109) | AC109: =IF(AND(M109<>"", M109<>0), H109, "") | AD109: =IF(AND(M109<>"", M109<>0), N109/$N$505*MATCH(AC109,'Misc Lists'!$K$2:$K$25,0), "") | AE109: =IF(AND(M109<>"", M109<>0), I109, "") | AF109: =IF(AND(M109<>"", M109<>0), N109/$N$505*MATCH(AE109,'Misc Lists'!$L$2:$L$25,0), "")
B110: 29736RAP5 | C110: N/A | D110: LAUDER ESTEE COS INCNOTE CALL MAKE WHOLE2.37500% 12/01/2029 | E110: Corp | F110: 2.375 | G110: 47453 | H110: A2 | I110: A- | J110: 90.036 | K110: 4.756 | L110: 500(2) | M110: 50 | N110: =IF(AND(M110<>"", M110<>0), IF(L110 <> "N/A", IF(M110>=VALUE(LEFT(L110, FIND("(", L110)-1)), J110*10*M110, 1000*M110), 1000*M110), "") -> 50000 | O110: =IF(AND(M110<>"",M110<>0),N110/$N$505, "") -> 0.049997948 | P110: =IF(AND(M110<>"", M110<>0), F110*1000/100, "") -> 23.75 | Q110: =IF(AND(M110<>"", M110<>0), NOW(), "") -> 45791.491 | R110: =IF(AND(M110<>"", M110<>0), ROUND((G110 - Q110)/365, 0), "") -> 5 | S110: =IF(AND(M110<>"",M110<>0),MDURATION(Q110,G110,F110/100,K110/100,2), "") -> 4.1737635 | T110: =IF(AND(M110<>"",M110<>0),YIELD(Q110,G110,F110/100,N110/(M110*10),100,2),"") -> 0.023748599 | U110: =IF(AND(M110<>"",M110<>0), IF(E110 = "Muni", T110, IF(E110="Corp", T110*(1 -'Investor Input'!$C$4-'Investor Input'!$C$5), T110*(1 -'Investor Input'!$C$4))), T110) -> 0.012824244 | V110: =IF(AND(M110<>"",M110<>0),(FV(K110/(2*100),(G110-Q110)*2/365, F110*1000/(2*100), -N110/M110))*M110, "") -> 55971.939 | W110: =IF(AND(M110<>"",M110<>0),V110-N110,"") -> 5971.9389 | X110: =IF(AND(M110<>"",M110<>0),W110/N110,"") -> 0.11943878 | Y110: =IF(AND(M110<>"", M110<>0), MONTH(G110), "") -> 12 | Z110: =IF(AND(M110<>"", M110<>0), MONTH(EDATE(G110, 6)), "") -> 6 | AA110: =IF(AND(M110<>"", M110<>0), F110*1000*M110/(100*2), "") -> 593.75 | AB110: =IF(AND(AA110<>"",AA110<>0), IF(E110="Muni", AA110, IF(E110 = "Corp", (1-'Investor Input'!$C$4-'Investor Input'!$C$5)*AA110, (1-'Investor Input'!$C$4)*AA110)), AA110) -> 320.625 | AC110: =IF(AND(M110<>"", M110<>0), H110, "") -> A2 | AD110: =IF(AND(M110<>"", M110<>0), N110/$N$505*MATCH(AC110,'Misc Lists'!$K$2:$K$25,0), "") -> 0.34998563 | AE110: =IF(AND(M110<>"", M110<>0), I110, "") -> A- | AF110: =IF(AND(M110<>"", M110<>0), N110/$N$505*MATCH(AE110,'Misc Lists'!$L$2:$L$25,0), "") -> 0.39998358
B111: 718172CP2 | C111: N/A | D111: PHILIP MORRIS INTL INC NOTE 2.10000% 05/01/2030 CALL MAKE WHOLE | E111: Corp | F111: 2.1 | G111: 47604 | H111: A2 | I111: A- | J111: 88.019 | K111: 4.756 | L111: 500(2) | N111: =IF(AND(M111<>"", M111<>0), IF(L111 <> "N/A", IF(M111>=VALUE(LEFT(L111, FIND("(", L111)-1)), J111*10*M111, 1000*M111), 1000*M111), "") | O111: =IF(AND(M111<>"",M111<>0),N111/$N$505, "") | P111: =IF(AND(M111<>"", M111<>0), F111*1000/100, "") | Q111: =IF(AND(M111<>"", M111<>0), NOW(), "") | R111: =IF(AND(M111<>"", M111<>0), ROUND((G111 - Q111)/365, 0), "") | S111: =IF(AND(M111<>"",M111<>0),MDURATION(Q111,G111,F111/100,K111/100,2), "") | T111: =IF(AND(M111<>"",M111<>0),YIELD(Q111,G111,F111/100,N111/(M111*10),100,2),"") | U111: =IF(AND(M111<>"",M111<>0), IF(E111 = "Muni", T111, IF(E111="Corp", T111*(1 -'Investor Input'!$C$4-'Investor Input'!$C$5), T111*(1 -'Investor Input'!$C$4))), T111) | V111: =IF(AND(M111<>"",M111<>0),(FV(K111/(2*100),(G111-Q111)*2/365, F111*1000/(2*100), -N111/M111))*M111, "") | W111: =IF(AND(M111<>"",M111<>0),V111-N111,"") | X111: =IF(AND(M111<>"",M111<>0),W111/N111,"") | Y111: =IF(AND(M111<>"", M111<>0), MONTH(G111), "") | Z111: =IF(AND(M111<>"", M111<>0), MONTH(EDATE(G111, 6)), "") | AA111: =IF(AND(M111<>"", M111<>0), F111*1000*M111/(100*2), "") | AB111: =IF(AND(AA111<>"",AA111<>0), IF(E111="Muni", AA111, IF(E111 = "Corp", (1-'Investor Input'!$C$4-'Investor Input'!$C$5)*AA111, (1-'Investor Input'!$C$4)*AA111)), AA111) | AC111: =IF(AND(M111<>"", M111<>0), H111, "") | AD111: =IF(AND(M111<>"", M111<>0), N111/$N$505*MATCH(AC111,'Misc Lists'!$K$2:$K$25,0), "") | AE111: =IF(AND(M111<>"", M111<>0), I111, "") | AF111: =IF(AND(M111<>"", M111<>0), N111/$N$505*MATCH(AE111,'Misc Lists'!$L$2:$L$25,0), "")
B112: 89115A2Y7 | C112: N/A | D112: TORONTO DOMINION BK ONT SER C MTN 4.99400% 04/05/2029 CALL MAKE WHOLE | E112: Corp | F112: 4.994 | G112: 47213 | H112: A2 | I112: A- | J112: 100.874 | K112: 4.754 | L112: 500(2) | N112: =IF(AND(M112<>"", M112<>0), IF(L112 <> "N/A", IF(M112>=VALUE(LEFT(L112, FIND("(", L112)-1)), J112*10*M112, 1000*M112), 1000*M112), "") | O112: =IF(AND(M112<>"",M112<>0),N112/$N$505, "") | P112: =IF(AND(M112<>"", M112<>0), F112*1000/100, "") | Q112: =IF(AND(M112<>"", M112<>0), NOW(), "") | R112: =IF(AND(M112<>"", M112<>0), ROUND((G112 - Q112)/365, 0), "") | S112: =IF(AND(M112<>"",M112<>0),MDURATION(Q112,G112,F112/100,K112/100,2), "") | T112: =IF(AND(M112<>"",M112<>0),YIELD(Q112,G112,F112/100,N112/(M112*10),100,2),"") | U112: =IF(AND(M112<>"",M112<>0), IF(E112 = "Muni", T112, IF(E112="Corp", T112*(1 -'Investor Input'!$C$4-'Investor Input'!$C$5), T112*(1 -'Investor Input'!$C$4))), T112) | V112: =IF(AND(M112<>"",M112<>0),(FV(K112/(2*100),(G112-Q112)*2/365, F112*1000/(2*100), -N112/M112))*M112, "") | W112: =IF(AND(M112<>"",M112<>0),V112-N112,"") | X112: =IF(AND(M112<>"",M112<>0),W112/N112,"") | Y112: =IF(AND(M112<>"", M112<>0), MONTH(G112), "") | Z112: =IF(AND(M112<>"", M112<>0), MONTH(EDATE(G112, 6)), "") | AA112: =IF(AND(M112<>"", M112<>0), F112*1000*M112/(100*2), "") | AB112: =IF(AND(AA112<>"",AA112<>0), IF(E112="Muni", AA112, IF(E112 = "Corp", (1-'Investor Input'!$C$4-'Investor Input'!$C$5)*AA112, (1-'Investor Input'!$C$4)*AA112)), AA112) | AC112: =IF(AND(M112<>"", M112<>0), H112, "") | AD112: =IF(AND(M112<>"", M112<>0), N112/$N$505*MATCH(AC112,'Misc Lists'!$K$2:$K$25,0), "") | AE112: =IF(AND(M112<>"", M112<>0), I112, "") | AF112: =IF(AND(M112<>"", M112<>0), N112/$N$505*MATCH(AE112,'Misc Lists'!$L$2:$L$25,0), "")
B113: 678858BV2 | C113: N/A | D113: OKLAHOMA GAS &ELEC CO NOTE 3.25000% 04/01/2030 CALL MAKE WHOLE | E113: Corp | F113: 3.25 | G113: 47574 | H113: A3 | I113: A- | J113: 93.312 | K113: 4.754 | L113: 500(2) | N113: =IF(AND(M113<>"", M113<>0), IF(L113 <> "N/A", IF(M113>=VALUE(LEFT(L113, FIND("(", L113)-1)), J113*10*M113, 1000*M113), 1000*M113), "") | O113: =IF(AND(M113<>"",M113<>0),N113/$N$505, "") | P113: =IF(AND(M113<>"", M113<>0), F113*1000/100, "") | Q113: =IF(AND(M113<>"", M113<>0), NOW(), "") | R113: =IF(AND(M113<>"", M113<>0), ROUND((G113 - Q113)/365, 0), "") | S113: =IF(AND(M113<>"",M113<>0),MDURATION(Q113,G113,F113/100,K113/100,2), "") | T113: =IF(AND(M113<>"",M113<>0),YIELD(Q113,G113,F113/100,N113/(M113*10),100,2),"") | U113: =IF(AND(M113<>"",M113<>0), IF(E113 = "Muni", T113, IF(E113="Corp", T113*(1 -'Investor Input'!$C$4-'Investor Input'!$C$5), T113*(1 -'Investor Input'!$C$4))), T113) | V113: =IF(AND(M113<>"",M113<>0),(FV(K113/(2*100),(G113-Q113)*2/365, F113*1000/(2*100), -N113/M113))*M113, "") | W113: =IF(AND(M113<>"",M113<>0),V113-N113,"") | X113: =IF(AND(M113<>"",M113<>0),W113/N113,"") | Y113: =IF(AND(M113<>"", M113<>0), MONTH(G113), "") | Z113: =IF(AND(M113<>"", M113<>0), MONTH(EDATE(G113, 6)), "") | AA113: =IF(AND(M113<>"", M113<>0), F113*1000*M113/(100*2), "") | AB113: =IF(AND(AA113<>"",AA113<>0), IF(E113="Muni", AA113, IF(E113 = "Corp", (1-'Investor Input'!$C$4-'Investor Input'!$C$5)*AA113, (1-'Investor Input'!$C$4)*AA113)), AA113) | AC113: =IF(AND(M113<>"", M113<>0), H113, "") | AD113: =IF(AND(M113<>"", M113<>0), N113/$N$505*MATCH(AC113,'Misc Lists'!$K$2:$K$25,0), "") | AE113: =IF(AND(M113<>"", M113<>0), I113, "") | AF113: =IF(AND(M113<>"", M113<>0), N113/$N$505*MATCH(AE113,'Misc Lists'!$L$2:$L$25,0), "")
B114: 74251VAK8 | C114: N/A | D114: PRINCIPAL FINANCIAL GROUP INC NOTE 3.40000% 05/15/2025 | E114: Corp | F114: 3.4 | G114: 45792 | H114: BAA1 | I114: A- | J114: 99.756 | K114: 4.753 | L114: 10(2) | N114: =IF(AND(M114<>"", M114<>0), IF(L114 <> "N/A", IF(M114>=VALUE(LEFT(L114, FIND("(", L114)-1)), J114*10*M114, 1000*M114), 1000*M114), "") | O114: =IF(AND(M114<>"",M114<>0),N114/$N$505, "") | P114: =IF(AND(M114<>"", M114<>0), F114*1000/100, "") | Q114: =IF(AND(M114<>"", M114<>0), NOW(), "") | R114: =IF(AND(M114<>"", M114<>0), ROUND((G114 - Q114)/365, 0), "") | S114: =IF(AND(M114<>"",M114<>0),MDURATION(Q114,G114,F114/100,K114/100,2), "") | T114: =IF(AND(M114<>"",M114<>0),YIELD(Q114,G114,F114/100,N114/(M114*10),100,2),"") | U114: =IF(AND(M114<>"",M114<>0), IF(E114 = "Muni", T114, IF(E114="Corp", T114*(1 -'Investor Input'!$C$4-'Investor Input'!$C$5), T114*(1 -'Investor Input'!$C$4))), T114) | V114: =IF(AND(M114<>"",M114<>0),(FV(K114/(2*100),(G114-Q114)*2/365, F114*1000/(2*100), -N114/M114))*M114, "") | W114: =IF(AND(M114<>"",M114<>0),V114-N114,"") | X114: =IF(AND(M114<>"",M114<>0),W114/N114,"") | Y114: =IF(AND(M114<>"", M114<>0), MONTH(G114), "") | Z114: =IF(AND(M114<>"", M114<>0), MONTH(EDATE(G114, 6)), "") | AA114: =IF(AND(M114<>"", M114<>0), F114*1000*M114/(100*2), "") | AB114: =IF(AND(AA114<>"",AA114<>0), IF(E114="Muni", AA114, IF(E114 = "Corp", (1-'Investor Input'!$C$4-'Investor Input'!$C$5)*AA114, (1-'Investor Input'!$C$4)*AA114)), AA114) | AC114: =IF(AND(M114<>"", M114<>0), H114, "") | AD114: =IF(AND(M114<>"", M114<>0), N114/$N$505*MATCH(AC114,'Misc Lists'!$K$2:$K$25,0), "") | AE114: =IF(AND(M114<>"", M114<>0), I114, "") | AF114: =IF(AND(M114<>"", M114<>0), N114/$N$505*MATCH(AE114,'Misc Lists'!$L$2:$L$25,0), "")
B115: 48130CZV0 | C115: N/A | D115: JPMORGAN CHASE &CO SER E MTN 4.90000% 02/26/2030 | E115: Corp | F115: 4.9 | G115: 47540 | H115: A1 | I115: A | J115: 100.636 | K115: 4.752 | L115: 1,492(1) | N115: =IF(AND(M115<>"", M115<>0), IF(L115 <> "N/A", IF(M115>=VALUE(LEFT(L115, FIND("(", L115)-1)), J115*10*M115, 1000*M115), 1000*M115), "") | O115: =IF(AND(M115<>"",M115<>0),N115/$N$505, "") | P115: =IF(AND(M115<>"", M115<>0), F115*1000/100, "") | Q115: =IF(AND(M115<>"", M115<>0), NOW(), "") | R115: =IF(AND(M115<>"", M115<>0), ROUND((G115 - Q115)/365, 0), "") | S115: =IF(AND(M115<>"",M115<>0),MDURATION(Q115,G115,F115/100,K115/100,2), "") | T115: =IF(AND(M115<>"",M115<>0),YIELD(Q115,G115,F115/100,N115/(M115*10),100,2),"") | U115: =IF(AND(M115<>"",M115<>0), IF(E115 = "Muni", T115, IF(E115="Corp", T115*(1 -'Investor Input'!$C$4-'Investor Input'!$C$5), T115*(1 -'Investor Input'!$C$4))), T115) | V115: =IF(AND(M115<>"",M115<>0),(FV(K115/(2*100),(G115-Q115)*2/365, F115*1000/(2*100), -N115/M115))*M115, "") | W115: =IF(AND(M115<>"",M115<>0),V115-N115,"") | X115: =IF(AND(M115<>"",M115<>0),W115/N115,"") | Y115: =IF(AND(M115<>"", M115<>0), MONTH(G115), "") | Z115: =IF(AND(M115<>"", M115<>0), MONTH(EDATE(G115, 6)), "") | AA115: =IF(AND(M115<>"", M115<>0), F115*1000*M115/(100*2), "") | AB115: =IF(AND(AA115<>"",AA115<>0), IF(E115="Muni", AA115, IF(E115 = "Corp", (1-'Investor Input'!$C$4-'Investor Input'!$C$5)*AA115, (1-'Investor Input'!$C$4)*AA115)), AA115) | AC115: =IF(AND(M115<>"", M115<>0), H115, "") | AD115: =IF(AND(M115<>"", M115<>0), N115/$N$505*MATCH(AC115,'Misc Lists'!$K$2:$K$25,0), "") | AE115: =IF(AND(M115<>"", M115<>0), I115, "") | AF115: =IF(AND(M115<>"", M115<>0), N115/$N$505*MATCH(AE115,'Misc Lists'!$L$2:$L$25,0), "")
B116: 459200LG4 | C116: N/A | D116: INTERNATIONAL BUSINESS MACHS NOTE 4.80000% 02/10/2030 CALL MAKE WHOLE | E116: Corp | F116: 4.8 | G116: 47524 | H116: A3 | I116: A- | J116: 100.212 | K116: 4.75 | L116: 425(100) | N116: =IF(AND(M116<>"", M116<>0), IF(L116 <> "N/A", IF(M116>=VALUE(LEFT(L116, FIND("(", L116)-1)), J116*10*M116, 1000*M116), 1000*M116), "") | O116: =IF(AND(M116<>"",M116<>0),N116/$N$505, "") | P116: =IF(AND(M116<>"", M116<>0), F116*1000/100, "") | Q116: =IF(AND(M116<>"", M116<>0), NOW(), "") | R116: =IF(AND(M116<>"", M116<>0), ROUND((G116 - Q116)/365, 0), "") | S116: =IF(AND(M116<>"",M116<>0),MDURATION(Q116,G116,F116/100,K116/100,2), "") | T116: =IF(AND(M116<>"",M116<>0),YIELD(Q116,G116,F116/100,N116/(M116*10),100,2),"") | U116: =IF(AND(M116<>"",M116<>0), IF(E116 = "Muni", T116, IF(E116="Corp", T116*(1 -'Investor Input'!$C$4-'Investor Input'!$C$5), T116*(1 -'Investor Input'!$C$4))), T116) | V116: =IF(AND(M116<>"",M116<>0),(FV(K116/(2*100),(G116-Q116)*2/365, F116*1000/(2*100), -N116/M116))*M116, "") | W116: =IF(AND(M116<>"",M116<>0),V116-N116,"") | X116: =IF(AND(M116<>"",M116<>0),W116/N116,"") | Y116: =IF(AND(M116<>"", M116<>0), MONTH(G116), "") | Z116: =IF(AND(M116<>"", M116<>0), MONTH(EDATE(G116, 6)), "") | AA116: =IF(AND(M116<>"", M116<>0), F116*1000*M116/(100*2), "") | AB116: =IF(AND(AA116<>"",AA116<>0), IF(E116="Muni", AA116, IF(E116 = "Corp", (1-'Investor Input'!$C$4-'Investor Input'!$C$5)*AA116, (1-'Investor Input'!$C$4)*AA116)), AA116) | AC116: =IF(AND(M116<>"", M116<>0), H116, "") | AD116: =IF(AND(M116<>"", M116<>0), N116/$N$505*MATCH(AC116,'Misc Lists'!$K$2:$K$25,0), "") | AE116: =IF(AND(M116<>"", M116<>0), I116, "") | AF116: =IF(AND(M116<>"", M116<>0), N116/$N$505*MATCH(AE116,'Misc Lists'!$L$2:$L$25,0), "")
B117: 05971KAC3 | C117: N/A | D117: BANCO SANTANDER S.A.NOTE 3.30600% 06/27/2029 | E117: Corp | F117: 3.306 | G117: 47296 | H117: A2 | I117: A+ | J117: 94.452 | K117: 4.749 | L117: 500(200) | N117: =IF(AND(M117<>"", M117<>0), IF(L117 <> "N/A", IF(M117>=VALUE(LEFT(L117, FIND("(", L117)-1)), J117*10*M117, 1000*M117), 1000*M117), "") | O117: =IF(AND(M117<>"",M117<>0),N117/$N$505, "") | P117: =IF(AND(M117<>"", M117<>0), F117*1000/100, "") | Q117: =IF(AND(M117<>"", M117<>0), NOW(), "") | R117: =IF(AND(M117<>"", M117<>0), ROUND((G117 - Q117)/365, 0), "") | S117: =IF(AND(M117<>"",M117<>0),MDURATION(Q117,G117,F117/100,K117/100,2), "") | T117: =IF(AND(M117<>"",M117<>0),YIELD(Q117,G117,F117/100,N117/(M117*10),100,2),"") | U117: =IF(AND(M117<>"",M117<>0), IF(E117 = "Muni", T117, IF(E117="Corp", T117*(1 -'Investor Input'!$C$4-'Investor Input'!$C$5), T117*(1 -'Investor Input'!$C$4))), T117) | V117: =IF(AND(M117<>"",M117<>0),(FV(K117/(2*100),(G117-Q117)*2/365, F117*1000/(2*100), -N117/M117))*M117, "") | W117: =IF(AND(M117<>"",M117<>0),V117-N117,"") | X117: =IF(AND(M117<>"",M117<>0),W117/N117,"") | Y117: =IF(AND(M117<>"", M117<>0), MONTH(G117), "") | Z117: =IF(AND(M117<>"", M117<>0), MONTH(EDATE(G117, 6)), "") | AA117: =IF(AND(M117<>"", M117<>0), F117*1000*M117/(100*2), "") | AB117: =IF(AND(AA117<>"",AA117<>0), IF(E117="Muni", AA117, IF(E117 = "Corp", (1-'Investor Input'!$C$4-'Investor Input'!$C$5)*AA117, (1-'Investor Input'!$C$4)*AA117)), AA117) | AC117: =IF(AND(M117<>"", M117<>0), H117, "") | AD117: =IF(AND(M117<>"", M117<>0), N117/$N$505*MATCH(AC117,'Misc Lists'!$K$2:$K$25,0), "") | AE117: =IF(AND(M117<>"", M117<>0), I117, "") | AF117: =IF(AND(M117<>"", M117<>0), N117/$N$505*MATCH(AE117,'Misc Lists'!$L$2:$L$25,0), "")
B118: 126117AV2 | C118: N/A | D118: CNA FINL CORP NOTE CALL MAKE WHOLE3.90000% 05/01/2029 | E118: Corp | F118: 3.9 | G118: 47239 | H118: BAA2 | I118: A- | J118: 96.858 | K118: 4.744 | L118: 70(10) | N118: =IF(AND(M118<>"", M118<>0), IF(L118 <> "N/A", IF(M118>=VALUE(LEFT(L118, FIND("(", L118)-1)), J118*10*M118, 1000*M118), 1000*M118), "") | O118: =IF(AND(M118<>"",M118<>0),N118/$N$505, "") | P118: =IF(AND(M118<>"", M118<>0), F118*1000/100, "") | Q118: =IF(AND(M118<>"", M118<>0), NOW(), "") | R118: =IF(AND(M118<>"", M118<>0), ROUND((G118 - Q118)/365, 0), "") | S118: =IF(AND(M118<>"",M118<>0),MDURATION(Q118,G118,F118/100,K118/100,2), "") | T118: =IF(AND(M118<>"",M118<>0),YIELD(Q118,G118,F118/100,N118/(M118*10),100,2),"") | U118: =IF(AND(M118<>"",M118<>0), IF(E118 = "Muni", T118, IF(E118="Corp", T118*(1 -'Investor Input'!$C$4-'Investor Input'!$C$5), T118*(1 -'Investor Input'!$C$4))), T118) | V118: =IF(AND(M118<>"",M118<>0),(FV(K118/(2*100),(G118-Q118)*2/365, F118*1000/(2*100), -N118/M118))*M118, "") | W118: =IF(AND(M118<>"",M118<>0),V118-N118,"") | X118: =IF(AND(M118<>"",M118<>0),W118/N118,"") | Y118: =IF(AND(M118<>"", M118<>0), MONTH(G118), "") | Z118: =IF(AND(M118<>"", M118<>0), MONTH(EDATE(G118, 6)), "") | AA118: =IF(AND(M118<>"", M118<>0), F118*1000*M118/(100*2), "") | AB118: =IF(AND(AA118<>"",AA118<>0), IF(E118="Muni", AA118, IF(E118 = "Corp", (1-'Investor Input'!$C$4-'Investor Input'!$C$5)*AA118, (1-'Investor Input'!$C$4)*AA118)), AA118) | AC118: =IF(AND(M118<>"", M118<>0), H118, "") | AD118: =IF(AND(M118<>"", M118<>0), N118/$N$505*MATCH(AC118,'Misc Lists'!$K$2:$K$25,0), "") | AE118: =IF(AND(M118<>"", M118<>0), I118, "") | AF118: =IF(AND(M118<>"", M118<>0), N118/$N$505*MATCH(AE118,'Misc Lists'!$L$2:$L$25,0), "")
B119: 606822BM5 | C119: N/A | D119: MITSUBISHI UFJ FINANCIAL GROUP NOTE3.19500% 07/18/2029 | E119: Corp | F119: 3.195 | G119: 47317 | H119: A1 | I119: A- | J119: 93.971 | K119: 4.744 | L119: 500(200) | N119: =IF(AND(M119<>"", M119<>0), IF(L119 <> "N/A", IF(M119>=VALUE(LEFT(L119, FIND("(", L119)-1)), J119*10*M119, 1000*M119), 1000*M119), "") | O119: =IF(AND(M119<>"",M119<>0),N119/$N$505, "") | P119: =IF(AND(M119<>"", M119<>0), F119*1000/100, "") | Q119: =IF(AND(M119<>"", M119<>0), NOW(), "") | R119: =IF(AND(M119<>"", M119<>0), ROUND((G119 - Q119)/365, 0), "") | S119: =IF(AND(M119<>"",M119<>0),MDURATION(Q119,G119,F119/100,K119/100,2), "") | T119: =IF(AND(M119<>"",M119<>0),YIELD(Q119,G119,F119/100,N119/(M119*10),100,2),"") | U119: =IF(AND(M119<>"",M119<>0), IF(E119 = "Muni", T119, IF(E119="Corp", T119*(1 -'Investor Input'!$C$4-'Investor Input'!$C$5), T119*(1 -'Investor Input'!$C$4))), T119) | V119: =IF(AND(M119<>"",M119<>0),(FV(K119/(2*100),(G119-Q119)*2/365, F119*1000/(2*100), -N119/M119))*M119, "") | W119: =IF(AND(M119<>"",M119<>0),V119-N119,"") | X119: =IF(AND(M119<>"",M119<>0),W119/N119,"") | Y119: =IF(AND(M119<>"", M119<>0), MONTH(G119), "") | Z119: =IF(AND(M119<>"", M119<>0), MONTH(EDATE(G119, 6)), "") | AA119: =IF(AND(M119<>"", M119<>0), F119*1000*M119/(100*2), "") | AB119: =IF(AND(AA119<>"",AA119<>0), IF(E119="Muni", AA119, IF(E119 = "Corp", (1-'Investor Input'!$C$4-'Investor Input'!$C$5)*AA119, (1-'Investor Input'!$C$4)*AA119)), AA119) | AC119: =IF(AND(M119<>"", M119<>0), H119, "") | AD119: =IF(AND(M119<>"", M119<>0), N119/$N$505*MATCH(AC119,'Misc Lists'!$K$2:$K$25,0), "") | AE119: =IF(AND(M119<>"", M119<>0), I119, "") | AF119: =IF(AND(M119<>"", M119<>0), N119/$N$505*MATCH(AE119,'Misc Lists'!$L$2:$L$25,0), "")
B120: 20030NDA6 | C120: N/A | D120: COMCAST CORP NEW NOTE CALL MAKE WHOLE2.65000% 02/01/2030 | E120: Corp | F120: 2.65 | G120: 47515 | H120: A3 | I120: A- | J120: 90.97 | K120: 4.742 | L120: 500(2) | N120: =IF(AND(M120<>"", M120<>0), IF(L120 <> "N/A", IF(M120>=VALUE(LEFT(L120, FIND("(", L120)-1)), J120*10*M120, 1000*M120), 1000*M120), "") | O120: =IF(AND(M120<>"",M120<>0),N120/$N$505, "") | P120: =IF(AND(M120<>"", M120<>0), F120*1000/100, "") | Q120: =IF(AND(M120<>"", M120<>0), NOW(), "") | R120: =IF(AND(M120<>"", M120<>0), ROUND((G120 - Q120)/365, 0), "") | S120: =IF(AND(M120<>"",M120<>0),MDURATION(Q120,G120,F120/100,K120/100,2), "") | T120: =IF(AND(M120<>"",M120<>0),YIELD(Q120,G120,F120/100,N120/(M120*10),100,2),"") | U120: =IF(AND(M120<>"",M120<>0), IF(E120 = "Muni", T120, IF(E120="Corp", T120*(1 -'Investor Input'!$C$4-'Investor Input'!$C$5), T120*(1 -'Investor Input'!$C$4))), T120) | V120: =IF(AND(M120<>"",M120<>0),(FV(K120/(2*100),(G120-Q120)*2/365, F120*1000/(2*100), -N120/M120))*M120, "") | W120: =IF(AND(M120<>"",M120<>0),V120-N120,"") | X120: =IF(AND(M120<>"",M120<>0),W120/N120,"") | Y120: =IF(AND(M120<>"", M120<>0), MONTH(G120), "") | Z120: =IF(AND(M120<>"", M120<>0), MONTH(EDATE(G120, 6)), "") | AA120: =IF(AND(M120<>"", M120<>0), F120*1000*M120/(100*2), "") | AB120: =IF(AND(AA120<>"",AA120<>0), IF(E120="Muni", AA120, IF(E120 = "Corp", (1-'Investor Input'!$C$4-'Investor Input'!$C$5)*AA120, (1-'Investor Input'!$C$4)*AA120)), AA120) | AC120: =IF(AND(M120<>"", M120<>0), H120, "") | AD120: =IF(AND(M120<>"", M120<>0), N120/$N$505*MATCH(AC120,'Misc Lists'!$K$2:$K$25,0), "") | AE120: =IF(AND(M120<>"", M120<>0), I120, "") | AF120: =IF(AND(M120<>"", M120<>0), N120/$N$505*MATCH(AE120,'Misc Lists'!$L$2:$L$25,0), "")
B121: 571748CA8 | C121: N/A | D121: MARSH &MCLENNAN COS INC NOTE 4.65000% 03/15/2030 CALL MAKE WHOLE | E121: Corp | F121: 4.65 | G121: 47557 | H121: A3 | I121: A- | J121: 99.609 | K121: 4.739 | L121: 30(2) | N121: =IF(AND(M121<>"", M121<>0), IF(L121 <> "N/A", IF(M121>=VALUE(LEFT(L121, FIND("(", L121)-1)), J121*10*M121, 1000*M121), 1000*M121), "") | O121: =IF(AND(M121<>"",M121<>0),N121/$N$505, "") | P121: =IF(AND(M121<>"", M121<>0), F121*1000/100, "") | Q121: =IF(AND(M121<>"", M121<>0), NOW(), "") | R121: =IF(AND(M121<>"", M121<>0), ROUND((G121 - Q121)/365, 0), "") | S121: =IF(AND(M121<>"",M121<>0),MDURATION(Q121,G121,F121/100,K121/100,2), "") | T121: =IF(AND(M121<>"",M121<>0),YIELD(Q121,G121,F121/100,N121/(M121*10),100,2),"") | U121: =IF(AND(M121<>"",M121<>0), IF(E121 = "Muni", T121, IF(E121="Corp", T121*(1 -'Investor Input'!$C$4-'Investor Input'!$C$5), T121*(1 -'Investor Input'!$C$4))), T121) | V121: =IF(AND(M121<>"",M121<>0),(FV(K121/(2*100),(G121-Q121)*2/365, F121*1000/(2*100), -N121/M121))*M121, "") | W121: =IF(AND(M121<>"",M121<>0),V121-N121,"") | X121: =IF(AND(M121<>"",M121<>0),W121/N121,"") | Y121: =IF(AND(M121<>"", M121<>0), MONTH(G121), "") | Z121: =IF(AND(M121<>"", M121<>0), MONTH(EDATE(G121, 6)), "") | AA121: =IF(AND(M121<>"", M121<>0), F121*1000*M121/(100*2), "") | AB121: =IF(AND(AA121<>"",AA121<>0), IF(E121="Muni", AA121, IF(E121 = "Corp", (1-'Investor Input'!$C$4-'Investor Input'!$C$5)*AA121, (1-'Investor Input'!$C$4)*AA121)), AA121) | AC121: =IF(AND(M121<>"", M121<>0), H121, "") | AD121: =IF(AND(M121<>"", M121<>0), N121/$N$505*MATCH(AC121,'Misc Lists'!$K$2:$K$25,0), "") | AE121: =IF(AND(M121<>"", M121<>0), I121, "") | AF121: =IF(AND(M121<>"", M121<>0), N121/$N$505*MATCH(AE121,'Misc Lists'!$L$2:$L$25,0), "")
B122: 036752BB8 | C122: N/A | D122: ELEVANCE HEALTH INC NOTE CALL MAKE WHOLE4.75000% 02/15/2030 | E122: Corp | F122: 4.75 | G122: 47529 | H122: BAA2 | I122: A | J122: 100.05 | K122: 4.738 | L122: 500(1) | N122: =IF(AND(M122<>"", M122<>0), IF(L122 <> "N/A", IF(M122>=VALUE(LEFT(L122, FIND("(", L122)-1)), J122*10*M122, 1000*M122), 1000*M122), "") | O122: =IF(AND(M122<>"",M122<>0),N122/$N$505, "") | P122: =IF(AND(M122<>"", M122<>0), F122*1000/100, "") | Q122: =IF(AND(M122<>"", M122<>0), NOW(), "") | R122: =IF(AND(M122<>"", M122<>0), ROUND((G122 - Q122)/365, 0), "") | S122: =IF(AND(M122<>"",M122<>0),MDURATION(Q122,G122,F122/100,K122/100,2), "") | T122: =IF(AND(M122<>"",M122<>0),YIELD(Q122,G122,F122/100,N122/(M122*10),100,2),"") | U122: =IF(AND(M122<>"",M122<>0), IF(E122 = "Muni", T122, IF(E122="Corp", T122*(1 -'Investor Input'!$C$4-'Investor Input'!$C$5), T122*(1 -'Investor Input'!$C$4))), T122) | V122: =IF(AND(M122<>"",M122<>0),(FV(K122/(2*100),(G122-Q122)*2/365, F122*1000/(2*100), -N122/M122))*M122, "") | W122: =IF(AND(M122<>"",M122<>0),V122-N122,"") | X122: =IF(AND(M122<>"",M122<>0),W122/N122,"") | Y122: =IF(AND(M122<>"", M122<>0), MONTH(G122), "") | Z122: =IF(AND(M122<>"", M122<>0), MONTH(EDATE(G122, 6)), "") | AA122: =IF(AND(M122<>"", M122<>0), F122*1000*M122/(100*2), "") | AB122: =IF(AND(AA122<>"",AA122<>0), IF(E122="Muni", AA122, IF(E122 = "Corp", (1-'Investor Input'!$C$4-'Investor Input'!$C$5)*AA122, (1-'Investor Input'!$C$4)*AA122)), AA122) | AC122: =IF(AND(M122<>"", M122<>0), H122, "") | AD122: =IF(AND(M122<>"", M122<>0), N122/$N$505*MATCH(AC122,'Misc Lists'!$K$2:$K$25,0), "") | AE122: =IF(AND(M122<>"", M122<>0), I122, "") | AF122: =IF(AND(M122<>"", M122<>0), N122/$N$505*MATCH(AE122,'Misc Lists'!$L$2:$L$25,0), "")
... B254: 04621WAF7 | C254: N/A | D254: ASSURED GTY US HLDGSINC NOTE 6.12500% 09/15/2028 CALL MAKE WHOLE | E254: Corp | F254: 6.125 | G254: 47011 | H254: BAA1 | I254: A | J254: 104.821 | K254: 4.621 | L254: 475(2) | N254: =IF(AND(M254<>"", M254<>0), IF(L254 <> "N/A", IF(M254>=VALUE(LEFT(L254, FIND("(", L254)-1)), J254*10*M254, 1000*M254), 1000*M254), "") | O254: =IF(AND(M254<>"",M254<>0),N254/$N$505, "") | P254: =IF(AND(M254<>"", M254<>0), F254*1000/100, "") | Q254: =IF(AND(M254<>"", M254<>0), NOW(), "") | R254: =IF(AND(M254<>"", M254<>0), ROUND((G254 - Q254)/365, 0), "") | S254: =IF(AND(M254<>"",M254<>0),MDURATION(Q254,G254,F254/100,K254/100,2), "") | T254: =IF(AND(M254<>"",M254<>0),YIELD(Q254,G254,F254/100,N254/(M254*10),100,2),"") | U254: =IF(AND(M254<>"",M254<>0), IF(E254 = "Muni", T254, IF(E254="Corp", T254*(1 -'Investor Input'!$C$4-'Investor Input'!$C$5), T254*(1 -'Investor Input'!$C$4))), T254) | V254: =IF(AND(M254<>"",M254<>0),(FV(K254/(2*100),(G254-Q254)*2/365, F254*1000/(2*100), -N254/M254))*M254, "") | W254: =IF(AND(M254<>"",M254<>0),V254-N254,"") | X254: =IF(AND(M254<>"",M254<>0),W254/N254,"") | Y254: =IF(AND(M254<>"", M254<>0), MONTH(G254), "") | Z254: =IF(AND(M254<>"", M254<>0), MONTH(EDATE(G254, 6)), "") | AA254: =IF(AND(M254<>"", M254<>0), F254*1000*M254/(100*2), "") | AB254: =IF(AND(AA254<>"",AA254<>0), IF(E254="Muni", AA254, IF(E254 = "Corp", (1-'Investor Input'!$C$4-'Investor Input'!$C$5)*AA254, (1-'Investor Input'!$C$4)*AA254)), AA254) | AC254: =IF(AND(M254<>"", M254<>0), H254, "") | AD254: =IF(AND(M254<>"", M254<>0), N254/$N$505*MATCH(AC254,'Misc Lists'!$K$2:$K$25,0), "") | AE254: =IF(AND(M254<>"", M254<>0), I254, "") | AF254: =IF(AND(M254<>"", M254<>0), N254/$N$505*MATCH(AE254,'Misc Lists'!$L$2:$L$25,0), "")
B255: 032095AP6 | C255: N/A | D255: AMPHENOL CORP NOTE CALL MAKE WHOLE5.05000% 04/05/2029 | E255: Corp | F255: 5.05 | G255: 47213 | H255: A3 | I255: A- | J255: 101.571 | K255: 4.621 | L255: 500(2) | M255: 2 | N255: =IF(AND(M255<>"", M255<>0), IF(L255 <> "N/A", IF(M255>=VALUE(LEFT(L255, FIND("(", L255)-1)), J255*10*M255, 1000*M255), 1000*M255), "") -> 2000 | O255: =IF(AND(M255<>"",M255<>0),N255/$N$505, "") -> 0.0019999179 | P255: =IF(AND(M255<>"", M255<>0), F255*1000/100, "") -> 50.5 | Q255: =IF(AND(M255<>"", M255<>0), NOW(), "") -> 45791.491 | R255: =IF(AND(M255<>"", M255<>0), ROUND((G255 - Q255)/365, 0), "") -> 4 | S255: =IF(AND(M255<>"",M255<>0),MDURATION(Q255,G255,F255/100,K255/100,2), "") -> 3.4858267 | T255: =IF(AND(M255<>"",M255<>0),YIELD(Q255,G255,F255/100,N255/(M255*10),100,2),"") -> 0.050484746 | U255: =IF(AND(M255<>"",M255<>0), IF(E255 = "Muni", T255, IF(E255="Corp", T255*(1 -'Investor Input'!$C$4-'Investor Input'!$C$5), T255*(1 -'Investor Input'!$C$4))), T255) -> 0.027261763 | V255: =IF(AND(M255<>"",M255<>0),(FV(K255/(2*100),(G255-Q255)*2/365, F255*1000/(2*100), -N255/M255))*M255, "") -> 1963.8439 | W255: =IF(AND(M255<>"",M255<>0),V255-N255,"") -> -36.156113 | X255: =IF(AND(M255<>"",M255<>0),W255/N255,"") -> -0.018078057 | Y255: =IF(AND(M255<>"", M255<>0), MONTH(G255), "") -> 4 | Z255: =IF(AND(M255<>"", M255<>0), MONTH(EDATE(G255, 6)), "") -> 10 | AA255: =IF(AND(M255<>"", M255<>0), F255*1000*M255/(100*2), "") -> 50.5 | AB255: =IF(AND(AA255<>"",AA255<>0), IF(E255="Muni", AA255, IF(E255 = "Corp", (1-'Investor Input'!$C$4-'Investor Input'!$C$5)*AA255, (1-'Investor Input'!$C$4)*AA255)), AA255) -> 27.27 | AC255: =IF(AND(M255<>"", M255<>0), H255, "") -> A3 | AD255: =IF(AND(M255<>"", M255<>0), N255/$N$505*MATCH(AC255,'Misc Lists'!$K$2:$K$25,0), "") -> 0.015999343 | AE255: =IF(AND(M255<>"", M255<>0), I255, "") -> A- | AF255: =IF(AND(M255<>"", M255<>0), N255/$N$505*MATCH(AE255,'Misc Lists'!$L$2:$L$25,0), "") -> 0.015999343
B256: 10373QBX7 | C256: N/A | D256: BP CAP MKTS AMER INCNOTE CALL MAKE WHOLE4.69900% 04/10/2029 | E256: Corp | F256: 4.699 | G256: 47218 | H256: A1 | I256: A- | J256: 100.285 | K256: 4.621 | L256: 500(1) | N256: =IF(AND(M256<>"", M256<>0), IF(L256 <> "N/A", IF(M256>=VALUE(LEFT(L256, FIND("(", L256)-1)), J256*10*M256, 1000*M256), 1000*M256), "") | O256: =IF(AND(M256<>"",M256<>0),N256/$N$505, "") | P256: =IF(AND(M256<>"", M256<>0), F256*1000/100, "") | Q256: =IF(AND(M256<>"", M256<>0), NOW(), "") | R256: =IF(AND(M256<>"", M256<>0), ROUND((G256 - Q256)/365, 0), "") | S256: =IF(AND(M256<>"",M256<>0),MDURATION(Q256,G256,F256/100,K256/100,2), "") | T256: =IF(AND(M256<>"",M256<>0),YIELD(Q256,G256,F256/100,N256/(M256*10),100,2),"") | U256: =IF(AND(M256<>"",M256<>0), IF(E256 = "Muni", T256, IF(E256="Corp", T256*(1 -'Investor Input'!$C$4-'Investor Input'!$C$5), T256*(1 -'Investor Input'!$C$4))), T256) | V256: =IF(AND(M256<>"",M256<>0),(FV(K256/(2*100),(G256-Q256)*2/365, F256*1000/(2*100), -N256/M256))*M256, "") | W256: =IF(AND(M256<>"",M256<>0),V256-N256,"") | X256: =IF(AND(M256<>"",M256<>0),W256/N256,"") | Y256: =IF(AND(M256<>"", M256<>0), MONTH(G256), "") | Z256: =IF(AND(M256<>"", M256<>0), MONTH(EDATE(G256, 6)), "") | AA256: =IF(AND(M256<>"", M256<>0), F256*1000*M256/(100*2), "") | AB256: =IF(AND(AA256<>"",AA256<>0), IF(E256="Muni", AA256, IF(E256 = "Corp", (1-'Investor Input'!$C$4-'Investor Input'!$C$5)*AA256, (1-'Investor Input'!$C$4)*AA256)), AA256) | AC256: =IF(AND(M256<>"", M256<>0), H256, "") | AD256: =IF(AND(M256<>"", M256<>0), N256/$N$505*MATCH(AC256,'Misc Lists'!$K$2:$K$25,0), "") | AE256: =IF(AND(M256<>"", M256<>0), I256, "") | AF256: =IF(AND(M256<>"", M256<>0), N256/$N$505*MATCH(AE256,'Misc Lists'!$L$2:$L$25,0), "")
B257: 23291KAH8 | C257: N/A | D257: DH EUROPE FIN II S AR L NOTE 2.60000% 11/15/2029 CALL MAKE WHOLE | E257: Corp | F257: 2.6 | G257: 47437 | H257: A3 | I257: A- | J257: 91.586 | K257: 4.621 | L257: 500(2) | N257: =IF(AND(M257<>"", M257<>0), IF(L257 <> "N/A", IF(M257>=VALUE(LEFT(L257, FIND("(", L257)-1)), J257*10*M257, 1000*M257), 1000*M257), "") | O257: =IF(AND(M257<>"",M257<>0),N257/$N$505, "") | P257: =IF(AND(M257<>"", M257<>0), F257*1000/100, "") | Q257: =IF(AND(M257<>"", M257<>0), NOW(), "") | R257: =IF(AND(M257<>"", M257<>0), ROUND((G257 - Q257)/365, 0), "") | S257: =IF(AND(M257<>"",M257<>0),MDURATION(Q257,G257,F257/100,K257/100,2), "") | T257: =IF(AND(M257<>"",M257<>0),YIELD(Q257,G257,F257/100,N257/(M257*10),100,2),"") | U257: =IF(AND(M257<>"",M257<>0), IF(E257 = "Muni", T257, IF(E257="Corp", T257*(1 -'Investor Input'!$C$4-'Investor Input'!$C$5), T257*(1 -'Investor Input'!$C$4))), T257) | V257: =IF(AND(M257<>"",M257<>0),(FV(K257/(2*100),(G257-Q257)*2/365, F257*1000/(2*100), -N257/M257))*M257, "") | W257: =IF(AND(M257<>"",M257<>0),V257-N257,"") | X257: =IF(AND(M257<>"",M257<>0),W257/N257,"") | Y257: =IF(AND(M257<>"", M257<>0), MONTH(G257), "") | Z257: =IF(AND(M257<>"", M257<>0), MONTH(EDATE(G257, 6)), "") | AA257: =IF(AND(M257<>"", M257<>0), F257*1000*M257/(100*2), "") | AB257: =IF(AND(AA257<>"",AA257<>0), IF(E257="Muni", AA257, IF(E257 = "Corp", (1-'Investor Input'!$C$4-'Investor Input'!$C$5)*AA257, (1-'Investor Input'!$C$4)*AA257)), AA257) | AC257: =IF(AND(M257<>"", M257<>0), H257, "") | AD257: =IF(AND(M257<>"", M257<>0), N257/$N$505*MATCH(AC257,'Misc Lists'!$K$2:$K$25,0), "") | AE257: =IF(AND(M257<>"", M257<>0), I257, "") | AF257: =IF(AND(M257<>"", M257<>0), N257/$N$505*MATCH(AE257,'Misc Lists'!$L$2:$L$25,0), "")
B258: 63743HFN7 | C258: N/A | D258: NATIONAL RURAL UTILSCOOP FIN SER D MTN 4.85000% 02/07/2029 CALL MAKE WHOLE | E258: Corp | F258: 4.85 | G258: 47156 | H258: A2 | I258: A- | J258: 100.807 | K258: 4.62 | L258: 150(10) | N258: =IF(AND(M258<>"", M258<>0), IF(L258 <> "N/A", IF(M258>=VALUE(LEFT(L258, FIND("(", L258)-1)), J258*10*M258, 1000*M258), 1000*M258), "") | O258: =IF(AND(M258<>"",M258<>0),N258/$N$505, "") | P258: =IF(AND(M258<>"", M258<>0), F258*1000/100, "") | Q258: =IF(AND(M258<>"", M258<>0), NOW(), "") | R258: =IF(AND(M258<>"", M258<>0), ROUND((G258 - Q258)/365, 0), "") | S258: =IF(AND(M258<>"",M258<>0),MDURATION(Q258,G258,F258/100,K258/100,2), "") | T258: =IF(AND(M258<>"",M258<>0),YIELD(Q258,G258,F258/100,N258/(M258*10),100,2),"") | U258: =IF(AND(M258<>"",M258<>0), IF(E258 = "Muni", T258, IF(E258="Corp", T258*(1 -'Investor Input'!$C$4-'Investor Input'!$C$5), T258*(1 -'Investor Input'!$C$4))), T258) | V258: =IF(AND(M258<>"",M258<>0),(FV(K258/(2*100),(G258-Q258)*2/365, F258*1000/(2*100), -N258/M258))*M258, "") | W258: =IF(AND(M258<>"",M258<>0),V258-N258,"") | X258: =IF(AND(M258<>"",M258<>0),W258/N258,"") | Y258: =IF(AND(M258<>"", M258<>0), MONTH(G258), "") | Z258: =IF(AND(M258<>"", M258<>0), MONTH(EDATE(G258, 6)), "") | AA258: =IF(AND(M258<>"", M258<>0), F258*1000*M258/(100*2), "") | AB258: =IF(AND(AA258<>"",AA258<>0), IF(E258="Muni", AA258, IF(E258 = "Corp", (1-'Investor Input'!$C$4-'Investor Input'!$C$5)*AA258, (1-'Investor Input'!$C$4)*AA258)), AA258) | AC258: =IF(AND(M258<>"", M258<>0), H258, "") | AD258: =IF(AND(M258<>"", M258<>0), N258/$N$505*MATCH(AC258,'Misc Lists'!$K$2:$K$25,0), "") | AE258: =IF(AND(M258<>"", M258<>0), I258, "") | AF258: =IF(AND(M258<>"", M258<>0), N258/$N$505*MATCH(AE258,'Misc Lists'!$L$2:$L$25,0), "")
B259: 75884RAV5 | C259: N/A | D259: REGENCY CTRS L P NOTE CALL MAKE WHOLE3.60000% 02/01/2027 | E259: Corp | F259: 3.6 | G259: 46419 | H259: A3 | I259: A- | J259: 98.178 | K259: 4.618 | L259: 200(2) | N259: =IF(AND(M259<>"", M259<>0), IF(L259 <> "N/A", IF(M259>=VALUE(LEFT(L259, FIND("(", L259)-1)), J259*10*M259, 1000*M259), 1000*M259), "") | O259: =IF(AND(M259<>"",M259<>0),N259/$N$505, "") | P259: =IF(AND(M259<>"", M259<>0), F259*1000/100, "") | Q259: =IF(AND(M259<>"", M259<>0), NOW(), "") | R259: =IF(AND(M259<>"", M259<>0), ROUND((G259 - Q259)/365, 0), "") | S259: =IF(AND(M259<>"",M259<>0),MDURATION(Q259,G259,F259/100,K259/100,2), "") | T259: =IF(AND(M259<>"",M259<>0),YIELD(Q259,G259,F259/100,N259/(M259*10),100,2),"") | U259: =IF(AND(M259<>"",M259<>0), IF(E259 = "Muni", T259, IF(E259="Corp", T259*(1 -'Investor Input'!$C$4-'Investor Input'!$C$5), T259*(1 -'Investor Input'!$C$4))), T259) | V259: =IF(AND(M259<>"",M259<>0),(FV(K259/(2*100),(G259-Q259)*2/365, F259*1000/(2*100), -N259/M259))*M259, "") | W259: =IF(AND(M259<>"",M259<>0),V259-N259,"") | X259: =IF(AND(M259<>"",M259<>0),W259/N259,"") | Y259: =IF(AND(M259<>"", M259<>0), MONTH(G259), "") | Z259: =IF(AND(M259<>"", M259<>0), MONTH(EDATE(G259, 6)), "") | AA259: =IF(AND(M259<>"", M259<>0), F259*1000*M259/(100*2), "") | AB259: =IF(AND(AA259<>"",AA259<>0), IF(E259="Muni", AA259, IF(E259 = "Corp", (1-'Investor Input'!$C$4-'Investor Input'!$C$5)*AA259, (1-'Investor Input'!$C$4)*AA259)), AA259) | AC259: =IF(AND(M259<>"", M259<>0), H259, "") | AD259: =IF(AND(M259<>"", M259<>0), N259/$N$505*MATCH(AC259,'Misc Lists'!$K$2:$K$25,0), "") | AE259: =IF(AND(M259<>"", M259<>0), I259, "") | AF259: =IF(AND(M259<>"", M259<>0), N259/$N$505*MATCH(AE259,'Misc Lists'!$L$2:$L$25,0), "")
B260: 743315AW3 | C260: N/A | D260: PROGRESSIVE CORP NOTE CALL MAKE WHOLE3.20000% 03/26/2030 | E260: Corp | F260: 3.2 | G260: 47568 | H260: A2 | I260: A | J260: 93.693 | K260: 4.617 | L260: 28(2) | M260: 15 | N260: =IF(AND(M260<>"", M260<>0), IF(L260 <> "N/A", IF(M260>=VALUE(LEFT(L260, FIND("(", L260)-1)), J260*10*M260, 1000*M260), 1000*M260), "") -> 15000 | O260: =IF(AND(M260<>"",M260<>0),N260/$N$505, "") -> 0.014999384 | P260: =IF(AND(M260<>"", M260<>0), F260*1000/100, "") -> 32 | Q260: =IF(AND(M260<>"", M260<>0), NOW(), "") -> 45791.491 | R260: =IF(AND(M260<>"", M260<>0), ROUND((G260 - Q260)/365, 0), "") -> 5 | S260: =IF(AND(M260<>"",M260<>0),MDURATION(Q260,G260,F260/100,K260/100,2), "") -> 4.4111679 | T260: =IF(AND(M260<>"",M260<>0),YIELD(Q260,G260,F260/100,N260/(M260*10),100,2),"") -> 0.031994457 | U260: =IF(AND(M260<>"",M260<>0), IF(E260 = "Muni", T260, IF(E260="Corp", T260*(1 -'Investor Input'!$C$4-'Investor Input'!$C$5), T260*(1 -'Investor Input'!$C$4))), T260) -> 0.017277007 | V260: =IF(AND(M260<>"",M260<>0),(FV(K260/(2*100),(G260-Q260)*2/365, F260*1000/(2*100), -N260/M260))*M260, "") -> 16145.262 | W260: =IF(AND(M260<>"",M260<>0),V260-N260,"") -> 1145.2619 | X260: =IF(AND(M260<>"",M260<>0),W260/N260,"") -> 0.076350795 | Y260: =IF(AND(M260<>"", M260<>0), MONTH(G260), "") -> 3 | Z260: =IF(AND(M260<>"", M260<>0), MONTH(EDATE(G260, 6)), "") -> 9 | AA260: =IF(AND(M260<>"", M260<>0), F260*1000*M260/(100*2), "") -> 240 | AB260: =IF(AND(AA260<>"",AA260<>0), IF(E260="Muni", AA260, IF(E260 = "Corp", (1-'Investor Input'!$C$4-'Investor Input'!$C$5)*AA260, (1-'Investor Input'!$C$4)*AA260)), AA260) -> 129.6 | AC260: =IF(AND(M260<>"", M260<>0), H260, "") -> A2 | AD260: =IF(AND(M260<>"", M260<>0), N260/$N$505*MATCH(AC260,'Misc Lists'!$K$2:$K$25,0), "") -> 0.10499569 | AE260: =IF(AND(M260<>"", M260<>0), I260, "") -> A | AF260: =IF(AND(M260<>"", M260<>0), N260/$N$505*MATCH(AE260,'Misc Lists'!$L$2:$L$25,0), "") -> 0.10499569
B261: 86562MDG2 | C261: N/A | D261: SUMITOMO MITSUI FIN GRP INC NOTE 5.71600% 09/14/2028 | E261: Corp | F261: 5.716 | G261: 47010 | H261: A1 | I261: A- | J261: 103.524 | K261: 4.616 | L261: 500(200) | N261: =IF(AND(M261<>"", M261<>0), IF(L261 <> "N/A", IF(M261>=VALUE(LEFT(L261, FIND("(", L261)-1)), J261*10*M261, 1000*M261), 1000*M261), "") | O261: =IF(AND(M261<>"",M261<>0),N261/$N$505, "") | P261: =IF(AND(M261<>"", M261<>0), F261*1000/100, "") | Q261: =IF(AND(M261<>"", M261<>0), NOW(), "") | R261: =IF(AND(M261<>"", M261<>0), ROUND((G261 - Q261)/365, 0), "") | S261: =IF(AND(M261<>"",M261<>0),MDURATION(Q261,G261,F261/100,K261/100,2), "") | T261: =IF(AND(M261<>"",M261<>0),YIELD(Q261,G261,F261/100,N261/(M261*10),100,2),"") | U261: =IF(AND(M261<>"",M261<>0), IF(E261 = "Muni", T261, IF(E261="Corp", T261*(1 -'Investor Input'!$C$4-'Investor Input'!$C$5), T261*(1 -'Investor Input'!$C$4))), T261) | V261: =IF(AND(M261<>"",M261<>0),(FV(K261/(2*100),(G261-Q261)*2/365, F261*1000/(2*100), -N261/M261))*M261, "") | W261: =IF(AND(M261<>"",M261<>0),V261-N261,"") | X261: =IF(AND(M261<>"",M261<>0),W261/N261,"") | Y261: =IF(AND(M261<>"", M261<>0), MONTH(G261), "") | Z261: =IF(AND(M261<>"", M261<>0), MONTH(EDATE(G261, 6)), "") | AA261: =IF(AND(M261<>"", M261<>0), F261*1000*M261/(100*2), "") | AB261: =IF(AND(AA261<>"",AA261<>0), IF(E261="Muni", AA261, IF(E261 = "Corp", (1-'Investor Input'!$C$4-'Investor Input'!$C$5)*AA261, (1-'Investor Input'!$C$4)*AA261)), AA261) | AC261: =IF(AND(M261<>"", M261<>0), H261, "") | AD261: =IF(AND(M261<>"", M261<>0), N261/$N$505*MATCH(AC261,'Misc Lists'!$K$2:$K$25,0), "") | AE261: =IF(AND(M261<>"", M261<>0), I261, "") | AF261: =IF(AND(M261<>"", M261<>0), N261/$N$505*MATCH(AE261,'Misc Lists'!$L$2:$L$25,0), "")
...

Sheet Secure Bonds Scenario
A1: {=MID(CELL("filename",A1),FIND("]",CELL("filename",A1))+1,255)} -> Secure Bonds Scenario
B2: General Bond Information | M2: Purchase Information | V2: Valuation on Maturity | Y2: Yearly Cash Flow Information | AC2: Rating Info
B3: CUSIP | C3: State | D3: Description | E3: Type | F3: Cpn | G3: Maturity Date | H3: Mdy | I3: S&P | J3: Price | K3: YTM | L3: Qty (Min) | M3: Purchase Qty | N3: Total Price | O3: Portfolio Pct | P3: Annual Coupon | Q3: Purchase Date | R3: Yrs to Maturity | S3: Duration Yrs | T3: YTM At Buy | U3: After-Tax YTM | V3: Price | W3: Interest Earned | X3: Total Return | Y3: 1st Coupon Mth | Z3: 2nd Coupon Month | AA3: Coupon Amt | AB3: After-Tax Coupon Amt | AC3: Mdy Rating | AD3: Mdy Score | AE3: S&P Rating | AF3: S&P Score
B4: {=_xlfn.TAKE(_xlfn._xlws.SORT(_xlfn._xlws.FILTER(_xlfn._xlws.FILTER(Master_Bond_List[], ('Investor Input'!C6 >= IFERROR(VALUE(MID(Master_Bond_List[Quantity Ask(min)], FIND("(", Master_Bond_List[Quantity Ask(min)]) + 1, LEN(Master_Bond_List[Quantity Ask(min)]) - FIND("(", Master_Bond_List[Quantity Ask(min)])-1)), 1)*1000)*((Master_Bond_List[Maturity Date]-TODAY()) < 'Investor Input'!C7*365)*(Master_Bond_List[Type] = "Muni")*(Master_Bond_List[State]='Investor Input'!D3)*((Master_Bond_List[Moody''s Rating] = "AAA") + (Master_Bond_List[Moody''s Rating] = "AA1") + (Master_Bond_List[Moody''s Rating] = "AA2") + (Master_Bond_List[Moody''s Rating] = "AA3")) + ('Investor Input'!C6 >= IFERROR(VALUE(MID(Master_Bond_List[Quantity Ask(min)], FIND("(", Master_Bond_List[Quantity Ask(min)]) + 1, LEN(Master_Bond_List[Quantity Ask(min)]) - FIND("(", Master_Bond_List[Quantity Ask(min)])-1)), 1)*1000)*((Master_Bond_List[Maturity Date]-TODAY()) < 'Investor Input'!C7*365)*(Master_Bond_List[Type] = "Tres") + ('Investor Input'!C6 >= IFERROR(VALUE(MID(Master_Bond_List[Quantity Ask(min)], FIND("(", Master_Bond_List[Quantity Ask(min)]) + 1, LEN(Master_Bond_List[Quantity Ask(min)]) - FIND("(", Master_Bond_List[Quantity Ask(min)])-1)), 1)*1000)*((Master_Bond_List[Maturity Date]-TODAY()) < 'Investor Input'!C7*365)*(Master_Bond_List[Type] = "TIPS")*((Master_Bond_List[Moody''s Rating] = "AAA") + (Master_Bond_List[Moody''s Rating] = "AA1") + (Master_Bond_List[Moody''s Rating] = "AA2") + (Master_Bond_List[Moody''s Rating] = "AA3")) + ('Investor Input'!C6 >= IFERROR(VALUE(MID(Master_Bond_List[Quantity Ask(min)], FIND("(", Master_Bond_List[Quantity Ask(min)]) + 1, LEN(Master_Bond_List[Quantity Ask(min)]) - FIND("(", Master_Bond_List[Quantity Ask(min)])-1)), 1)*1000)*((Master_Bond_List[Maturity Date]-TODAY()) < 'Investor Input'!C7*365)*(Master_Bond_List[Type] = "Corp")*((Master_Bond_List[Moody''s Rating] = "AAA") + (Master_Bond_List[Moody''s Rating] = "AA1") + (Master_Bond_List[Moody''s Rating] = "AA2") + (Master_Bond_List[Moody''s Rating] = "AA3"))), {1,1,1,1,1,1,0,1,1,0,1,0,0,1,0,0,1,0}), {4,10}, {-1,-1}), 500)} -> 91282CGZ8 | C4: N/A | D4: UNITED STATES TREAS SER K-2030 3.50000% 04/30/2030 NTS NOTE | E4: Tres | F4: 3.5 | G4: 47603 | H4: AAA | I4: -- | J4: 96.087 | K4: 4.348 | L4: 4,937(1) | N4: =IF(AND(M4<>"", M4<>0), IF(L4 <> "N/A", IF(M4>=VALUE(LEFT(L4, FIND("(", L4)-1)), J4*10*M4, 1000*M4), 1000*M4), "") | O4: =IF(AND(M4<>"",M4<>0),N4/$N$505, "") | P4: =IF(AND(M4<>"", M4<>0), F4*1000/100, "") | Q4: =IF(AND(M4<>"", M4<>0), NOW(), "") | R4: =IF(AND(M4<>"", M4<>0), ROUND((G4 - Q4)/365, 0), "") | S4: =IF(AND(M4<>"",M4<>0),MDURATION(Q4,G4,F4/100,K4/100,2), "") | T4: =IF(AND(M4<>"",M4<>0),YIELD(Q4,G4,F4/100,N4/(M4*10),100,2),"") | U4: =IF(AND(M4<>"",M4<>0), IF(E4 = "Muni", T4, IF(E4="Corp", T4*(1 -'Investor Input'!$C$4-'Investor Input'!$C$5), T4*(1 -'Investor Input'!$C$4))), T4) | V4: =IF(AND(M4<>"",M4<>0),(FV(K4/(2*100),(G4-Q4)*2/365, F4*1000/(2*100), -N4/M4))*M4, "") | W4: =IF(AND(M4<>"",M4<>0),V4-N4,"") | X4: =IF(AND(M4<>"",M4<>0),W4/N4,"") | Y4: =IF(AND(M4<>"", M4<>0), MONTH(G4), "") | Z4: =IF(AND(M4<>"", M4<>0), MONTH(EDATE(G4, 6)), "") | AA4: =IF(AND(M4<>"", M4<>0), F4*1000*M4/(100*2), "") | AB4: =IF(AND(AA4<>"",AA4<>0), IF(E4="Muni", AA4, IF(E4 = "Corp", (1-'Investor Input'!$C$4-'Investor Input'!$C$5)*AA4, (1-'Investor Input'!$C$4)*AA4)), AA4) | AC4: =IF(AND(M4<>"", M4<>0), H4, "") | AD4: =IF(AND(M4<>"", M4<>0), N4/$N$505*MATCH(AC4,'Misc Lists'!$K$2:$K$25,0), "") | AE4: =IF(AND(M4<>"", M4<>0), I4, "") | AF4: =IF(AND(M4<>"", M4<>0), N4/$N$505*MATCH(AE4,'Misc Lists'!$L$2:$L$25,0), "")
B5: 91282CGS4 | C5: N/A | D5: UNITED STATES TREAS SER J-2030 3.62500% 03/31/2030 NTS NOTE | E5: Tres | F5: 3.625 | G5: 47573 | H5: AAA | I5: -- | J5: 96.727 | K5: 4.345 | L5: 65,000(400) | N5: =IF(AND(M5<>"", M5<>0), IF(L5 <> "N/A", IF(M5>=VALUE(LEFT(L5, FIND("(", L5)-1)), J5*10*M5, 1000*M5), 1000*M5), "") | O5: =IF(AND(M5<>"",M5<>0),N5/$N$505, "") | P5: =IF(AND(M5<>"", M5<>0), F5*1000/100, "") | Q5: =IF(AND(M5<>"", M5<>0), NOW(), "") | R5: =IF(AND(M5<>"", M5<>0), ROUND((G5 - Q5)/365, 0), "") | S5: =IF(AND(M5<>"",M5<>0),MDURATION(Q5,G5,F5/100,K5/100,2), "") | T5: =IF(AND(M5<>"",M5<>0),YIELD(Q5,G5,F5/100,N5/(M5*10),100,2),"") | U5: =IF(AND(M5<>"",M5<>0), IF(E5 = "Muni", T5, IF(E5="Corp", T5*(1 -'Investor Input'!$C$4-'Investor Input'!$C$5), T5*(1 -'Investor Input'!$C$4))), T5) | V5: =IF(AND(M5<>"",M5<>0),(FV(K5/(2*100),(G5-Q5)*2/365, F5*1000/(2*100), -N5/M5))*M5, "") | W5: =IF(AND(M5<>"",M5<>0),V5-N5,"") | X5: =IF(AND(M5<>"",M5<>0),W5/N5,"") | Y5: =IF(AND(M5<>"", M5<>0), MONTH(G5), "") | Z5: =IF(AND(M5<>"", M5<>0), MONTH(EDATE(G5, 6)), "") | AA5: =IF(AND(M5<>"", M5<>0), F5*1000*M5/(100*2), "") | AB5: =IF(AND(AA5<>"",AA5<>0), IF(E5="Muni", AA5, IF(E5 = "Corp", (1-'Investor Input'!$C$4-'Investor Input'!$C$5)*AA5, (1-'Investor Input'!$C$4)*AA5)), AA5) | AC5: =IF(AND(M5<>"", M5<>0), H5, "") | AD5: =IF(AND(M5<>"", M5<>0), N5/$N$505*MATCH(AC5,'Misc Lists'!$K$2:$K$25,0), "") | AE5: =IF(AND(M5<>"", M5<>0), I5, "") | AF5: =IF(AND(M5<>"", M5<>0), N5/$N$505*MATCH(AE5,'Misc Lists'!$L$2:$L$25,0), "")
B6: 91282CGJ4 | C6: N/A | D6: UNITED STATES TREAS SER G-2030 3.50000% 01/31/2030 NTS NOTE | E6: Tres | F6: 3.5 | G6: 47514 | H6: AAA | I6: -- | J6: 96.282 | K6: 4.342 | L6: 65,000(400) | N6: =IF(AND(M6<>"", M6<>0), IF(L6 <> "N/A", IF(M6>=VALUE(LEFT(L6, FIND("(", L6)-1)), J6*10*M6, 1000*M6), 1000*M6), "") | O6: =IF(AND(M6<>"",M6<>0),N6/$N$505, "") | P6: =IF(AND(M6<>"", M6<>0), F6*1000/100, "") | Q6: =IF(AND(M6<>"", M6<>0), NOW(), "") | R6: =IF(AND(M6<>"", M6<>0), ROUND((G6 - Q6)/365, 0), "") | S6: =IF(AND(M6<>"",M6<>0),MDURATION(Q6,G6,F6/100,K6/100,2), "") | T6: =IF(AND(M6<>"",M6<>0),YIELD(Q6,G6,F6/100,N6/(M6*10),100,2),"") | U6: =IF(AND(M6<>"",M6<>0), IF(E6 = "Muni", T6, IF(E6="Corp", T6*(1 -'Investor Input'!$C$4-'Investor Input'!$C$5), T6*(1 -'Investor Input'!$C$4))), T6) | V6: =IF(AND(M6<>"",M6<>0),(FV(K6/(2*100),(G6-Q6)*2/365, F6*1000/(2*100), -N6/M6))*M6, "") | W6: =IF(AND(M6<>"",M6<>0),V6-N6,"") | X6: =IF(AND(M6<>"",M6<>0),W6/N6,"") | Y6: =IF(AND(M6<>"", M6<>0), MONTH(G6), "") | Z6: =IF(AND(M6<>"", M6<>0), MONTH(EDATE(G6, 6)), "") | AA6: =IF(AND(M6<>"", M6<>0), F6*1000*M6/(100*2), "") | AB6: =IF(AND(AA6<>"",AA6<>0), IF(E6="Muni", AA6, IF(E6 = "Corp", (1-'Investor Input'!$C$4-'Investor Input'!$C$5)*AA6, (1-'Investor Input'!$C$4)*AA6)), AA6) | AC6: =IF(AND(M6<>"", M6<>0), H6, "") | AD6: =IF(AND(M6<>"", M6<>0), N6/$N$505*MATCH(AC6,'Misc Lists'!$K$2:$K$25,0), "") | AE6: =IF(AND(M6<>"", M6<>0), I6, "") | AF6: =IF(AND(M6<>"", M6<>0), N6/$N$505*MATCH(AE6,'Misc Lists'!$L$2:$L$25,0), "")
B7: 91282CAJ0 | C7: N/A | D7: UNITED STATES TREAS SER AC-2025 0.25000% 08/31/2025 NTS NOTE | E7: Tres | F7: 0.25 | G7: 45900 | H7: AAA | I7: -- | J7: 97.889 | K7: 4.34 | L7: 8,000(200) | N7: =IF(AND(M7<>"", M7<>0), IF(L7 <> "N/A", IF(M7>=VALUE(LEFT(L7, FIND("(", L7)-1)), J7*10*M7, 1000*M7), 1000*M7), "") | O7: =IF(AND(M7<>"",M7<>0),N7/$N$505, "") | P7: =IF(AND(M7<>"", M7<>0), F7*1000/100, "") | Q7: =IF(AND(M7<>"", M7<>0), NOW(), "") | R7: =IF(AND(M7<>"", M7<>0), ROUND((G7 - Q7)/365, 0), "") | S7: =IF(AND(M7<>"",M7<>0),MDURATION(Q7,G7,F7/100,K7/100,2), "") | T7: =IF(AND(M7<>"",M7<>0),YIELD(Q7,G7,F7/100,N7/(M7*10),100,2),"") | U7: =IF(AND(M7<>"",M7<>0), IF(E7 = "Muni", T7, IF(E7="Corp", T7*(1 -'Investor Input'!$C$4-'Investor Input'!$C$5), T7*(1 -'Investor Input'!$C$4))), T7) | V7: =IF(AND(M7<>"",M7<>0),(FV(K7/(2*100),(G7-Q7)*2/365, F7*1000/(2*100), -N7/M7))*M7, "") | W7: =IF(AND(M7<>"",M7<>0),V7-N7,"") | X7: =IF(AND(M7<>"",M7<>0),W7/N7,"") | Y7: =IF(AND(M7<>"", M7<>0), MONTH(G7), "") | Z7: =IF(AND(M7<>"", M7<>0), MONTH(EDATE(G7, 6)), "") | AA7: =IF(AND(M7<>"", M7<>0), F7*1000*M7/(100*2), "") | AB7: =IF(AND(AA7<>"",AA7<>0), IF(E7="Muni", AA7, IF(E7 = "Corp", (1-'Investor Input'!$C$4-'Investor Input'!$C$5)*AA7, (1-'Investor Input'!$C$4)*AA7)), AA7) | AC7: =IF(AND(M7<>"", M7<>0), H7, "") | AD7: =IF(AND(M7<>"", M7<>0), N7/$N$505*MATCH(AC7,'Misc Lists'!$K$2:$K$25,0), "") | AE7: =IF(AND(M7<>"", M7<>0), I7, "") | AF7: =IF(AND(M7<>"", M7<>0), N7/$N$505*MATCH(AE7,'Misc Lists'!$L$2:$L$25,0), "")
B8: 91282CGB1 | C8: N/A | D8: UNITED STATES TREAS SER T-2029 3.87500% 12/31/2029 NTS NOTE | E8: Tres | F8: 3.875 | G8: 47483 | H8: AAA | I8: -- | J8: 97.973 | K8: 4.34 | L8: 10,000(275) | N8: =IF(AND(M8<>"", M8<>0), IF(L8 <> "N/A", IF(M8>=VALUE(LEFT(L8, FIND("(", L8)-1)), J8*10*M8, 1000*M8), 1000*M8), "") | O8: =IF(AND(M8<>"",M8<>0),N8/$N$505, "") | P8: =IF(AND(M8<>"", M8<>0), F8*1000/100, "") | Q8: =IF(AND(M8<>"", M8<>0), NOW(), "") | R8: =IF(AND(M8<>"", M8<>0), ROUND((G8 - Q8)/365, 0), "") | S8: =IF(AND(M8<>"",M8<>0),MDURATION(Q8,G8,F8/100,K8/100,2), "") | T8: =IF(AND(M8<>"",M8<>0),YIELD(Q8,G8,F8/100,N8/(M8*10),100,2),"") | U8: =IF(AND(M8<>"",M8<>0), IF(E8 = "Muni", T8, IF(E8="Corp", T8*(1 -'Investor Input'!$C$4-'Investor Input'!$C$5), T8*(1 -'Investor Input'!$C$4))), T8) | V8: =IF(AND(M8<>"",M8<>0),(FV(K8/(2*100),(G8-Q8)*2/365, F8*1000/(2*100), -N8/M8))*M8, "") | W8: =IF(AND(M8<>"",M8<>0),V8-N8,"") | X8: =IF(AND(M8<>"",M8<>0),W8/N8,"") | Y8: =IF(AND(M8<>"", M8<>0), MONTH(G8), "") | Z8: =IF(AND(M8<>"", M8<>0), MONTH(EDATE(G8, 6)), "") | AA8: =IF(AND(M8<>"", M8<>0), F8*1000*M8/(100*2), "") | AB8: =IF(AND(AA8<>"",AA8<>0), IF(E8="Muni", AA8, IF(E8 = "Corp", (1-'Investor Input'!$C$4-'Investor Input'!$C$5)*AA8, (1-'Investor Input'!$C$4)*AA8)), AA8) | AC8: =IF(AND(M8<>"", M8<>0), H8, "") | AD8: =IF(AND(M8<>"", M8<>0), N8/$N$505*MATCH(AC8,'Misc Lists'!$K$2:$K$25,0), "") | AE8: =IF(AND(M8<>"", M8<>0), I8, "") | AF8: =IF(AND(M8<>"", M8<>0), N8/$N$505*MATCH(AE8,'Misc Lists'!$L$2:$L$25,0), "")
B9: 91282CGQ8 | C9: N/A | D9: UNITED STATES TREAS SER H-2030 4.00000% 02/28/2030 NTS NOTE | E9: Tres | F9: 4 | G9: 47542 | H9: AAA | I9: -- | J9: 98.475 | K9: 4.34 | L9: 3,000(200) | N9: =IF(AND(M9<>"", M9<>0), IF(L9 <> "N/A", IF(M9>=VALUE(LEFT(L9, FIND("(", L9)-1)), J9*10*M9, 1000*M9), 1000*M9), "") | O9: =IF(AND(M9<>"",M9<>0),N9/$N$505, "") | P9: =IF(AND(M9<>"", M9<>0), F9*1000/100, "") | Q9: =IF(AND(M9<>"", M9<>0), NOW(), "") | R9: =IF(AND(M9<>"", M9<>0), ROUND((G9 - Q9)/365, 0), "") | S9: =IF(AND(M9<>"",M9<>0),MDURATION(Q9,G9,F9/100,K9/100,2), "") | T9: =IF(AND(M9<>"",M9<>0),YIELD(Q9,G9,F9/100,N9/(M9*10),100,2),"") | U9: =IF(AND(M9<>"",M9<>0), IF(E9 = "Muni", T9, IF(E9="Corp", T9*(1 -'Investor Input'!$C$4-'Investor Input'!$C$5), T9*(1 -'Investor Input'!$C$4))), T9) | V9: =IF(AND(M9<>"",M9<>0),(FV(K9/(2*100),(G9-Q9)*2/365, F9*1000/(2*100), -N9/M9))*M9, "") | W9: =IF(AND(M9<>"",M9<>0),V9-N9,"") | X9: =IF(AND(M9<>"",M9<>0),W9/N9,"") | Y9: =IF(AND(M9<>"", M9<>0), MONTH(G9), "") | Z9: =IF(AND(M9<>"", M9<>0), MONTH(EDATE(G9, 6)), "") | AA9: =IF(AND(M9<>"", M9<>0), F9*1000*M9/(100*2), "") | AB9: =IF(AND(AA9<>"",AA9<>0), IF(E9="Muni", AA9, IF(E9 = "Corp", (1-'Investor Input'!$C$4-'Investor Input'!$C$5)*AA9, (1-'Investor Input'!$C$4)*AA9)), AA9) | AC9: =IF(AND(M9<>"", M9<>0), H9, "") | AD9: =IF(AND(M9<>"", M9<>0), N9/$N$505*MATCH(AC9,'Misc Lists'!$K$2:$K$25,0), "") | AE9: =IF(AND(M9<>"", M9<>0), I9, "") | AF9: =IF(AND(M9<>"", M9<>0), N9/$N$505*MATCH(AE9,'Misc Lists'!$L$2:$L$25,0), "")
B10: 9128284Z0 | C10: N/A | D10: UNITED STATES TREAS SER P-2025 2.75000% 08/31/2025 NTS NOTE | E10: Tres | F10: 2.75 | G10: 45900 | H10: AAA | I10: -- | J10: 99.18 | K10: 4.337 | L10: 30,000(600) | N10: =IF(AND(M10<>"", M10<>0), IF(L10 <> "N/A", IF(M10>=VALUE(LEFT(L10, FIND("(", L10)-1)), J10*10*M10, 1000*M10), 1000*M10), "") | O10: =IF(AND(M10<>"",M10<>0),N10/$N$505, "") | P10: =IF(AND(M10<>"", M10<>0), F10*1000/100, "") | Q10: =IF(AND(M10<>"", M10<>0), NOW(), "") | R10: =IF(AND(M10<>"", M10<>0), ROUND((G10 - Q10)/365, 0), "") | S10: =IF(AND(M10<>"",M10<>0),MDURATION(Q10,G10,F10/100,K10/100,2), "") | T10: =IF(AND(M10<>"",M10<>0),YIELD(Q10,G10,F10/100,N10/(M10*10),100,2),"") | U10: =IF(AND(M10<>"",M10<>0), IF(E10 = "Muni", T10, IF(E10="Corp", T10*(1 -'Investor Input'!$C$4-'Investor Input'!$C$5), T10*(1 -'Investor Input'!$C$4))), T10) | V10: =IF(AND(M10<>"",M10<>0),(FV(K10/(2*100),(G10-Q10)*2/365, F10*1000/(2*100), -N10/M10))*M10, "") | W10: =IF(AND(M10<>"",M10<>0),V10-N10,"") | X10: =IF(AND(M10<>"",M10<>0),W10/N10,"") | Y10: =IF(AND(M10<>"", M10<>0), MONTH(G10), "") | Z10: =IF(AND(M10<>"", M10<>0), MONTH(EDATE(G10, 6)), "") | AA10: =IF(AND(M10<>"", M10<>0), F10*1000*M10/(100*2), "") | AB10: =IF(AND(AA10<>"",AA10<>0), IF(E10="Muni", AA10, IF(E10 = "Corp", (1-'Investor Input'!$C$4-'Investor Input'!$C$5)*AA10, (1-'Investor Input'!$C$4)*AA10)), AA10) | AC10: =IF(AND(M10<>"", M10<>0), H10, "") | AD10: =IF(AND(M10<>"", M10<>0), N10/$N$505*MATCH(AC10,'Misc Lists'!$K$2:$K$25,0), "") | AE10: =IF(AND(M10<>"", M10<>0), I10, "") | AF10: =IF(AND(M10<>"", M10<>0), N10/$N$505*MATCH(AE10,'Misc Lists'!$L$2:$L$25,0), "")
B11: 91282CFY2 | C11: N/A | D11: UNITED STATES TREAS SER S-2029 3.87500% 11/30/2029 NTS NOTE | E11: Tres | F11: 3.875 | G11: 47452 | H11: AAA | I11: -- | J11: 98.028 | K11: 4.335 | L11: 65,000(400) | N11: =IF(AND(M11<>"", M11<>0), IF(L11 <> "N/A", IF(M11>=VALUE(LEFT(L11, FIND("(", L11)-1)), J11*10*M11, 1000*M11), 1000*M11), "") | O11: =IF(AND(M11<>"",M11<>0),N11/$N$505, "") | P11: =IF(AND(M11<>"", M11<>0), F11*1000/100, "") | Q11: =IF(AND(M11<>"", M11<>0), NOW(), "") | R11: =IF(AND(M11<>"", M11<>0), ROUND((G11 - Q11)/365, 0), "") | S11: =IF(AND(M11<>"",M11<>0),MDURATION(Q11,G11,F11/100,K11/100,2), "") | T11: =IF(AND(M11<>"",M11<>0),YIELD(Q11,G11,F11/100,N11/(M11*10),100,2),"") | U11: =IF(AND(M11<>"",M11<>0), IF(E11 = "Muni", T11, IF(E11="Corp", T11*(1 -'Investor Input'!$C$4-'Investor Input'!$C$5), T11*(1 -'Investor Input'!$C$4))), T11) | V11: =IF(AND(M11<>"",M11<>0),(FV(K11/(2*100),(G11-Q11)*2/365, F11*1000/(2*100), -N11/M11))*M11, "") | W11: =IF(AND(M11<>"",M11<>0),V11-N11,"") | X11: =IF(AND(M11<>"",M11<>0),W11/N11,"") | Y11: =IF(AND(M11<>"", M11<>0), MONTH(G11), "") | Z11: =IF(AND(M11<>"", M11<>0), MONTH(EDATE(G11, 6)), "") | AA11: =IF(AND(M11<>"", M11<>0), F11*1000*M11/(100*2), "") | AB11: =IF(AND(AA11<>"",AA11<>0), IF(E11="Muni", AA11, IF(E11 = "Corp", (1-'Investor Input'!$C$4-'Investor Input'!$C$5)*AA11, (1-'Investor Input'!$C$4)*AA11)), AA11) | AC11: =IF(AND(M11<>"", M11<>0), H11, "") | AD11: =IF(AND(M11<>"", M11<>0), N11/$N$505*MATCH(AC11,'Misc Lists'!$K$2:$K$25,0), "") | AE11: =IF(AND(M11<>"", M11<>0), I11, "") | AF11: =IF(AND(M11<>"", M11<>0), N11/$N$505*MATCH(AE11,'Misc Lists'!$L$2:$L$25,0), "")
B12: 912828Z94 | C12: N/A | D12: UNITED STATES TREAS NTS NOTE 1.50000% 02/15/2030 | E12: Tres | F12: 1.5 | G12: 47529 | H12: AAA | I12: NR | J12: 87.404 | K12: 4.333 | L12: 3,000(200) | N12: =IF(AND(M12<>"", M12<>0), IF(L12 <> "N/A", IF(M12>=VALUE(LEFT(L12, FIND("(", L12)-1)), J12*10*M12, 1000*M12), 1000*M12), "") | O12: =IF(AND(M12<>"",M12<>0),N12/$N$505, "") | P12: =IF(AND(M12<>"", M12<>0), F12*1000/100, "") | Q12: =IF(AND(M12<>"", M12<>0), NOW(), "") | R12: =IF(AND(M12<>"", M12<>0), ROUND((G12 - Q12)/365, 0), "") | S12: =IF(AND(M12<>"",M12<>0),MDURATION(Q12,G12,F12/100,K12/100,2), "") | T12: =IF(AND(M12<>"",M12<>0),YIELD(Q12,G12,F12/100,N12/(M12*10),100,2),"") | U12: =IF(AND(M12<>"",M12<>0), IF(E12 = "Muni", T12, IF(E12="Corp", T12*(1 -'Investor Input'!$C$4-'Investor Input'!$C$5), T12*(1 -'Investor Input'!$C$4))), T12) | V12: =IF(AND(M12<>"",M12<>0),(FV(K12/(2*100),(G12-Q12)*2/365, F12*1000/(2*100), -N12/M12))*M12, "") | W12: =IF(AND(M12<>"",M12<>0),V12-N12,"") | X12: =IF(AND(M12<>"",M12<>0),W12/N12,"") | Y12: =IF(AND(M12<>"", M12<>0), MONTH(G12), "") | Z12: =IF(AND(M12<>"", M12<>0), MONTH(EDATE(G12, 6)), "") | AA12: =IF(AND(M12<>"", M12<>0), F12*1000*M12/(100*2), "") | AB12: =IF(AND(AA12<>"",AA12<>0), IF(E12="Muni", AA12, IF(E12 = "Corp", (1-'Investor Input'!$C$4-'Investor Input'!$C$5)*AA12, (1-'Investor Input'!$C$4)*AA12)), AA12) | AC12: =IF(AND(M12<>"", M12<>0), H12, "") | AD12: =IF(AND(M12<>"", M12<>0), N12/$N$505*MATCH(AC12,'Misc Lists'!$K$2:$K$25,0), "") | AE12: =IF(AND(M12<>"", M12<>0), I12, "") | AF12: =IF(AND(M12<>"", M12<>0), N12/$N$505*MATCH(AE12,'Misc Lists'!$L$2:$L$25,0), "")
B13: 91282CFT3 | C13: N/A | D13: UNITED STATES TREAS SER R-2029 4.00000% 10/31/2029 NTS NOTE | E13: Tres | F13: 4 | G13: 47422 | H13: AAA | I13: -- | J13: 98.598 | K13: 4.332 | L13: 65,000(400) | N13: =IF(AND(M13<>"", M13<>0), IF(L13 <> "N/A", IF(M13>=VALUE(LEFT(L13, FIND("(", L13)-1)), J13*10*M13, 1000*M13), 1000*M13), "") | O13: =IF(AND(M13<>"",M13<>0),N13/$N$505, "") | P13: =IF(AND(M13<>"", M13<>0), F13*1000/100, "") | Q13: =IF(AND(M13<>"", M13<>0), NOW(), "") | R13: =IF(AND(M13<>"", M13<>0), ROUND((G13 - Q13)/365, 0), "") | S13: =IF(AND(M13<>"",M13<>0),MDURATION(Q13,G13,F13/100,K13/100,2), "") | T13: =IF(AND(M13<>"",M13<>0),YIELD(Q13,G13,F13/100,N13/(M13*10),100,2),"") | U13: =IF(AND(M13<>"",M13<>0), IF(E13 = "Muni", T13, IF(E13="Corp", T13*(1 -'Investor Input'!$C$4-'Investor Input'!$C$5), T13*(1 -'Investor Input'!$C$4))), T13) | V13: =IF(AND(M13<>"",M13<>0),(FV(K13/(2*100),(G13-Q13)*2/365, F13*1000/(2*100), -N13/M13))*M13, "") | W13: =IF(AND(M13<>"",M13<>0),V13-N13,"") | X13: =IF(AND(M13<>"",M13<>0),W13/N13,"") | Y13: =IF(AND(M13<>"", M13<>0), MONTH(G13), "") | Z13: =IF(AND(M13<>"", M13<>0), MONTH(EDATE(G13, 6)), "") | AA13: =IF(AND(M13<>"", M13<>0), F13*1000*M13/(100*2), "") | AB13: =IF(AND(AA13<>"",AA13<>0), IF(E13="Muni", AA13, IF(E13 = "Corp", (1-'Investor Input'!$C$4-'Investor Input'!$C$5)*AA13, (1-'Investor Input'!$C$4)*AA13)), AA13) | AC13: =IF(AND(M13<>"", M13<>0), H13, "") | AD13: =IF(AND(M13<>"", M13<>0), N13/$N$505*MATCH(AC13,'Misc Lists'!$K$2:$K$25,0), "") | AE13: =IF(AND(M13<>"", M13<>0), I13, "") | AF13: =IF(AND(M13<>"", M13<>0), N13/$N$505*MATCH(AE13,'Misc Lists'!$L$2:$L$25,0), "")
B14: 91282CFL0 | C14: N/A | D14: UNITED STATES TREAS SER Q-2029 3.87500% 09/30/2029 NTS NOTE | E14: Tres | F14: 3.875 | G14: 47391 | H14: AAA | I14: -- | J14: 98.106 | K14: 4.331 | L14: 65,000(400) | N14: =IF(AND(M14<>"", M14<>0), IF(L14 <> "N/A", IF(M14>=VALUE(LEFT(L14, FIND("(", L14)-1)), J14*10*M14, 1000*M14), 1000*M14), "") | O14: =IF(AND(M14<>"",M14<>0),N14/$N$505, "") | P14: =IF(AND(M14<>"", M14<>0), F14*1000/100, "") | Q14: =IF(AND(M14<>"", M14<>0), NOW(), "") | R14: =IF(AND(M14<>"", M14<>0), ROUND((G14 - Q14)/365, 0), "") | S14: =IF(AND(M14<>"",M14<>0),MDURATION(Q14,G14,F14/100,K14/100,2), "") | T14: =IF(AND(M14<>"",M14<>0),YIELD(Q14,G14,F14/100,N14/(M14*10),100,2),"") | U14: =IF(AND(M14<>"",M14<>0), IF(E14 = "Muni", T14, IF(E14="Corp", T14*(1 -'Investor Input'!$C$4-'Investor Input'!$C$5), T14*(1 -'Investor Input'!$C$4))), T14) | V14: =IF(AND(M14<>"",M14<>0),(FV(K14/(2*100),(G14-Q14)*2/365, F14*1000/(2*100), -N14/M14))*M14, "") | W14: =IF(AND(M14<>"",M14<>0),V14-N14,"") | X14: =IF(AND(M14<>"",M14<>0),W14/N14,"") | Y14: =IF(AND(M14<>"", M14<>0), MONTH(G14), "") | Z14: =IF(AND(M14<>"", M14<>0), MONTH(EDATE(G14, 6)), "") | AA14: =IF(AND(M14<>"", M14<>0), F14*1000*M14/(100*2), "") | AB14: =IF(AND(AA14<>"",AA14<>0), IF(E14="Muni", AA14, IF(E14 = "Corp", (1-'Investor Input'!$C$4-'Investor Input'!$C$5)*AA14, (1-'Investor Input'!$C$4)*AA14)), AA14) | AC14: =IF(AND(M14<>"", M14<>0), H14, "") | AD14: =IF(AND(M14<>"", M14<>0), N14/$N$505*MATCH(AC14,'Misc Lists'!$K$2:$K$25,0), "") | AE14: =IF(AND(M14<>"", M14<>0), I14, "") | AF14: =IF(AND(M14<>"", M14<>0), N14/$N$505*MATCH(AE14,'Misc Lists'!$L$2:$L$25,0), "")
B15: 91282CMD0 | C15: N/A | D15: UNITED STATES TREAS SER AH-2029 4.37500% 12/31/2029 NTS NOTE | E15: Tres | F15: 4.375 | G15: 47483 | H15: AAA | I15: -- | J15: 100.188 | K15: 4.33 | L15: 65,000(400) | N15: =IF(AND(M15<>"", M15<>0), IF(L15 <> "N/A", IF(M15>=VALUE(LEFT(L15, FIND("(", L15)-1)), J15*10*M15, 1000*M15), 1000*M15), "") | O15: =IF(AND(M15<>"",M15<>0),N15/$N$505, "") | P15: =IF(AND(M15<>"", M15<>0), F15*1000/100, "") | Q15: =IF(AND(M15<>"", M15<>0), NOW(), "") | R15: =IF(AND(M15<>"", M15<>0), ROUND((G15 - Q15)/365, 0), "") | S15: =IF(AND(M15<>"",M15<>0),MDURATION(Q15,G15,F15/100,K15/100,2), "") | T15: =IF(AND(M15<>"",M15<>0),YIELD(Q15,G15,F15/100,N15/(M15*10),100,2),"") | U15: =IF(AND(M15<>"",M15<>0), IF(E15 = "Muni", T15, IF(E15="Corp", T15*(1 -'Investor Input'!$C$4-'Investor Input'!$C$5), T15*(1 -'Investor Input'!$C$4))), T15) | V15: =IF(AND(M15<>"",M15<>0),(FV(K15/(2*100),(G15-Q15)*2/365, F15*1000/(2*100), -N15/M15))*M15, "") | W15: =IF(AND(M15<>"",M15<>0),V15-N15,"") | X15: =IF(AND(M15<>"",M15<>0),W15/N15,"") | Y15: =IF(AND(M15<>"", M15<>0), MONTH(G15), "") | Z15: =IF(AND(M15<>"", M15<>0), MONTH(EDATE(G15, 6)), "") | AA15: =IF(AND(M15<>"", M15<>0), F15*1000*M15/(100*2), "") | AB15: =IF(AND(AA15<>"",AA15<>0), IF(E15="Muni", AA15, IF(E15 = "Corp", (1-'Investor Input'!$C$4-'Investor Input'!$C$5)*AA15, (1-'Investor Input'!$C$4)*AA15)), AA15) | AC15: =IF(AND(M15<>"", M15<>0), H15, "") | AD15: =IF(AND(M15<>"", M15<>0), N15/$N$505*MATCH(AC15,'Misc Lists'!$K$2:$K$25,0), "") | AE15: =IF(AND(M15<>"", M15<>0), I15, "") | AF15: =IF(AND(M15<>"", M15<>0), N15/$N$505*MATCH(AE15,'Misc Lists'!$L$2:$L$25,0), "")
B16: 91282CLN9 | C16: N/A | D16: UNITED STATES TREAS SER AD-2029 3.50000% 09/30/2029 NTS NOTE | E16: Tres | F16: 3.5 | G16: 47391 | H16: AAA | I16: -- | J16: 96.563 | K16: 4.329 | L16: 65,000(400) | N16: =IF(AND(M16<>"", M16<>0), IF(L16 <> "N/A", IF(M16>=VALUE(LEFT(L16, FIND("(", L16)-1)), J16*10*M16, 1000*M16), 1000*M16), "") | O16: =IF(AND(M16<>"",M16<>0),N16/$N$505, "") | P16: =IF(AND(M16<>"", M16<>0), F16*1000/100, "") | Q16: =IF(AND(M16<>"", M16<>0), NOW(), "") | R16: =IF(AND(M16<>"", M16<>0), ROUND((G16 - Q16)/365, 0), "") | S16: =IF(AND(M16<>"",M16<>0),MDURATION(Q16,G16,F16/100,K16/100,2), "") | T16: =IF(AND(M16<>"",M16<>0),YIELD(Q16,G16,F16/100,N16/(M16*10),100,2),"") | U16: =IF(AND(M16<>"",M16<>0), IF(E16 = "Muni", T16, IF(E16="Corp", T16*(1 -'Investor Input'!$C$4-'Investor Input'!$C$5), T16*(1 -'Investor Input'!$C$4))), T16) | V16: =IF(AND(M16<>"",M16<>0),(FV(K16/(2*100),(G16-Q16)*2/365, F16*1000/(2*100), -N16/M16))*M16, "") | W16: =IF(AND(M16<>"",M16<>0),V16-N16,"") | X16: =IF(AND(M16<>"",M16<>0),W16/N16,"") | Y16: =IF(AND(M16<>"", M16<>0), MONTH(G16), "") | Z16: =IF(AND(M16<>"", M16<>0), MONTH(EDATE(G16, 6)), "") | AA16: =IF(AND(M16<>"", M16<>0), F16*1000*M16/(100*2), "") | AB16: =IF(AND(AA16<>"",AA16<>0), IF(E16="Muni", AA16, IF(E16 = "Corp", (1-'Investor Input'!$C$4-'Investor Input'!$C$5)*AA16, (1-'Investor Input'!$C$4)*AA16)), AA16) | AC16: =IF(AND(M16<>"", M16<>0), H16, "") | AD16: =IF(AND(M16<>"", M16<>0), N16/$N$505*MATCH(AC16,'Misc Lists'!$K$2:$K$25,0), "") | AE16: =IF(AND(M16<>"", M16<>0), I16, "") | AF16: =IF(AND(M16<>"", M16<>0), N16/$N$505*MATCH(AE16,'Misc Lists'!$L$2:$L$25,0), "")
... B71: 91282CKB6 | C71: N/A | D71: UNITED STATES TREAS SER AY-2026 4.62500% 02/28/2026 NTS NOTE | E71: Tres | F71: 4.625 | G71: 46081 | H71: AAA | I71: -- | J71: 100.34 | K71: 4.282 | L71: 29,024(400) | N71: =IF(AND(M71<>"", M71<>0), IF(L71 <> "N/A", IF(M71>=VALUE(LEFT(L71, FIND("(", L71)-1)), J71*10*M71, 1000*M71), 1000*M71), "") | O71: =IF(AND(M71<>"",M71<>0),N71/$N$505, "") | P71: =IF(AND(M71<>"", M71<>0), F71*1000/100, "") | Q71: =IF(AND(M71<>"", M71<>0), NOW(), "") | R71: =IF(AND(M71<>"", M71<>0), ROUND((G71 - Q71)/365, 0), "") | S71: =IF(AND(M71<>"",M71<>0),MDURATION(Q71,G71,F71/100,K71/100,2), "") | T71: =IF(AND(M71<>"",M71<>0),YIELD(Q71,G71,F71/100,N71/(M71*10),100,2),"") | U71: =IF(AND(M71<>"",M71<>0), IF(E71 = "Muni", T71, IF(E71="Corp", T71*(1 -'Investor Input'!$C$4-'Investor Input'!$C$5), T71*(1 -'Investor Input'!$C$4))), T71) | V71: =IF(AND(M71<>"",M71<>0),(FV(K71/(2*100),(G71-Q71)*2/365, F71*1000/(2*100), -N71/M71))*M71, "") | W71: =IF(AND(M71<>"",M71<>0),V71-N71,"") | X71: =IF(AND(M71<>"",M71<>0),W71/N71,"") | Y71: =IF(AND(M71<>"", M71<>0), MONTH(G71), "") | Z71: =IF(AND(M71<>"", M71<>0), MONTH(EDATE(G71, 6)), "") | AA71: =IF(AND(M71<>"", M71<>0), F71*1000*M71/(100*2), "") | AB71: =IF(AND(AA71<>"",AA71<>0), IF(E71="Muni", AA71, IF(E71 = "Corp", (1-'Investor Input'!$C$4-'Investor Input'!$C$5)*AA71, (1-'Investor Input'!$C$4)*AA71)), AA71) | AC71: =IF(AND(M71<>"", M71<>0), H71, "") | AD71: =IF(AND(M71<>"", M71<>0), N71/$N$505*MATCH(AC71,'Misc Lists'!$K$2:$K$25,0), "") | AE71: =IF(AND(M71<>"", M71<>0), I71, "") | AF71: =IF(AND(M71<>"", M71<>0), N71/$N$505*MATCH(AE71,'Misc Lists'!$L$2:$L$25,0), "")
B72: 91282CHE4 | C72: N/A | D72: UNITED STATES TREAS SER Z-2028 3.62500% 05/31/2028 NTS NOTE | E72: Tres | F72: 3.625 | G72: 46904 | H72: AAA | I72: -- | J72: 98.005 | K72: 4.282 | L72: 65,000(400) | M72: 200 | N72: =IF(AND(M72<>"", M72<>0), IF(L72 <> "N/A", IF(M72>=VALUE(LEFT(L72, FIND("(", L72)-1)), J72*10*M72, 1000*M72), 1000*M72), "") -> 200000 | O72: =IF(AND(M72<>"",M72<>0),N72/$N$505, "") -> 0.19850629 | P72: =IF(AND(M72<>"", M72<>0), F72*1000/100, "") -> 36.25 | Q72: =IF(AND(M72<>"", M72<>0), NOW(), "") -> 45791.491 | R72: =IF(AND(M72<>"", M72<>0), ROUND((G72 - Q72)/365, 0), "") -> 3 | S72: =IF(AND(M72<>"",M72<>0),MDURATION(Q72,G72,F72/100,K72/100,2), "") -> 2.8006465 | T72: =IF(AND(M72<>"",M72<>0),YIELD(Q72,G72,F72/100,N72/(M72*10),100,2),"") -> 0.036245376 | U72: =IF(AND(M72<>"",M72<>0), IF(E72 = "Muni", T72, IF(E72="Corp", T72*(1 -'Investor Input'!$C$4-'Investor Input'!$C$5), T72*(1 -'Investor Input'!$C$4))), T72) -> 0.022834587 | V72: =IF(AND(M72<>"",M72<>0),(FV(K72/(2*100),(G72-Q72)*2/365, F72*1000/(2*100), -N72/M72))*M72, "") -> 204230.01 | W72: =IF(AND(M72<>"",M72<>0),V72-N72,"") -> 4230.0069 | X72: =IF(AND(M72<>"",M72<>0),W72/N72,"") -> 0.021150035 | Y72: =IF(AND(M72<>"", M72<>0), MONTH(G72), "") -> 5 | Z72: =IF(AND(M72<>"", M72<>0), MONTH(EDATE(G72, 6)), "") -> 11 | AA72: =IF(AND(M72<>"", M72<>0), F72*1000*M72/(100*2), "") -> 3625 | AB72: =IF(AND(AA72<>"",AA72<>0), IF(E72="Muni", AA72, IF(E72 = "Corp", (1-'Investor Input'!$C$4-'Investor Input'!$C$5)*AA72, (1-'Investor Input'!$C$4)*AA72)), AA72) -> 2283.75 | AC72: =IF(AND(M72<>"", M72<>0), H72, "") -> AAA | AD72: =IF(AND(M72<>"", M72<>0), N72/$N$505*MATCH(AC72,'Misc Lists'!$K$2:$K$25,0), "") -> 0.39701258 | AE72: =IF(AND(M72<>"", M72<>0), I72, "") -> -- | AF72: =IF(AND(M72<>"", M72<>0), N72/$N$505*MATCH(AE72,'Misc Lists'!$L$2:$L$25,0), "") -> 4.5656447
B73: 9128283W8 | C73: N/A | D73: UNITED STATES TREAS NOTES 2.75000% 02/15/2028 | E73: Tres | F73: 2.75 | G73: 46798 | H73: AAA | I73: -- | J73: 95.743 | K73: 4.281 | L73: 65,000(400) | N73: =IF(AND(M73<>"", M73<>0), IF(L73 <> "N/A", IF(M73>=VALUE(LEFT(L73, FIND("(", L73)-1)), J73*10*M73, 1000*M73), 1000*M73), "") | O73: =IF(AND(M73<>"",M73<>0),N73/$N$505, "") | P73: =IF(AND(M73<>"", M73<>0), F73*1000/100, "") | Q73: =IF(AND(M73<>"", M73<>0), NOW(), "") | R73: =IF(AND(M73<>"", M73<>0), ROUND((G73 - Q73)/365, 0), "") | S73: =IF(AND(M73<>"",M73<>0),MDURATION(Q73,G73,F73/100,K73/100,2), "") | T73: =IF(AND(M73<>"",M73<>0),YIELD(Q73,G73,F73/100,N73/(M73*10),100,2),"") | U73: =IF(AND(M73<>"",M73<>0), IF(E73 = "Muni", T73, IF(E73="Corp", T73*(1 -'Investor Input'!$C$4-'Investor Input'!$C$5), T73*(1 -'Investor Input'!$C$4))), T73) | V73: =IF(AND(M73<>"",M73<>0),(FV(K73/(2*100),(G73-Q73)*2/365, F73*1000/(2*100), -N73/M73))*M73, "") | W73: =IF(AND(M73<>"",M73<>0),V73-N73,"") | X73: =IF(AND(M73<>"",M73<>0),W73/N73,"") | Y73: =IF(AND(M73<>"", M73<>0), MONTH(G73), "") | Z73: =IF(AND(M73<>"", M73<>0), MONTH(EDATE(G73, 6)), "") | AA73: =IF(AND(M73<>"", M73<>0), F73*1000*M73/(100*2), "") | AB73: =IF(AND(AA73<>"",AA73<>0), IF(E73="Muni", AA73, IF(E73 = "Corp", (1-'Investor Input'!$C$4-'Investor Input'!$C$5)*AA73, (1-'Investor Input'!$C$4)*AA73)), AA73) | AC73: =IF(AND(M73<>"", M73<>0), H73, "") | AD73: =IF(AND(M73<>"", M73<>0), N73/$N$505*MATCH(AC73,'Misc Lists'!$K$2:$K$25,0), "") | AE73: =IF(AND(M73<>"", M73<>0), I73, "") | AF73: =IF(AND(M73<>"", M73<>0), N73/$N$505*MATCH(AE73,'Misc Lists'!$L$2:$L$25,0), "")
B74: 912828YB0 | C74: N/A | D74: UNITED STATES TREAS SER E-2029 1.62500% 08/15/2029 NTS NOTE | E74: Tres | F74: 1.625 | G74: 47345 | H74: AAA | I74: -- | J74: 89.248 | K74: 4.281 | L74: 1,200(200) | M74: 200 | N74: =IF(AND(M74<>"", M74<>0), IF(L74 <> "N/A", IF(M74>=VALUE(LEFT(L74, FIND("(", L74)-1)), J74*10*M74, 1000*M74), 1000*M74), "") -> 200000 | O74: =IF(AND(M74<>"",M74<>0),N74/$N$505, "") -> 0.19850629 | P74: =IF(AND(M74<>"", M74<>0), F74*1000/100, "") -> 16.25 | Q74: =IF(AND(M74<>"", M74<>0), NOW(), "") -> 45791.491 | R74: =IF(AND(M74<>"", M74<>0), ROUND((G74 - Q74)/365, 0), "") -> 4 | S74: =IF(AND(M74<>"",M74<>0),MDURATION(Q74,G74,F74/100,K74/100,2), "") -> 4.0140006 | T74: =IF(AND(M74<>"",M74<>0),YIELD(Q74,G74,F74/100,N74/(M74*10),100,2),"") -> 0.016247993 | U74: =IF(AND(M74<>"",M74<>0), IF(E74 = "Muni", T74, IF(E74="Corp", T74*(1 -'Investor Input'!$C$4-'Investor Input'!$C$5), T74*(1 -'Investor Input'!$C$4))), T74) -> 0.010236235 | V74: =IF(AND(M74<>"",M74<>0),(FV(K74/(2*100),(G74-Q74)*2/365, F74*1000/(2*100), -N74/M74))*M74, "") -> 224513.66 | W74: =IF(AND(M74<>"",M74<>0),V74-N74,"") -> 24513.656 | X74: =IF(AND(M74<>"",M74<>0),W74/N74,"") -> 0.12256828 | Y74: =IF(AND(M74<>"", M74<>0), MONTH(G74), "") -> 8 | Z74: =IF(AND(M74<>"", M74<>0), MONTH(EDATE(G74, 6)), "") -> 2 | AA74: =IF(AND(M74<>"", M74<>0), F74*1000*M74/(100*2), "") -> 1625 | AB74: =IF(AND(AA74<>"",AA74<>0), IF(E74="Muni", AA74, IF(E74 = "Corp", (1-'Investor Input'!$C$4-'Investor Input'!$C$5)*AA74, (1-'Investor Input'!$C$4)*AA74)), AA74) -> 1023.75 | AC74: =IF(AND(M74<>"", M74<>0), H74, "") -> AAA | AD74: =IF(AND(M74<>"", M74<>0), N74/$N$505*MATCH(AC74,'Misc Lists'!$K$2:$K$25,0), "") -> 0.39701258 | AE74: =IF(AND(M74<>"", M74<>0), I74, "") -> -- | AF74: =IF(AND(M74<>"", M74<>0), N74/$N$505*MATCH(AE74,'Misc Lists'!$L$2:$L$25,0), "") -> 4.5656447
B75: 91282CHD6 | C75: N/A | D75: UNITED STATES TREAS SER BC-2025 4.25000% 05/31/2025 NTS NOTE | E75: Tres | F75: 4.25 | G75: 45808 | H75: AAA | I75: -- | J75: 99.981 | K75: 4.28 | L75: 30,000(600) | N75: =IF(AND(M75<>"", M75<>0), IF(L75 <> "N/A", IF(M75>=VALUE(LEFT(L75, FIND("(", L75)-1)), J75*10*M75, 1000*M75), 1000*M75), "") | O75: =IF(AND(M75<>"",M75<>0),N75/$N$505, "") | P75: =IF(AND(M75<>"", M75<>0), F75*1000/100, "") | Q75: =IF(AND(M75<>"", M75<>0), NOW(), "") | R75: =IF(AND(M75<>"", M75<>0), ROUND((G75 - Q75)/365, 0), "") | S75: =IF(AND(M75<>"",M75<>0),MDURATION(Q75,G75,F75/100,K75/100,2), "") | T75: =IF(AND(M75<>"",M75<>0),YIELD(Q75,G75,F75/100,N75/(M75*10),100,2),"") | U75: =IF(AND(M75<>"",M75<>0), IF(E75 = "Muni", T75, IF(E75="Corp", T75*(1 -'Investor Input'!$C$4-'Investor Input'!$C$5), T75*(1 -'Investor Input'!$C$4))), T75) | V75: =IF(AND(M75<>"",M75<>0),(FV(K75/(2*100),(G75-Q75)*2/365, F75*1000/(2*100), -N75/M75))*M75, "") | W75: =IF(AND(M75<>"",M75<>0),V75-N75,"") | X75: =IF(AND(M75<>"",M75<>0),W75/N75,"") | Y75: =IF(AND(M75<>"", M75<>0), MONTH(G75), "") | Z75: =IF(AND(M75<>"", M75<>0), MONTH(EDATE(G75, 6)), "") | AA75: =IF(AND(M75<>"", M75<>0), F75*1000*M75/(100*2), "") | AB75: =IF(AND(AA75<>"",AA75<>0), IF(E75="Muni", AA75, IF(E75 = "Corp", (1-'Investor Input'!$C$4-'Investor Input'!$C$5)*AA75, (1-'Investor Input'!$C$4)*AA75)), AA75) | AC75: =IF(AND(M75<>"", M75<>0), H75, "") | AD75: =IF(AND(M75<>"", M75<>0), N75/$N$505*MATCH(AC75,'Misc Lists'!$K$2:$K$25,0), "") | AE75: =IF(AND(M75<>"", M75<>0), I75, "") | AF75: =IF(AND(M75<>"", M75<>0), N75/$N$505*MATCH(AE75,'Misc Lists'!$L$2:$L$25,0), "")
